Workbook
Name BILL1: 'Bill 1 Summary'!$B$5:$B$23
Name BINEY: 'Bill 1 Summary'!$B$4:$B$4
Name CC: Lists!$H$2:$H$12
Name PLACAT: Lists!$J$2:$J$85
Name UOM: Lists!$E$2:$E$20

Sheet Contract Summary
A1: CONTRACT SUMMARY | D1: Date: | E1: 45717 | G1: Week No: | H1: =VLOOKUP(E1,Lists!A2:C4383,2,FALSE) -> 9 | I1: Instructions
A2: CONTRACT DETAILS
A3: Client: | C3: Nurus-Siraj Nigeria Limited
A4: Name of Contract: | C4: PROPOSED CONSTRUCTION OF 15 SPAN, DUAL CARRIAGEWAY, 6TH BRIDGE OVER RIVER KADUNA AND APPROACH ROADS
A5: Short Name: | C5: 6TH BRIDGE OVER RIVER KADUNA
A6: Original Contract Amount: | C6: 4.6171489e+09 | D6: NAIRA
A7: Current Contract Amount: | C7: 4.6171489e+09 | D7: NAIRA | E7: RETC: | F7: No | J7: =C7-'BEME & Works Completed Fd'!J194 -> 4.6171489e+09 | L7: - Check to Detail Sheet
A8: Contract Schedules
A9: • | B9: Date of Contract Award | C9: 44149 | E9: • Works Actually Commenced on Site:
A10: • | B10: Contract Commencement Date: | C10: 44183
A11: • | B11: Original Contract Duration (Months): | C11: 12 | E11: • Duration Already on Site : | H11: =IF(H9=0,0,IF(ISBLANK(E$1),((E$1-H9)/(365/12)),(E$1-H9)/(365/12))) -> 0
A12: • | B12: Original Contract Completion Date: | C12: =ROUNDUP(C10+(365/12)*C11,0) -> 44548
A13: • | B13: Extension of Time Requested (Months): | C13: 0 | E13: =IF(H13>0,"• Remaining to Original Completion Date:","• Overdue to Original completion Date:") -> • Overdue to Original completion Date: | H13: =IF(C12=0,0,IF(ISBLANK(E$1),((C12-E$1)/(365/12)),(C12-E$1)/(365/12))) -> -38.432877
A14: • | B14: Extension of Time Granted (Months): | C14: 0
A15: • | B15: Revised Contract Duration (Months) | C15: =C11+C14 -> 12 | E15: =IF(H15>0,"• Remaining to Revised Completion Date:","• Overdue to Revised completion Date:") -> • Overdue to Revised completion Date: | H15: =IF(C16=0,0,IF(ISBLANK(E$1),((C16-E$1)/(365/12)),(C16-E$1)/(365/12))) -> -38.432877
A16: • | B16: Revised Completion Date: | C16: =ROUNDUP(C12+C14*(365/12),0) -> 44548
A18: VALUE OF WORKS TO DATE
A20: CLIENT POSITION (INCL. VAT) - CERTIFICATES
A21: • | B21: Works Vetted & Certified - Payable to Contractor: | C21: ='[1]Certificate Status'!Y39 -> 1.8799307e+09 | D21: =IF(C$7=0,0,C21/C$7) -> 0.40716268 | K21: =C21-'[1]Certificate Status'!Y39 -> 0 | L21: - Check to Detail Sheet
A22: • | B22: Works submitted and not yet vetted: | C22: ='[1]Certificate Status'!Y40 -> 0 | D22: =IF(C$7=0,0,C22/C$7) -> 0 | K22: =C22-'[1]Certificate Status'!Y40 -> 0 | L22: - Check to Detail Sheet
A23: • | B23: Total value of works submitted: | C23: =SUM(C21:C22) -> 1.8799307e+09 | D23: =IF(C$7=0,0,C23/C$7) -> 0.40716268
A24: • | B24: Add - Retention Money - Deducted | C24: ='[1]Certificate Status'!H35 -> 2.0318186e+08
A25: • | B25: Deduct - Retention Money - Released | C25: ='[1]Certificate Status'!J35 -> 0
A26: • | B26: Add -Total Advance Payment Recovered | C26: 0
A27: • | B27: Total Gross Value of Works Completed & Certified: | C27: =SUM(C23:C26) -> 2.0831126e+09 | D27: =IF(C$7=0,0,C27/C$7) -> 0.4511686 | F27: =C43-C27 -> #VALUE! | G27: =IF(F$27>0,"In Favour of PW","Negative Cash Position") -> #VALUE!
H28: =IF(F$27>0,"- Payments received less works certified"," - Payments Received less work Certified") -> #VALUE!
A29: PW POSITION (INCL. VAT) - WEEKLY PROGRESS REPORTS
A30: • | B30: Add - Bill 1 | C30: ='[1]Weekly Summary'!F9 -> 0
A31: • | B31: Permanent Works Completed | C31: ='[1]Weekly Summary'!F18 -> 10158750 | D31: =IF(C$7=0,0,C31/C$7) -> 0.0022002214
A32: • | B32: Add - Contingencies | C32: ='[1]Weekly Summary'!F22 -> 25372651
A33: • | B33: Total Value of Works Done | C33: =SUM(C30:C32) -> 35531401 | D33: =IF(C$7=0,0,C33/C$7) -> 0.0076955285 | F33: =C43-C33 -> #VALUE! | G33: =IF(F$33>0,"In Favour of PW","Negative Cash Position") -> #VALUE! | K33: =C33-'[1]BEME & Works Completed'!M178 -> 0 | L33: - Check to Detail Sheet
H34: =IF(F$33>0,"- Payments received less works completed"," - Payments Received less work Completed") -> #VALUE!
A35: Total Work in Progress | C35: =C33-C27 -> -2.0475812e+09 | D35: =IF(C35<0,"- Works Certified is greater than physical works Completed","") -> - Works Certified is greater than physical works Completed
A37: PAYMENT STATUS
A39: Payments Received to Date | C39: Gross | D39: Net Amount | F39: % Cont. Value
A40: Advance Payments | C40: =SUMIF('[1]Payments Recieved'!$C$5:$C$37,"Advance",'[1]Payments Recieved'!$D$5:$D$37) -> #VALUE! | D40: =SUMIF('[1]Payments Recieved'!$C$5:$C$37,"Advance",'[1]Payments Recieved'!$J$5:$J$37) -> #VALUE! | F40: =IF(C$7=0,0,C40/C$7) -> #VALUE!
A41: Certficates Paid | C41: =SUMIF('[1]Payments Recieved'!$C$5:$C$37,"Cert",'[1]Payments Recieved'!$D$5:$D$37) -> #VALUE! | D41: =SUMIF('[1]Payments Recieved'!$C$5:$C$37,"Cert",'[1]Payments Recieved'!$J$5:$J$37) -> #VALUE! | F41: =IF(C$7=0,0,C41/C$7) -> #VALUE!
A42: On Account | C42: =SUMIF('[1]Payments Recieved'!$C$5:$C$37,"On Account",'[1]Payments Recieved'!$D$5:$D$37) -> #VALUE! | D42: =SUMIF('[1]Payments Recieved'!$C$5:$C$37,"On Account",'[1]Payments Recieved'!$J$5:$J$37) -> #VALUE! | F42: =IF(C$7=0,0,C42/C$7) -> #VALUE!
A43: Total Payments Received | C43: =SUM(C40:C42) -> #VALUE! | D43: =SUM(D40:D42) -> #VALUE! | F43: =IF(C$7=0,0,C43/C$7) -> #VALUE! | K43: =C43-'[1]Payments Recieved'!D38 -> #VALUE! | L43: - Check to Detail Sheet
A45: Amounts Certified - Not Yet Paid | C45: =C23-SUM(C41:C42) -> #VALUE!
A47: Advance Payment Guarantee: | C47: 1500000000 | E47: APG Expiry: | F47: 43186 | G47: =IF(F47<TODAY(),"Days Expired:","Days to Expiry:") -> Days Expired: | H47: =F47-E1 -> -2531
A48: Advance Payment Recovered (on submitted Certs): | C48: 0 | D48: =IF(C40=0,0,C48/C40) -> #VALUE! | E48: Renewal Exp: | G48: =IF(ISBLANK(F48),"",IF(F48<TODAY(),"Days Expired:","Days to Expiry:")) | H48: =IF(ISBLANK(F48),"",F48-E1)
A49: Advance Payment yet to be recovered: | C49: =C47-C48 -> 1500000000 | D49: =IF(C40=0,0,C49/C40) -> #VALUE!
A51: BILL 1
A53: Total Bill 1 Requested by client to date: | C53: ='[1]Bill 1 Summary'!C24 -> 49933962 | D53: Total Amount Claimed in Certs: | G53: ='[1]Bill 1 Summary'!H24 -> 23453874
A54: Total Paid out by PW to date: | C54: ='[1]Bill 1 Summary'!D24 -> 43357962 | D54: Total Amount Paid by Client: | G54: ='[1]Bill 1 Summary'!J24 -> 0
A55: Amount Outstanding from Amounts Requested: | C55: =C53-C54 -> 6576000 | D55: Total Amount Outstanding to PW: | G55: =G53-G54 -> 23453874
A56: Note: All amounts are net of Service Charge: | D56: Amount rec'd by PW - not paid out: | G56: =G54-C54 -> -43357962
A58: COST & REVENUE SUMMARY
B60: Completed Works | C60: BEME | D60: Completed Previously | F60: This Week | G60: Project to Date | H60: % Compl.
B61: ='Weekly Summary'!A7 -> CONCRETE APRON WORK | C61: ='Weekly Summary'!C16 -> 4.2751379e+09 | D61: ='Weekly Summary'!D16 -> 1.3500779e+09 | F61: ='Weekly Summary'!E16 -> 24311509 | G61: ='Weekly Summary'!F16 -> 1.3743894e+09 | H61: =IF(C61=0,0,G61/C61) -> 0.32148423
B63: ='Weekly Summary'!A20 -> Total Contingency (Incl. VAT) | C63: ='Weekly Summary'!C20 -> 3.4201103e+08 | D63: ='Weekly Summary'!D20 -> 0 | F63: ='Weekly Summary'!E20 -> 0 | G63: ='Weekly Summary'!F20 -> 0 | H63: =IF(C63=0,0,G63/C63) -> 0
B64: Tota Completed Works to Date (Incl VAT) | C64: =SUM(C61:C63) -> 4.6171489e+09 | D64: =SUM(D61:D63) -> 1.3500779e+09 | F64: =SUM(F61:F63) -> 24311509 | G64: =SUM(G61:G63) -> 1.3743894e+09 | H64: =IF(C64=0,0,G64/C64) -> 0.29767058
B66: Total Costs to Date | D66: ='Weekly Summary'!D34 -> 1.0632881e+09 | F66: ='Weekly Summary'!E34 -> 18112042 | G66: ='Weekly Summary'!F34 -> 1.0814001e+09
A68: ='Weekly Summary'!A36 -> Net Earnings - Excluding Bill 1 | D68: =SUM(D61:E63)-D66 -> 2.8678983e+08 | F68: =SUM(F61:F63)-F66 -> 6199466.7 | G68: =SUM(G61:G63)-G66 -> 2.9298929e+08
A69: ='Weekly Summary'!A37 -> % Net Earnings | D69: =IF(SUM(D61:E63)=0,0,D68/SUM(D61:E63)) -> 0.21242465 | F69: =IF(SUM(F61:F63)=0,0,F68/SUM(F61:F63)) -> 0.25500131 | G69: =IF(SUM(G61:G63)=0,0,G68/SUM(G61:G63)) -> 0.21317779
A71: FINANCIAL INFORMATION
C73: Previous Week | D73: This Week | F73: Movement
A74: Creditors Balance | F74: =C74-D74 -> 0
A75: Bank & Cash Funds Available | F75: =C75-D75 -> 0

Sheet Weekly Summary
A1: WEEKLY WORK SUMMARY | D1: Date: | E1: ='Contract Summary'!E1 -> 45717 | F1: Week No: | G1: =IF(E1=0,0,VLOOKUP(E1,Lists!A2:B5000,2,FALSE)) -> 9 | H1: Instructions
A3: ='Contract Summary'!C4 -> PROPOSED CONSTRUCTION OF 15 SPAN, DUAL CARRIAGEWAY, 6TH BRIDGE OVER RIVER KADUNA AND APPROACH ROADS
A5: Works Completed | C5: BEME | D5: Completed Previously | E5: This Week | F5: Project to Date | G5: % Compl.
A7: CONCRETE APRON WORK
A8: • | B8: Bill 1 | C8: ='BEME & Works Completed Fd'!J24 -> 35500000 | D8: ='BEME & Works Completed Fd'!K24 -> 0 | E8: ='BEME & Works Completed Fd'!L24 -> 0 | F8: =D8+E8 -> 0 | G8: =IF(C8=0,0,F8/C8) -> 0
A9: • | B9: Excavation and Piling | C9: ='BEME & Works Completed Fd'!J36 -> 595098800 | D9: ='BEME & Works Completed Fd'!K36 -> 4.0044645e+08 | E9: ='BEME & Works Completed Fd'!L36 -> 0 | F9: =D9+E9 -> 4.0044645e+08 | G9: =IF(C9=0,0,F9/C9) -> 0.6729075
A10: • | B10: Pile cap, Pier, Pier caps and Abutment | C10: ='BEME & Works Completed Fd'!J55 -> 953352380 | D10: ='BEME & Works Completed Fd'!K55 -> 3.0485608e+08 | E10: ='BEME & Works Completed Fd'!L55 -> 4771872 | F10: =D10+E10 -> 3.0962796e+08 | G10: =IF(C10=0,0,F10/C10) -> 0.32477808
A11: • | B11: Superstructure | C11: ='BEME & Works Completed Fd'!J72 -> 2095531280 | D11: ='BEME & Works Completed Fd'!K72 -> 5.505839e+08 | E11: ='BEME & Works Completed Fd'!L72 -> 17843485 | F11: =D11+E11 -> 5.6842739e+08 | G11: =IF(C11=0,0,F11/C11) -> 0.27125693
A12: • | B12: Pavement | C12: ='BEME & Works Completed Fd'!J84 -> 0 | D12: ='BEME & Works Completed Fd'!K84 -> 0 | E12: ='BEME & Works Completed Fd'!L84 -> 0 | F12: =D12+E12 -> 0 | G12: =IF(C12=0,0,F12/C12) -> 0
A13: • | B13: Miscellanous | C13: ='BEME & Works Completed Fd'!J99 -> 297390000 | D13: ='BEME & Works Completed Fd'!K99 -> 0 | E13: ='BEME & Works Completed Fd'!L99 -> 0 | F13: =D13+E13 -> 0 | G13: =IF(C13=0,0,F13/C13) -> 0
A14: SUB-TOTAL | C14: =SUM(C8:C13) -> 3976872460 | D14: =SUM(D8:D13) -> 1.2558864e+09 | E14: =SUM(E8:E13) -> 22615357 | F14: =SUM(F8:F13) -> 1.2785018e+09 | G14: =IF(C14=0,0,F14/C14) -> 0.32148423
A15: ="Add VAT & State Levies - "&SUM(Lists!$M$4,'BEME & Works Completed Fd'!$C$243:$C$245)*100&"%" -> Add VAT & State Levies - 7.5% | C15: =C14*SUM(Lists!$M$4,'BEME & Works Completed Fd'!$C$243:$C$245) -> 2.9826543e+08 | D15: =D14*SUM(Lists!$M$4,'BEME & Works Completed Fd'!$C$243:$C$245) -> 94191482 | E15: =E14*SUM(Lists!$M$4,'BEME & Works Completed Fd'!$C$243:$C$245) -> 1696151.8 | F15: =F14*SUM(Lists!$M$4,'BEME & Works Completed Fd'!$C$243:$C$245) -> 95887634
A16: Total Works Completed (Incl. VAT) | C16: =SUM(C14:C15) -> 4.2751379e+09 | D16: =SUM(D14:D15) -> 1.3500779e+09 | E16: =SUM(E14:E15) -> 24311509 | F16: =SUM(F14:F15) -> 1.3743894e+09 | G16: =IF(C16=0,0,F16/C16) -> 0.32148423
A18: Contingency | C18: ='BEME & Works Completed Fd'!J126 -> 3.181498e+08 | D18: ='BEME & Works Completed Fd'!K126 -> 0 | E18: ='BEME & Works Completed Fd'!L126 -> 0 | F18: ='BEME & Works Completed Fd'!M126 -> 0 | G18: =IF(C18=0,0,F18/C18) -> 0
A19: ="Add VAT & State Levies - "&SUM(Lists!$M$4,'BEME & Works Completed Fd'!$C$243:$C$245)*100&"%" -> Add VAT & State Levies - 7.5% | C19: =C18*SUM(Lists!$M$4,'BEME & Works Completed Fd'!$C$243:$C$245) -> 23861235 | D19: =D18*SUM(Lists!$M$4,'BEME & Works Completed Fd'!$C$243:$C$245) -> 0 | E19: =E18*SUM(Lists!$M$4,'BEME & Works Completed Fd'!$C$243:$C$245) -> 0 | F19: =F18*SUM(Lists!$M$4,'BEME & Works Completed Fd'!$C$243:$C$245) -> 0
A20: Total Contingency (Incl. VAT) | C20: =SUM(C18:C19) -> 3.4201103e+08 | D20: =SUM(D18:D19) -> 0 | E20: =SUM(E18:E19) -> 0 | F20: =SUM(F18:F19) -> 0 | G20: =IF(C20=0,0,F20/C20) -> 0
A22: Total Works Completed (Incl. VAT) | C22: =C16+C20 -> 4.6171489e+09 | D22: =D16+D20 -> 1.3500779e+09 | E22: =E16+E20 -> 24311509 | F22: =F16+F20 -> 1.3743894e+09 | G22: =G16+G20 -> 0.32148423
A24: Costs to Date | D24: Completed Previously | E24: This Week | F24: Project to Date | G24: % of Total
A25: • | B25: =IF(ISBLANK(Lists!H2),"",Lists!H2) -> Plant | D25: =SUMIF('Cost Report'!$E$5:$E$85,'Weekly Summary'!$B25,'Cost Report'!$I$5:$I$85) -> 1.5772974e+08 | E25: =SUMIF('Cost Report'!$E$5:$E$85,'Weekly Summary'!$B25,'Cost Report'!$J$5:$J$85) -> 3269800 | F25: =SUMIF('Cost Report'!$E$5:$E$85,'Weekly Summary'!$B25,'Cost Report'!$K$5:$K$85) -> 1.6099954e+08 | G25: =IF(F$34=0,0,F25/F$34) -> 0.14888064
A26: • | B26: =IF(ISBLANK(Lists!H3),"",Lists!H3) -> AGO | D26: =SUMIF('Cost Report'!$E$5:$E$85,'Weekly Summary'!$B26,'Cost Report'!$I$5:$I$85) -> 177509365 | E26: =SUMIF('Cost Report'!$E$5:$E$85,'Weekly Summary'!$B26,'Cost Report'!$J$5:$J$85) -> 2412300 | F26: =SUMIF('Cost Report'!$E$5:$E$85,'Weekly Summary'!$B26,'Cost Report'!$K$5:$K$85) -> 179921665 | G26: =IF(F$34=0,0,F26/F$34) -> 0.16637844
A27: • | B27: =IF(ISBLANK(Lists!H4),"",Lists!H4) -> Materials | D27: =SUMIF('Cost Report'!$E$5:$E$85,'Weekly Summary'!$B27,'Cost Report'!$I$5:$I$85) -> 4.5978258e+08 | E27: =SUMIF('Cost Report'!$E$5:$E$85,'Weekly Summary'!$B27,'Cost Report'!$J$5:$J$85) -> 10452897 | F27: =SUMIF('Cost Report'!$E$5:$E$85,'Weekly Summary'!$B27,'Cost Report'!$K$5:$K$85) -> 4.7023547e+08 | G27: =IF(F$34=0,0,F27/F$34) -> 0.43483948
A28: • | B28: =IF(ISBLANK(Lists!H5),"",Lists!H5) -> Sub Contractors | D28: =SUMIF('Cost Report'!$E$5:$E$85,'Weekly Summary'!$B28,'Cost Report'!$I$5:$I$85) -> 34045601 | E28: =SUMIF('Cost Report'!$E$5:$E$85,'Weekly Summary'!$B28,'Cost Report'!$J$5:$J$85) -> 0 | F28: =SUMIF('Cost Report'!$E$5:$E$85,'Weekly Summary'!$B28,'Cost Report'!$K$5:$K$85) -> 34045601 | G28: =IF(F$34=0,0,F28/F$34) -> 0.03148289
A29: • | B29: =IF(ISBLANK(Lists!H6),"",Lists!H6) -> Local Labour | D29: =SUMIF('Cost Report'!$E$5:$E$85,'Weekly Summary'!$B29,'Cost Report'!$I$5:$I$85) -> 78887600 | E29: =SUMIF('Cost Report'!$E$5:$E$85,'Weekly Summary'!$B29,'Cost Report'!$J$5:$J$85) -> 1364500 | F29: =SUMIF('Cost Report'!$E$5:$E$85,'Weekly Summary'!$B29,'Cost Report'!$K$5:$K$85) -> 80252100 | G29: =IF(F$34=0,0,F29/F$34) -> 0.074211291
A30: • | B30: =IF(ISBLANK(Lists!H7),"",Lists!H7) -> Overheads | D30: =SUMIF('Cost Report'!$E$5:$E$85,'Weekly Summary'!$B30,'Cost Report'!$I$5:$I$85) -> 31000000 | E30: =SUMIF('Cost Report'!$E$5:$E$85,'Weekly Summary'!$B30,'Cost Report'!$J$5:$J$85) -> 0 | F30: =SUMIF('Cost Report'!$E$5:$E$85,'Weekly Summary'!$B30,'Cost Report'!$K$5:$K$85) -> 31000000 | G30: =IF(F$34=0,0,F30/F$34) -> 0.02866654
A31: • | B31: =IF(ISBLANK(Lists!H8),"",Lists!H8) -> Site Level Expenses | D31: =SUMIF('Cost Report'!$E$5:$E$85,'Weekly Summary'!$B31,'Cost Report'!$I$5:$I$85) -> 1.243332e+08 | E31: =SUMIF('Cost Report'!$E$5:$E$85,'Weekly Summary'!$B31,'Cost Report'!$J$5:$J$85) -> 612545.95 | F31: =SUMIF('Cost Report'!$E$5:$E$85,'Weekly Summary'!$B31,'Cost Report'!$K$5:$K$85) -> 1.2494575e+08 | G31: =IF(F$34=0,0,F31/F$34) -> 0.11554072
A32: • | B32: =IF(ISBLANK(Lists!H10),"",Lists!H10) | D32: =SUMIF('Cost Report'!$E$5:$E$85,'Weekly Summary'!$B32,'Cost Report'!$I$5:$I$85) -> 0 | E32: =SUMIF('Cost Report'!$E$5:$E$85,'Weekly Summary'!$B32,'Cost Report'!$J$5:$J$85) -> 0 | F32: =SUMIF('Cost Report'!$E$5:$E$85,'Weekly Summary'!$B32,'Cost Report'!$K$5:$K$85) -> 0
A33: • | B33: =IF(ISBLANK(Lists!H11),"",Lists!H11) | D33: =SUMIF('Cost Report'!$E$5:$E$85,'Weekly Summary'!$B33,'Cost Report'!$I$5:$I$85) -> 0 | E33: =SUMIF('Cost Report'!$E$5:$E$85,'Weekly Summary'!$B33,'Cost Report'!$J$5:$J$85) -> 0 | F33: =SUMIF('Cost Report'!$E$5:$E$85,'Weekly Summary'!$B33,'Cost Report'!$K$5:$K$85) -> 0
A34: Total Costs to Date | D34: =SUM(D25:D33) -> 1.0632881e+09 | E34: =SUM(E25:E33) -> 18112042 | F34: =SUM(F25:F33) -> 1.0814001e+09 | G34: =IF(F$34=0,0,F34/F$34) -> 1
A36: Net Earnings - Excluding Bill 1 | D36: =D16-D34 -> 2.8678983e+08 | E36: =E16-E34 -> 6199466.7 | F36: =F16-F34 -> 2.9298929e+08
A37: % Net Earnings | D37: =IF(D16=0,0,D36/D16) -> 0.21242465 | E37: =IF(E16=0,0,E36/E16) -> 0.25500131 | F37: =IF(F16=0,0,F36/F16) -> 0.21317779
A39: WEEKLY PROGRESS
A41: GENERAL REMARKS

Sheet BEME & Works Completed Fd
B1: BEME & Works Completed to date | N1: Instructions
B2: ='Contract Summary'!C4 -> PROPOSED CONSTRUCTION OF 15 SPAN, DUAL CARRIAGEWAY, 6TH BRIDGE OVER RIVER KADUNA AND APPROACH ROADS
B3: ="Updated to the "&TEXT('Contract Summary'!$E$1,"dd mmmm yyyy")&" - Week No. "&'Contract Summary'!$H$1 -> Updated to the 01 March 2025 - Week No. 9
F4: 0 | G4: =F4+E4 -> 0 | H4: =D4-G4 -> 0 | I4: 1 | J4: =I4*D4 -> 0 | L4: =F4*I4 -> 0 | M4: =SUM(K4,L4) -> 0 | N4: =IF(J4=0,0,M4/J4) -> 0
A6: Total Bill No. 1 Carried to Summary | J6: =SUM(J4:J5) -> 0 | K6: =SUM(K4:K5) -> 0 | L6: =SUM(L4:L5) -> 0 | M6: =SUM(M4:M5) -> 0 | N6: =IF(J6=0,0,M6/J6) -> 0
A8: ITEM | B8: DESCRIPTION | C8: UNIT | D8: CONTRACT QTY | E8: PREVIOUS QTY | F8: THIS WEEK QTY | G8: TOTAL QTY COMPLETED | H8: QTY OUTSTANDING | I8: RATE ₦ | J8: CONTRACT AMOUNT | K8: PREVIOUS AMOUNT | L8: THIS WEEK AMOUNT | M8: TOTAL AMOUNT | N8: % OF WORK COMPLETED
A10: 5 | B10: GENERAL
A11: 5.01 | B11: Provide, furnish and maintain office accommodation for the engineer's Representative | C11: P.S | D11: 1 | G11: =F11+E11 -> 0 | H11: =D11-G11 -> 1 | I11: 2500000 | J11: =I11*D11 -> 2500000 | K11: =E11*I11 -> 0 | L11: =F11*I11 -> 0 | M11: =SUM(K11,L11) -> 0 | N11: =IF(J11=0,0,M11/J11) -> 0
A12: 5.02 | B12: Provide equipment, labor and assistance as may be required by the Engineer's Representative | C12: P.S | D12: 1 | G12: =F12+E12 -> 0 | H12: =D12-G12 -> 1 | I12: 2000000 | J12: =I12*D12 -> 2000000 | K12: =E12*I12 -> 0 | L12: =F12*I12 -> 0 | M12: =SUM(K12,L12) -> 0 | N12: =IF(J12=0,0,M12/J12) -> 0
A13: 5.03 | B13: Allow for Survey and Design | C13: P.S | D13: 1 | G13: =F13+E13 -> 0 | H13: =D13-G13 -> 1 | I13: 5000000 | J13: =I13*D13 -> 5000000 | K13: =E13*I13 -> 0 | L13: =F13*I13 -> 0 | M13: =SUM(K13,L13) -> 0 | N13: =IF(J13=0,0,M13/J13) -> 0
A14: 5.04 | B14: Allow for Purchase and maintenance of project vehicles | C14: L.S | D14: 1 | G14: =F14+E14 -> 0 | H14: =D14-G14 -> 1 | I14: 10000000 | J14: =I14*D14 -> 10000000 | K14: =E14*I14 -> 0 | L14: =F14*I14 -> 0 | M14: =SUM(K14,L14) -> 0 | N14: =IF(J14=0,0,M14/J14) -> 0
A15: 5.05 | B15: Provide erect and maintain living accommodation for Resident Engineer, Technical officers and Technical Assistants | C15: P.S | D15: 1 | G15: =F15+E15 -> 0 | H15: =D15-G15 -> 1 | I15: 2000000 | J15: =I15*D15 -> 2000000 | K15: =E15*I15 -> 0 | L15: =F15*I15 -> 0 | M15: =SUM(K15,L15) -> 0 | N15: =IF(J15=0,0,M15/J15) -> 0
A16: 5.06 | B16: Allow for Envoronmental Impact assessment and safety | C16: P.S | D16: 1 | G16: =F16+E16 -> 0 | H16: =D16-G16 -> 1 | I16: 3000000 | J16: =I16*D16 -> 3000000 | K16: =E16*I16 -> 0 | L16: =F16*I16 -> 0 | M16: =SUM(K16,L16) -> 0 | N16: =IF(J16=0,0,M16/J16) -> 0
A17: 5.07 | B17: Allow for insurance of the Engineer and other Highway supervisory Staff against all accidents in connection with operation of the project. | C17: L.S | D17: 1 | G17: =F17+E17 -> 0 | H17: =D17-G17 -> 1 | I17: 0 | J17: =I17*D17 -> 0 | K17: =E17*I17 -> 0 | L17: =F17*I17 -> 0 | M17: =SUM(K17,L17) -> 0 | N17: =IF(J17=0,0,M17/J17) -> 0
A18: 5.08 | B18: Allow for Pavement Evaluation Unit Services | C18: P.S | D18: 1 | G18: =F18+E18 -> 0 | H18: =D18-G18 -> 1 | I18: 0 | J18: =I18*D18 -> 0 | K18: =E18*I18 -> 0 | L18: =F18*I18 -> 0 | M18: =SUM(K18,L18) -> 0 | N18: =IF(J18=0,0,M18/J18) -> 0
A19: 5.09 | B19: Allow for roadway markings and road signs | C19: P.S | D19: 1 | G19: =F19+E19 -> 0 | H19: =D19-G19 -> 1 | I19: 5000000 | J19: =I19*D19 -> 5000000 | K19: =E19*I19 -> 0 | L19: =F19*I19 -> 0 | M19: =SUM(K19,L19) -> 0 | N19: =IF(J19=0,0,M19/J19) -> 0
A20: 5.1 | B20: Allow for cost of progress photographs | C20: P.S | D20: 1 | G20: =F20+E20 -> 0 | H20: =D20-G20 -> 1 | I20: 1000000 | J20: =I20*D20 -> 1000000 | K20: =E20*I20 -> 0 | L20: =F20*I20 -> 0 | M20: =SUM(K20,L20) -> 0 | N20: =IF(J20=0,0,M20/J20) -> 0
A21: 5.11 | B21: Allow for the removal and relocation of existing installations for electricity, telephone, water supply and other utilities | C21: P.S | D21: 1 | G21: =F21+E21 -> 0 | H21: =D21-G21 -> 1 | I21: 0 | J21: =I21*D21 -> 0 | K21: =E21*I21 -> 0 | L21: =F21*I21 -> 0 | M21: =SUM(K21,L21) -> 0 | N21: =IF(J21=0,0,M21/J21) -> 0
A22: 5.12 | B22: Allow for compensation of crop, buildings and other properties affected by the proposed bridge alignment | C22: P.S | D22: 1 | G22: =F22+E22 -> 0 | H22: =D22-G22 -> 1 | I22: 5000000 | J22: =I22*D22 -> 5000000 | K22: =E22*I22 -> 0 | L22: =F22*I22 -> 0 | M22: =SUM(K22,L22) -> 0 | N22: =IF(J22=0,0,M22/J22) -> 0
A24: Total Bill No. 5.0 Carried to Summary | J24: =SUM(J11:J22) -> 35500000 | K24: =SUM(K14:K21) -> 0 | L24: =SUM(L14:L21) -> 0 | M24: =SUM(M14:M21) -> 0 | N24: =IF(J24=0,0,M24/J24) -> 0
A25: 5.1 | B25: EXCAVATION AND PILING
A26: 5.1.1 | B26: Provide and place lateritic material as filling in river to serve as access for river crossing | C26: m3 | D26: 37224 | E26: 27080 | G26: =F26+E26 -> 27080 | H26: =D26-G26 -> 10144 | I26: 6200 | J26: =I26*D26 -> 230788800 | K26: =E26*I26 -> 167896000 | L26: =F26*I26 -> 0 | M26: =SUM(K26,L26) -> 167896000 | N26: =IF(J26=0,0,M26/J26) -> 0.72748764
A27: 5.1.2 | B27: Excavate in any kind of material except rock for all foundations including dewatering, shoring and backfilling with suitable material. | C27: m3 | D27: 4500 | E27: 11617 | G27: =F27+E27 -> 11617 | H27: =D27-G27 -> -7117 | I27: 5300 | J27: =I27*D27 -> 23850000 | K27: =E27*I27 -> 61570100 | L27: =F27*I27 -> 0 | M27: =SUM(K27,L27) -> 61570100 | N27: =IF(J27=0,0,M27/J27) -> 2.5815556
A28: 5.1.3 | B28: Extra over item 5.1.1 for excavation of rock. (haulage inclusive) Provisional | C28: m3 | D28: 1200 | E28: 0 | G28: =F28+E28 -> 0 | H28: =D28-G28 -> 1200 | I28: 32500 | J28: =I28*D28 -> 39000000 | K28: =E28*I28 -> 0 | L28: =F28*I28 -> 0 | M28: =SUM(K28,L28) -> 0 | N28: =IF(J28=0,0,M28/J28) -> 0
A29: 5.1.4 | B29: Earth fill suitable borrowed materials for foundations behind and around abutments | C29: m3 | D29: 4300 | E29: 0 | G29: =F29+E29 -> 0 | H29: =D29-G29 -> 4300 | I29: 6200 | J29: =I29*D29 -> 26660000 | K29: =E29*I29 -> 0 | L29: =F29*I29 -> 0 | M29: =SUM(K29,L29) -> 0 | N29: =IF(J29=0,0,M29/J29) -> 0
A30: 5.1.5 | B30: Grade 15 mass concrete to rock foundation bottom level | C30: m3 | D30: 2000 | E30: 1378.9 | G30: =F30+E30 -> 1378.9 | H30: =D30-G30 -> 621.1 | I30: 121500 | J30: =I30*D30 -> 243000000 | K30: =E30*I30 -> 167536350 | L30: =F30*I30 -> 0 | M30: =SUM(K30,L30) -> 167536350 | N30: =IF(J30=0,0,M30/J30) -> 0.68945
A31: 5.1.6 | B31: Provide, place and fix 25mm dia High tensile steel reinforcement in bottom of foundation ( Micro piles ) | C31: Tons | D31: 10 | E31: 2.91864 | G31: =F31+E31 -> 2.91864 | H31: =D31-G31 -> 7.08136 | I31: 1180000 | J31: =I31*D31 -> 11800000 | K31: =E31*I31 -> 3443995.2 | L31: =F31*I31 -> 0 | M31: =SUM(K31,L31) -> 3443995.2 | N31: =IF(J31=0,0,M31/J31) -> 0.291864
A32: 5.1.7 | B32: Provide and bore tests 600mm nominal diameter piles to any depth. Rate to include driving casting, filing with concrete grade 25, reinforcement and trimming of pile head as specified. | C32: m | D32: rate only | G32: =F32+E32 -> 0 | H32: 0 | I32: 500000 | J32: 0 | K32: =E32*I32 -> 0 | L32: =F32*I32 -> 0 | M32: =SUM(K32,L32) -> 0 | N32: =IF(J32=0,0,M32/J32) -> 0
A33: 5.1.8 | B33: Allow for confirmatory deep soil investigation at bridge site | C33: LS | D33: 1 | G33: =F33+E33 -> 0 | H33: =D33-G33 -> 1 | I33: 20000000 | J33: =I33*D33 -> 20000000 | K33: =E33*I33 -> 0 | L33: =F33*I33 -> 0 | M33: =SUM(K33,L33) -> 0 | N33: =IF(J33=0,0,M33/J33) -> 0
A34: 5.1.9 | B34: Allow for Load tests on 600mm diameter piles to twice the design load | C34: LS | D34: rate only | G34: =F34+E34 -> 0 | H34: 0 | I34: 40000000 | J34: 0 | K34: =E34*I34 -> 0 | L34: =F34*I34 -> 0 | M34: =SUM(K34,L34) -> 0 | N34: =IF(J34=0,0,M34/J34) -> 0
A36: Total Bill No. 2 Carried to Summary | J36: =SUM(J26:J34) -> 595098800 | K36: =SUM(K26:K34) -> 4.0044645e+08 | L36: =SUM(L26:L34) -> 0 | M36: =SUM(M26:M34) -> 4.0044645e+08 | N36: =IF(J36=0,0,M36/J36) -> 0.6729075
A39: ITEM | B39: DESCRIPTION | C39: UNIT | D39: CONTRACT QTY | E39: PREVIOUS QTY | F39: THIS WEEK QTY | G39: TOTAL QTY COMPLETED | H39: QTY OUTSTANDING | I39: RATE ₦ | J39: CONTRACT AMOUNT | K39: PREVIOUS AMOUNT | L39: THIS WEEK AMOUNT | M39: TOTAL AMOUNT | N39: % OF WORK COMPLETED
A41: 5.2 | B41: PILE CAP, PIERS ,PIER CAPS, ABUTMENT AND APPROACH SLAB
A42: 5.2.1 | B42: Provide, mix and place grade 10 mass concrete 100mm blinding for bottom of pile caps and foundations and approach slab | C42: m3 | D42: 125 | E42: 0 | G42: =F42+E42 -> 0 | H42: =D42-G42 -> 125 | I42: 115000 | J42: =I42*D42 -> 14375000 | K42: =E42*I42 -> 0 | L42: =F42*I42 -> 0 | M42: =SUM(K42,L42) -> 0 | N42: =IF(J42=0,0,M42/J42) -> 0
A43: 5.2.2 | B43: Provide, mix and place grade 30 concrete in pile caps and foundations including formwork and shuttering | C43: m3 | D43: 1254 | E43: 686.4 | G43: =F43+E43 -> 686.4 | H43: =D43-G43 -> 567.6 | I43: 180000 | J43: =I43*D43 -> 225720000 | K43: =E43*I43 -> 1.23552e+08 | L43: =F43*I43 -> 0 | M43: =SUM(K43,L43) -> 1.23552e+08 | N43: =IF(J43=0,0,M43/J43) -> 0.54736842
A44: 5.2.3 | B44: Provide, cut and fix high tensile reinforcement in pile caps and foundations. | C44: Tons | D44: 105 | E44: 73.888412 | G44: =F44+E44 -> 73.888412 | H44: =D44-G44 -> 31.111588 | I44: 1180000 | J44: =I44*D44 -> 123900000 | K44: =E44*I44 -> 87188327 | L44: =F44*I44 -> 0 | M44: =SUM(K44,L44) -> 87188327 | N44: =IF(J44=0,0,M44/J44) -> 0.70369917
A45: 5.2.4 | B45: Provide, mix and place grade 30 concrete in abutments, wingwalls, piers, Retaining and pier caps | C45: m3 | D45: 1862 | E45: 344.9048 | F45: 26.5104 | G45: =F45+E45 -> 371.4152 | H45: =D45-G45 -> 1490.5848 | I45: 180000 | J45: =I45*D45 -> 335160000 | K45: =E45*I45 -> 62082864 | L45: =F45*I45 -> 4771872 | M45: =SUM(K45,L45) -> 66854736 | N45: =IF(J45=0,0,M45/J45) -> 0.19947111
A46: 5.2.5 | B46: Provide, cut and fix high tensile reinforcement in Abutment, Wingwalls, Piers and Pier Cap | C46: Tons | D46: 165 | E46: 27.14652 | G46: =F46+E46 -> 27.14652 | H46: =D46-G46 -> 137.85348 | I46: 1180000 | J46: =I46*D46 -> 194700000 | K46: =E46*I46 -> 32032894 | L46: =F46*I46 -> 0 | M46: =SUM(K46,L46) -> 32032894 | N46: =IF(J46=0,0,M46/J46) -> 0.16452436
A47: 5.2.6 | B47: Provide and fix 100 mm diameter PVC pipe as weep holes in abutments and wingwalls as shown the drawings. | C47: Nos. | D47: 144 | G47: =F47+E47 -> 0 | H47: =D47-G47 -> 144 | I47: 6500 | J47: =I47*D47 -> 936000 | K47: =E47*I47 -> 0 | L47: =F47*I47 -> 0 | M47: =SUM(K47,L47) -> 0 | N47: =IF(J47=0,0,M47/J47) -> 0
A48: 5.2.7 | B48: Grade 20 Concrete for Abutment Slope Protection | C48: m2 | D48: 550 | G48: =F48+E48 -> 0 | H48: =D48-G48 -> 550 | I48: 17000 | J48: =I48*D48 -> 9350000 | K48: =E48*I48 -> 0 | L48: =F48*I48 -> 0 | M48: =SUM(K48,L48) -> 0 | N48: =IF(J48=0,0,M48/J48) -> 0
A49: 5.2.8 | B49: Grade 30 Concrete in Toebeam | C49: m3 | D49: 75 | G49: =F49+E49 -> 0 | H49: =D49-G49 -> 75 | I49: 180000 | J49: =I49*D49 -> 13500000 | K49: =E49*I49 -> 0 | L49: =F49*I49 -> 0 | M49: =SUM(K49,L49) -> 0 | N49: =IF(J49=0,0,M49/J49) -> 0
A50: 5.2.9 | B50: H.T. Rebar in Toe for Abutment Protection | C50: Tons | D50: 7.5 | G50: =F50+E50 -> 0 | H50: =D50-G50 -> 7.5 | I50: 1180000 | J50: =I50*D50 -> 8850000 | K50: =E50*I50 -> 0 | L50: =F50*I50 -> 0 | M50: =SUM(K50,L50) -> 0 | N50: =IF(J50=0,0,M50/J50) -> 0
A51: 5.2.10 | B51: Apply two coat of bitumen paint to concrete surfaces in contact with the earth. | C51: m2 | D51: 350 | G51: =F51+E51 -> 0 | H51: =D51-G51 -> 350 | I51: 12500 | J51: =I51*D51 -> 4375000 | K51: =E51*I51 -> 0 | L51: =F51*I51 -> 0 | M51: =SUM(K51,L51) -> 0 | N51: =IF(J51=0,0,M51/J51) -> 0
A52: 5.2.11 | B52: Provide filter layers behind abutment, wingwalls and retaining wall | C52: m2 | D52: 407 | G52: =F52+E52 -> 0 | H52: =D52-G52 -> 407 | I52: 16500 | J52: =I52*D52 -> 6715500 | K52: =E52*I52 -> 0 | L52: =F52*I52 -> 0 | M52: =SUM(K52,L52) -> 0 | N52: =IF(J52=0,0,M52/J52) -> 0
A53: 5.2.12 | B53: Provide, mix and place concrete grade 30 in approach slabs including reinforcement as shown on the drawing.. | C53: m3 | D53: 49.284 | G53: =F53+E53 -> 0 | H53: =D53-G53 -> 49.284 | I53: 320000 | J53: =I53*D53 -> 15770880 | K53: =E53*I53 -> 0 | L53: =F53*I53 -> 0 | M53: =SUM(K53,L53) -> 0 | N53: =IF(J53=0,0,M53/J53) -> 0
A55: Total Bill No. 3 Carried to Summary | J55: =SUM(J42:J54) -> 953352380 | K55: =SUM(K42:K54) -> 3.0485608e+08 | L55: =SUM(L42:L54) -> 4771872 | M55: =SUM(M42:M54) -> 3.0962796e+08 | N55: =IF(J55=0,0,M55/J55) -> 0.32477808
A57: ITEM | B57: DESCRIPTION | C57: UNIT | D57: CONTRACT QTY | E57: PREVIOUS QTY | F57: THIS WEEK QTY | G57: TOTAL QTY COMPLETED | H57: QTY OUTSTANDING | I57: RATE ₦ | J57: CONTRACT AMOUNT | K57: PREVIOUS AMOUNT | L57: THIS WEEK AMOUNT | M57: TOTAL AMOUNT | N57: % OF WORK COMPLETED
A59: 5.3 | B59: SUPERSTRUCTURE
A60: 5.3.1 | B60: Provide, mix and place concrete grade 40 in prefabricated longitudinal beams 255 Nos including shuttering, transportation and lauching to the right position | C60: No | D60: 255 | E60: 81.75 | F60: 3 | G60: =F60+E60 -> 84.75 | H60: =D60-G60 -> 170.25 | I60: 2700000 | J60: =I60*D60 -> 688500000 | K60: =E60*I60 -> 220725000 | L60: =F60*I60 -> 8100000 | M60: =SUM(K60,L60) -> 228825000 | N60: =IF(J60=0,0,M60/J60) -> 0.33235294
A61: 5.3.2 | B61: Provide, mix and place concrete grade 30 in bridge deck slab including shuttering. | C61: m3 | D61: 820 | E61: 0 | G61: =F61+E61 -> 0 | H61: =D61-G61 -> 820 | I61: 180000 | J61: =I61*D61 -> 147600000 | K61: =E61*I61 -> 0 | L61: =F61*I61 -> 0 | M61: =SUM(K61,L61) -> 0 | N61: =IF(J61=0,0,M61/J61) -> 0
A62: 5.3.3 | B62: Provide, mix and place grade 30 concrete in outer kerbs including steel reinforcement and shuttering. | C62: m | D62: 564 | E62: 0 | G62: =F62+E62 -> 0 | H62: =D62-G62 -> 564 | I62: 25000 | J62: =I62*D62 -> 14100000 | K62: =E62*I62 -> 0 | L62: =F62*I62 -> 0 | M62: =SUM(K62,L62) -> 0 | N62: =IF(J62=0,0,M62/J62) -> 0
A63: 5.3.4 | B63: Ditto item 5.43 but to inner kerbs. | C63: m | E63: 0 | G63: =F63+E63 -> 0 | H63: =D63-G63 -> 0 | I63: 141400 | J63: =I63*D63 -> 0 | K63: =E63*I63 -> 0 | L63: =F63*I63 -> 0 | M63: =SUM(K63,L63) -> 0 | N63: =IF(J63=0,0,M63/J63) -> 0
A64: 5.3.5 | B64: Provide, mix and place concrete grade 30 for parapets | C64: m | D64: 564 | E64: 423 | G64: =F64+E64 -> 423 | H64: =D64-G64 -> 141 | I64: 110000 | J64: =I64*D64 -> 62040000 | K64: =E64*I64 -> 46530000 | L64: =F64*I64 -> 0 | M64: =SUM(K64,L64) -> 46530000 | N64: =IF(J64=0,0,M64/J64) -> 0.75
A65: 5.3.6 | B65: Provide, fix rough shuttering to non-exposed faces of the superstructure. | C65: m2 | D65: 2000 | E65: 0 | G65: =F65+E65 -> 0 | H65: =D65-G65 -> 2000 | I65: 10500 | J65: =I65*D65 -> 21000000 | K65: =E65*I65 -> 0 | L65: =F65*I65 -> 0 | M65: =SUM(K65,L65) -> 0 | N65: =IF(J65=0,0,M65/J65) -> 0
A66: 5.3.7 | B66: Provide, fix wrot shuttering to exposed faces of the superstructure. | C66: m2 | D66: 5000 | E66: 776.36 | F66: 63.12 | G66: =F66+E66 -> 839.48 | H66: =D66-G66 -> 4160.52 | I66: 15000 | J66: =I66*D66 -> 75000000 | K66: =E66*I66 -> 11645400 | L66: =F66*I66 -> 946800 | M66: =SUM(K66,L66) -> 12592200 | N66: =IF(J66=0,0,M66/J66) -> 0.167896
A67: 5.3.8 | B67: Provide and fix H.T. steel reinforcement in beams and deck slab | C67: Tons | D67: 890 | E67: 230.24025 | F67: 7.4548181 | G67: =F67+E67 -> 237.69507 | H67: =D67-G67 -> 652.30493 | I67: 1180000 | J67: =I67*D67 -> 1050200000 | K67: =E67*I67 -> 2.716835e+08 | L67: =F67*I67 -> 8796685.3 | M67: =SUM(K67,L67) -> 2.8048019e+08 | N67: =IF(J67=0,0,M67/J67) -> 0.26707312
A68: 5.3.9 | B68: Provide walkway to include service ducts and inspection chambers as shown on the drawings. | C68: m | D68: 564 | E68: 0 | G68: =F68+E68 -> 0 | H68: =D68-G68 -> 564 | I68: 63000 | J68: =I68*D68 -> 35532000 | K68: =E68*I68 -> 0 | L68: =F68*I68 -> 0 | M68: =SUM(K68,L68) -> 0 | N68: =IF(J68=0,0,M68/J68) -> 0
A69: 5.3.12 | B69: Provide, mix and place concrete grade 30 in plinths | C69: m3 | D69: 8.76 | G69: =F69+E69 -> 0 | H69: =D69-G69 -> 8.76 | I69: 178000 | J69: =I69*D69 -> 1559280 | K69: =E69*I69 -> 0 | L69: =F69*I69 -> 0 | M69: =SUM(K69,L69) -> 0 | N69: =IF(J69=0,0,M69/J69) -> 0
A72: Total Bill No. 4 Carried to Summary | J72: =SUM(J60:J71) -> 2095531280 | K72: =SUM(K60:K71) -> 5.505839e+08 | L72: =SUM(L60:L71) -> 17843485 | M72: =SUM(M60:M71) -> 5.6842739e+08 | N72: =IF(J72=0,0,M72/J72) -> 0.27125693
A74: ITEM | B74: DESCRIPTION | C74: UNIT | D74: CONTRACT QTY | E74: PREVIOUS QTY | F74: THIS WEEK QTY | G74: TOTAL QTY COMPLETED | H74: QTY OUTSTANDING | I74: RATE ₦ | J74: CONTRACT AMOUNT | K74: PREVIOUS AMOUNT | L74: THIS WEEK AMOUNT | M74: TOTAL AMOUNT | N74: % OF WORK COMPLETED
A76: 5.4 | B76: PAVEMENT
A77: 5.4.1 | B77: Sacrify existing asphaltic surface, shape recomapct and use as improved sub base shape and cmpact formation as specified to 100% B.S Compaction | C77: m2 | D77: 0 | F77: 0 | G77: =F77+E77 -> 0 | H77: =D77-G77 -> 0 | I77: 1200 | J77: =I77*D77 -> 0 | K77: =E77*I77 -> 0 | L77: =F77*I77 -> 0 | M77: =SUM(K77,L77) -> 0 | N77: =IF(J77=0,0,M77/J77) -> 0
A78: 5.4.2 | B78: shape and compact formation as specified to 100% B.S Compaction | C78: m2 | D78: 0 | I78: 350
A79: 5.4.3 | B79: Provide, spread and compact to 100% WASC compaction naturally occurring laterite as sub-base in varying thickness not exceeding a compacted layer of 200mm thickness on the approach road carriageway (haulage inclusive) | C79: m3 | D79: 0 | I79: 6800
A80: 5.4.4 | B80: Provide , spread, shape and compact approved crushed stone base 200mm thick in the carriageway only | C80: m3 | D80: 0 | G80: =F80+E80 -> 0 | H80: =D80-G80 -> 0 | I80: 40500 | J80: =I80*D80 -> 0 | K80: =E80*I80 -> 0 | L80: =F80*I80 -> 0 | M80: =SUM(K80,L80) -> 0 | N80: =IF(J80=0,0,M80/J80) -> 0
A81: 5.4.5 | B81: Provide and lay prime coat using MC1 cut-back bitumen at 1.2/m2 including blinding with sand or quarry fines. | C81: m2 | D81: 0 | G81: =F81+E81 -> 0 | H81: =D81-G81 -> 0 | I81: 2500 | J81: =I81*D81 -> 0 | K81: =E81*I81 -> 0 | L81: =F81*I81 -> 0 | M81: =SUM(K81,L81) -> 0 | N81: =IF(J81=0,0,M81/J81) -> 0
A82: 5.4.6 | B82: Provide and lay 50mm thick asphaltic concrete wearing course inluding tack coat | C82: m2 | D82: 0 | G82: =F82+E82 -> 0 | H82: =D82-G82 -> 0 | I82: 23200 | J82: =I82*D82 -> 0 | K82: =E82*I82 -> 0 | L82: =F82*I82 -> 0 | M82: =SUM(K82,L82) -> 0 | N82: =IF(J82=0,0,M82/J82) -> 0
A84: Total Bill No. 5 Carried to Summary | J84: =SUM(J77:J83) -> 0 | K84: =SUM(K77:K83) -> 0 | L84: =SUM(L77:L83) -> 0 | M84: =SUM(M77:M83) -> 0 | N84: =IF(J84=0,0,M84/J84) -> 0
A86: ITEM | B86: DESCRIPTION | C86: UNIT | D86: CONTRACT QTY | E86: PREVIOUS QTY | F86: THIS WEEK QTY | G86: TOTAL QTY COMPLETED | H86: QTY OUTSTANDING | I86: RATE ₦ | J86: CONTRACT AMOUNT | K86: PREVIOUS AMOUNT | L86: THIS WEEK AMOUNT | M86: TOTAL AMOUNT | N86: % OF WORK COMPLETED
A88: 5.5 | B88: MISCELLANEOUS
A89: 5.5.1 | B89: Provide and place fixed bearings of approved design and type on top of abutment or piers. | C89: Nos | D89: 510 | F89: 0 | G89: =F89+E89 -> 0 | H89: =D89-G89 -> 510 | I89: 410000 | J89: =I89*D89 -> 209100000 | K89: =E89*I89 -> 0 | L89: =F89*I89 -> 0 | M89: =SUM(K89,L89) -> 0 | N89: =IF(J89=0,0,M89/J89) -> 0
A90: 5.5.2 | B90: Provide and install bearings movable bearings of approved design and type on top or Abutment of Piers. | C90: Nos | D90: 0 | F90: 0 | G90: =F90+E90 -> 0 | H90: =D90-G90 -> 0 | I90: 385000 | J90: =I90*D90 -> 0 | K90: =E90*I90 -> 0 | L90: =F90*I90 -> 0 | M90: =SUM(K90,L90) -> 0 | N90: =IF(J90=0,0,M90/J90) -> 0
A91: 5.5.3 | B91: Provide and install Thoma expansion Joint of approved design in the carriageway deck as shown on the drawings. | C91: m | D91: 190 | F91: 0 | G91: =F91+E91 -> 0 | H91: =D91-G91 -> 190 | I91: 300000 | J91: =I91*D91 -> 57000000 | K91: =E91*I91 -> 0 | L91: =F91*I91 -> 0 | M91: =SUM(K91,L91) -> 0 | N91: =IF(J91=0,0,M91/J91) -> 0
A92: 5.5.4 | B92: Ditto item 5.5.3 but along footpaths and kerbs as shown on the drawings. | C92: m | D92: 0 | F92: 0 | G92: =F92+E92 -> 0 | H92: =D92-G92 -> 0 | I92: 300000 | J92: =I92*D92 -> 0 | K92: =E92*I92 -> 0 | L92: =F92*I92 -> 0 | M92: =SUM(K92,L92) -> 0 | N92: =IF(J92=0,0,M92/J92) -> 0
A93: 5.5.5 | B93: Provide and fix into the bridge deck, cast iron inlet grating and finish complete as shown on the drawings. | C93: Nos | D93: 30 | F93: 0 | G93: =F93+E93 -> 0 | H93: =D93-G93 -> 30 | I93: 400000 | J93: =I93*D93 -> 12000000 | K93: =E93*I93 -> 0 | L93: =F93*I93 -> 0 | M93: =SUM(K93,L93) -> 0 | N93: =IF(J93=0,0,M93/J93) -> 0
A94: 5.5.6 | B94: Provide P.V.C. drainage pipes as shown on the drawings. | C94: m | D94: 30 | F94: 0 | G94: =F94+E94 -> 0 | H94: =D94-G94 -> 30 | I94: 30000 | J94: =I94*D94 -> 900000 | K94: =E94*I94 -> 0 | L94: =F94*I94 -> 0 | M94: =SUM(K94,L94) -> 0 | N94: =IF(J94=0,0,M94/J94) -> 0
A95: 5.5.7 | B95: Provide and lay concrete kerbs grade 20 along median as directed including for blinding and haunching. | C95: m | D95: 564 | F95: 0 | G95: =F95+E95 -> 0 | H95: =D95-G95 -> 564 | I95: 20000 | J95: =I95*D95 -> 11280000 | K95: =E95*I95 -> 0 | L95: =F95*I95 -> 0 | M95: =SUM(K95,L95) -> 0 | N95: =IF(J95=0,0,M95/J95) -> 0
A96: 5.5.8 | B96: Provide and place precast concrete bases for electric lighting poles. | C96: Nos | D96: 15 | F96: 0 | G96: =F96+E96 -> 0 | H96: =D96-G96 -> 15 | I96: 145000 | J96: =I96*D96 -> 2175000 | K96: =E96*I96 -> 0 | L96: =F96*I96 -> 0 | M96: =SUM(K96,L96) -> 0 | N96: =IF(J96=0,0,M96/J96) -> 0
A97: 5.5.9 | B97: Provide 100mm thick concrete (Grade 20) median | C97: m | D97: 282 | F97: 0 | G97: =F97+E97 -> 0 | H97: =D97-G97 -> 282 | I97: 17500 | J97: =I97*D97 -> 4935000 | K97: =E97*I97 -> 0 | L97: =F97*I97 -> 0 | M97: =SUM(K97,L97) -> 0 | N97: =IF(J97=0,0,M97/J97) -> 0
A99: Total Bill No.6 Carried to Summary | J99: =SUM(J89:J97) -> 297390000 | K99: =SUM(K89:K97) -> 0 | L99: =SUM(L89:L97) -> 0 | M99: =SUM(M89:M97) -> 0 | N99: =IF(J99=0,0,M99/J99) -> 0
A102: Contingency & VOP
A103: ITEM | B103: DESCRIPTION | C103: UNIT | D103: CONTRACT QTY | E103: PREVIOUS QTY | F103: THIS WEEK QTY | G103: TOTAL QTY COMPLETED | H103: QTY OUTSTANDING | I103: RATE ₦ | J103: CONTRACT AMOUNT | K103: PREVIOUS AMOUNT | L103: THIS WEEK AMOUNT | M103: TOTAL AMOUNT | N103: % OF WORK COMPLETED
B105: Add VOP @ 5% | D105: 1 | G105: =F105+E105 -> 0 | H105: =D105-G105 -> 1 | I105: =5%*J125 -> 198843623 | J105: =D105*I105 -> 198843623 | K105: 0 | L105: 0 | M105: =SUM(K105,L105) -> 0 | N105: =IF(J105=0,0,M105/J105) -> 0
B106: Add Contingencies @ 3% | D106: 1 | E106: 0 | G106: =F106+E106 -> 0 | H106: =D106-G106 -> 1 | I106: =3%*J125 -> 1.1930617e+08 | J106: =D106*I106 -> 1.1930617e+08 | K106: 0 | L106: 0 | M106: =SUM(K106,L106) -> 0 | N106: =IF(J106=0,0,M106/J106) -> 0
A113: Total Contingency & VOP Carried to Summary | D113: =D105 -> 1 | J113: =SUM(J105:J112) -> 3.181498e+08 | K113: =SUM(K105:K112) -> 0 | L113: =SUM(L105:L112) -> 0 | M113: =SUM(M105:M112) -> 0 | N113: =IF(J113=0,0,M113/J113) -> 0
A115: Summary All
A116: ITEM | B116: DESCRIPTION | C116: UNIT | D116: CONTRACT QTY | E116: PREVIOUS QTY | F116: THIS WEEK QTY | G116: TOTAL QTY COMPLETED | H116: QTY OUTSTANDING | I116: RATE ₦ | J116: CONTRACT AMOUNT | K116: PREVIOUS AMOUNT | L116: THIS WEEK AMOUNT | M116: TOTAL AMOUNT | N116: % OF WORK COMPLETED
A118: =IF(ISBLANK(#REF!),"",#REF!) -> #REF! | B118: =IF(ISBLANK(#REF!),"",#REF!) -> #REF!
A119: 5 | B119: Bill 1 | J119: =J24 -> 35500000 | K119: =K35 -> 0 | L119: =L35 -> 0 | M119: =M35 -> 0 | N119: =IF(J119=0,0,M119/J119) -> 0
A120: 5.1 | B120: Excavation and Piling | J120: =J36 -> 595098800 | K120: =K36 -> 4.0044645e+08 | L120: =L36 -> 0 | M120: =M36 -> 4.0044645e+08 | N120: =IF(J120=0,0,M120/J120) -> 0.6729075
A121: 5.2 | B121: Pile cap, Pier, Pier caps and Abutment | J121: =J55 -> 953352380 | K121: =K37 -> 0 | L121: =L37 -> 0 | M121: =M37 -> 0 | N121: =IF(J121=0,0,M121/J121) -> 0
A122: 5.3 | B122: Superstructure | J122: =J72 -> 2095531280 | K122: =K38 -> 0 | L122: =L38 -> 0 | M122: =M38 -> 0 | N122: =IF(J122=0,0,M122/J122) -> 0
A123: 5.4 | B123: Pavement | J123: =J84 -> 0
A124: 5.5 | B124: Miscellanous | J124: =J99 -> 297390000 | K124: =K40 -> 0 | L124: =L40 -> 0 | M124: =M40 -> 0 | N124: =IF(J124=0,0,M124/J124) -> 0
B125: SUB – TOTAL | J125: =SUM(J118:J124) -> 3976872460 | K125: =SUM(K118:K124) -> 4.0044645e+08 | L125: =SUM(L118:L124) -> 0 | M125: =SUM(M118:M124) -> 4.0044645e+08 | N125: =IF(J125=0,0,M125/J125) -> 0.10069381
B126: Contingency & VOP | J126: =J113 -> 3.181498e+08 | K126: =K113 -> 0 | L126: =L113 -> 0 | M126: =M113 -> 0 | N126: =IF(J126=0,0,M126/J126) -> 0
B127: SUB – TOTAL | J127: =SUM(J125:J126) -> 4.2950223e+09 | K127: =SUM(K125:K126) -> 4.0044645e+08 | L127: =SUM(L125:L126) -> 0 | M127: =SUM(M125:M126) -> 4.0044645e+08 | N127: =IF(J127=0,0,M127/J127) -> 0.09323501
B128: ="Add VAT @ "&Lists!$M$4*100&"%" -> Add VAT @ 7.5% | J128: =SUM(J127:J127)*Lists!$M$4 -> 3.2212667e+08 | K128: =SUM(K127:K127)*Lists!$M$4 -> 30033483 | L128: =SUM(L127:L127)*Lists!$M$4 -> 0 | M128: =SUM(M127:M127)*Lists!$M$4 -> 30033483 | N128: =IF(J128=0,0,M128/J128) -> 0.09323501
B129: TOTAL | J129: =SUM(J127:J128) -> 4.6171489e+09 | K129: =SUM(K127:K128) -> 4.3047993e+08 | L129: =SUM(L127:L128) -> 0 | M129: =SUM(M127:M128) -> 4.3047993e+08 | N129: =IF(J129=0,0,M129/J129) -> 0.09323501

Sheet Certificate Status
A1: CERTIFICATES | T1: Date: | U1: ='Weekly Summary'!E1 -> 45717 | V1: Week No: | W1: =IF(U1=0,0,VLOOKUP(U1,Lists!A2:B5000,2,FALSE)) -> 9 | X1: Instructions
A2: ='Contract Summary'!C4 -> PROPOSED CONSTRUCTION OF 15 SPAN, DUAL CARRIAGEWAY, 6TH BRIDGE OVER RIVER KADUNA AND APPROACH ROADS
A3: CERTIFICATES
A4: Date Submitted | B4: Cert Number | C4: Gross Value of Works Done | D4: Add Materials on Site | E4: General Bill 1 | F4: Total Value of Work Done | G4: Value of works per Cert | H4: Total Retention Held | I4: Retention This Cert | J4: Total Net Payment in Respect of works | K4: Add Release of Retention | L4: Add Value of Contingency Used | M4: Add Fluctuation on Materials | N4: Total Value of Works Executed | O4: Less Previously Certified without VAT | P4: ="Add VAT - "&Lists!$M$4*100&"%" -> Add VAT - 7.5% | Q4: Add Stamp Duty | R4: Add Admin Charge | S4: Educational Levy | T4: Total Amount Due | U4: Less Recovery of Advance | V4: Less advance Payment Refund per Cert | W4: Total Amount of Payment Certified | X4: Status
D5: 0 | F5: =SUM(C5:E5) -> 0 | G5: =F5 -> 0 | I5: =H5 -> 0 | J5: =F5-H5 -> 0 | N5: =SUM(J5:M5) -> 0 | O5: =SUM(K5:N5) -> 0 | P5: =O5*0.05 -> 0 | T5: =SUM(O5:S5) -> 0 | V5: =U5 -> 0 | W5: =T5-U5 -> 0 | X5: Not Vetted
D6: 0 | F6: =SUM(C6:E6) -> 0 | G6: =IF(F6=0,0,SUM(F6)-SUM(G$5:G5)) -> 0 | I6: =IF(H6=0,0,SUM(H6)-SUM(I$5:I5)) -> 0 | J6: =F6-H6 -> 0 | K6: 0 | L6: 0 | M6: 0 | N6: =SUM(J6:M6) -> 0 | O6: =IF(N6=0,0,N6-N5) -> 0 | P6: =O6*0.05 -> 0 | Q6: =O6*0.01 -> 0 | R6: =O6*0.02 -> 0 | T6: =SUM(O6:S6) -> 0 | V6: =IF(U6=0,0,SUM(U6)-SUM(V$5:V5)) -> 0 | W6: =T6-U6 -> 0
D7: 0 | F7: =SUM(C7:E7) -> 0 | G7: =IF(F7=0,0,SUM(F7)-SUM(G$5:G6)) -> 0 | I7: =IF(H7=0,0,SUM(H7)-SUM(I$5:I6)) -> 0 | J7: =F7-H7 -> 0 | K7: 0 | L7: 0 | M7: 0 | N7: =SUM(J7:M7) -> 0 | O7: =IF(N7=0,0,N7-N6) -> 0 | P7: =O7*0.05 -> 0 | Q7: =O7*0.01 -> 0 | R7: =O7*0.02 -> 0 | T7: =SUM(O7:S7) -> 0 | V7: =IF(U7=0,0,SUM(U7)-SUM(V$5:V6)) -> 0 | W7: =T7-U7 -> 0
D8: 0 | F8: =SUM(C8:E8) -> 0 | G8: =IF(F8=0,0,SUM(F8)-SUM(G$5:G7)) -> 0 | I8: =IF(H8=0,0,SUM(H8)-SUM(I$5:I7)) -> 0 | J8: =F8-H8 -> 0 | K8: 0 | L8: 0 | M8: 0 | N8: =SUM(J8:M8) -> 0 | O8: =IF(N8=0,0,N8-N7) -> 0 | P8: =O8*0.05 -> 0 | Q8: =O8*0.01 -> 0 | R8: =O8*0.02 -> 0 | T8: =SUM(O8:S8) -> 0 | V8: =IF(U8=0,0,SUM(U8)-SUM(V$5:V7)) -> 0 | W8: =T8-U8 -> 0
D9: 0 | F9: =SUM(C9:E9) -> 0 | G9: =IF(F9=0,0,SUM(F9)-SUM(G$5:G8)) -> 0 | I9: =IF(H9=0,0,SUM(H9)-SUM(I$5:I8)) -> 0 | J9: =F9-H9 -> 0 | K9: 0 | L9: 0 | M9: 0 | N9: =SUM(J9:M9) -> 0 | O9: =IF(N9=0,0,N9-N8) -> 0 | P9: =O9*0.05 -> 0 | Q9: =O9*0.01 -> 0 | R9: =O9*0.02 -> 0 | T9: =SUM(O9:S9) -> 0 | V9: =IF(U9=0,0,SUM(U9)-SUM(V$5:V8)) -> 0 | W9: =T9-U9 -> 0
D10: 0 | F10: =SUM(C10:E10) -> 0 | G10: =IF(F10=0,0,SUM(F10)-SUM(G$5:G9)) -> 0 | I10: =IF(H10=0,0,SUM(H10)-SUM(I$5:I9)) -> 0 | J10: =F10-H10 -> 0 | K10: 0 | L10: 0 | M10: 0 | N10: =SUM(J10:M10) -> 0 | O10: =IF(N10=0,0,N10-N9) -> 0 | P10: =O10*0.05 -> 0 | Q10: =O10*0.01 -> 0 | R10: =O10*0.02 -> 0 | T10: =SUM(O10:S10) -> 0 | V10: =IF(U10=0,0,SUM(U10)-SUM(V$5:V9)) -> 0 | W10: =T10-U10 -> 0
F11: =SUM(C11:E11) -> 0 | G11: =IF(F11=0,0,SUM(F11)-SUM(G$5:G10)) -> 0 | I11: =IF(H11=0,0,SUM(H11)-SUM(I$5:I10)) -> 0 | J11: =F11-H11 -> 0 | K11: 0 | L11: 0 | M11: 0 | N11: =SUM(J11:M11) -> 0 | O11: =IF(N11=0,0,N11-N10) -> 0 | P11: =O11*0.05 -> 0 | Q11: =O11*0.01 -> 0 | R11: =O11*0.02 -> 0 | T11: =SUM(O11:S11) -> 0 | V11: =IF(U11=0,0,SUM(U11)-SUM(V$5:V10)) -> 0 | W11: =T11-U11 -> 0
F12: =SUM(C12:E12) -> 0 | G12: =IF(F12=0,0,SUM(F12)-SUM(G$5:G11)) -> 0 | I12: =IF(H12=0,0,SUM(H12)-SUM(I$5:I11)) -> 0 | J12: =F12-H12 -> 0 | K12: 0 | L12: 0 | M12: 0 | N12: =SUM(J12:M12) -> 0 | O12: =IF(N12=0,0,N12-N11) -> 0 | P12: =O12*0.05 -> 0 | Q12: =O12*0.01 -> 0 | R12: =O12*0.02 -> 0 | T12: =SUM(O12:S12) -> 0 | V12: =IF(U12=0,0,SUM(U12)-SUM(V$5:V11)) -> 0 | W12: =T12-U12 -> 0
F13: =SUM(C13:E13) -> 0 | G13: =IF(F13=0,0,SUM(F13)-SUM(G$5:G12)) -> 0 | I13: =IF(H13=0,0,SUM(H13)-SUM(I$5:I12)) -> 0 | J13: =F13-H13 -> 0 | K13: 0 | L13: 0 | M13: 0 | N13: =SUM(J13:M13) -> 0 | O13: =IF(N13=0,0,N13-N12) -> 0 | P13: =O13*0.05 -> 0 | Q13: =O13*0.01 -> 0 | R13: =O13*0.02 -> 0 | T13: =SUM(O13:S13) -> 0 | V13: =IF(U13=0,0,SUM(U13)-SUM(V$5:V12)) -> 0 | W13: =T13-U13 -> 0
F14: =SUM(C14:E14) -> 0 | G14: =IF(F14=0,0,SUM(F14)-SUM(G$5:G13)) -> 0 | I14: =IF(H14=0,0,SUM(H14)-SUM(I$5:I13)) -> 0 | J14: =F14-H14 -> 0 | K14: 0 | L14: 0 | M14: 0 | N14: =SUM(J14:M14) -> 0 | O14: =IF(N14=0,0,N14-N13) -> 0 | P14: =O14*0.05 -> 0 | Q14: =O14*0.01 -> 0 | R14: =O14*0.02 -> 0 | T14: =SUM(O14:S14) -> 0 | V14: =IF(U14=0,0,SUM(U14)-SUM(V$5:V13)) -> 0 | W14: =T14-U14 -> 0
F15: =SUM(C15:E15) -> 0 | G15: =IF(F15=0,0,SUM(F15)-SUM(G$5:G14)) -> 0 | I15: =IF(H15=0,0,SUM(H15)-SUM(I$5:I14)) -> 0 | J15: =F15-H15 -> 0 | K15: 0 | L15: 0 | M15: 0 | N15: =SUM(J15:M15) -> 0 | O15: =IF(N15=0,0,N15-N14) -> 0 | P15: =O15*0.05 -> 0 | Q15: =O15*0.01 -> 0 | R15: =O15*0.02 -> 0 | T15: =SUM(O15:S15) -> 0 | V15: =IF(U15=0,0,SUM(U15)-SUM(V$5:V14)) -> 0 | W15: =T15-U15 -> 0
F16: =SUM(C16:E16) -> 0 | G16: =IF(F16=0,0,SUM(F16)-SUM(G$5:G15)) -> 0 | I16: =IF(H16=0,0,SUM(H16)-SUM(I$5:I15)) -> 0 | J16: =F16-H16 -> 0 | K16: 0 | L16: 0 | M16: 0 | N16: =SUM(J16:M16) -> 0 | O16: =IF(N16=0,0,N16-N15) -> 0 | P16: =O16*0.05 -> 0 | Q16: =O16*0.01 -> 0 | R16: =O16*0.02 -> 0 | S16: =O16*0.025 -> 0 | T16: =SUM(O16:S16) -> 0 | V16: =IF(U16=0,0,SUM(U16)-SUM(V$5:V15)) -> 0 | W16: =T16-U16 -> 0
F17: =SUM(C17:E17) -> 0 | G17: =IF(F17=0,0,SUM(F17)-SUM(G$5:G16)) -> 0 | I17: =IF(H17=0,0,SUM(H17)-SUM(I$5:I16)) -> 0 | J17: =F17-H17 -> 0 | K17: 0 | L17: 0 | M17: 0 | N17: =SUM(J17:M17) -> 0 | O17: =IF(N17=0,0,N17-N16) -> 0 | P17: =O17*0.05 -> 0 | Q17: =O17*0.01 -> 0 | R17: =O17*0.02 -> 0 | S17: =O17*0.025 -> 0 | T17: =SUM(O17:S17) -> 0 | V17: =IF(U17=0,0,SUM(U17)-SUM(V$5:V16)) -> 0 | W17: =T17-U17 -> 0
F18: =SUM(C18:E18) -> 0 | G18: =IF(F18=0,0,SUM(F18)-SUM(G$5:G17)) -> 0 | I18: =IF(H18=0,0,SUM(H18)-SUM(I$5:I17)) -> 0 | J18: =F18-H18 -> 0 | N18: =SUM(J18:M18) -> 0 | O18: =IF(N18=0,0,N18-N17) -> 0 | P18: =O18*0.05 -> 0 | Q18: =O18*0.01 -> 0 | R18: =O18*0.02 -> 0 | S18: =O18*0.025 -> 0 | T18: =SUM(O18:S18) -> 0 | V18: =IF(U18=0,0,SUM(U18)-SUM(V$5:V17)) -> 0 | W18: =T18-U18 -> 0
F19: =SUM(C19:E19) -> 0 | G19: =IF(F19=0,0,SUM(F19)-SUM(G$5:G18)) -> 0 | I19: =IF(H19=0,0,SUM(H19)-SUM(I$5:I18)) -> 0 | J19: =F19-H19 -> 0 | N19: =SUM(J19:M19) -> 0 | O19: =IF(N19=0,0,N19-N18) -> 0 | P19: =O19*0.05 -> 0 | Q19: =O19*0.01 -> 0 | R19: =O19*0.02 -> 0 | S19: =O19*0.025 -> 0 | T19: =SUM(O19:S19) -> 0 | V19: =IF(U19=0,0,SUM(U19)-SUM(V$5:V18)) -> 0 | W19: =T19-U19 -> 0
F20: =SUM(C20:E20) -> 0 | G20: =IF(F20=0,0,SUM(F20)-SUM(G$5:G19)) -> 0 | I20: =IF(H20=0,0,SUM(H20)-SUM(I$5:I19)) -> 0 | J20: =F20-H20 -> 0 | N20: =SUM(J20:M20) -> 0 | O20: =IF(N20=0,0,N20-N19) -> 0 | P20: =O20*0.05 -> 0 | Q20: =O20*0.01 -> 0 | R20: =O20*0.02 -> 0 | S20: =O20*0.025 -> 0 | T20: =SUM(O20:S20) -> 0 | V20: =IF(U20=0,0,SUM(U20)-SUM(V$5:V19)) -> 0 | W20: =T20-U20 -> 0
F21: =SUM(C21:E21) -> 0 | G21: =IF(F21=0,0,SUM(F21)-SUM(G$5:G20)) -> 0 | I21: =IF(H21=0,0,SUM(H21)-SUM(I$5:I20)) -> 0 | J21: =F21-H21 -> 0 | N21: =SUM(J21:M21) -> 0 | O21: =IF(N21=0,0,N21-N20) -> 0 | P21: =O21*0.05 -> 0 | Q21: =O21*0.01 -> 0 | R21: =O21*0.02 -> 0 | S21: =O21*0.025 -> 0 | T21: =SUM(O21:S21) -> 0 | V21: =IF(U21=0,0,SUM(U21)-SUM(V$5:V20)) -> 0 | W21: =T21-U21 -> 0
F22: =SUM(C22:E22) -> 0 | G22: =IF(F22=0,0,SUM(F22)-SUM(G$5:G21)) -> 0 | I22: =IF(H22=0,0,SUM(H22)-SUM(I$5:I21)) -> 0 | J22: =F22-H22 -> 0 | N22: =SUM(J22:M22) -> 0 | O22: =IF(N22=0,0,N22-N21) -> 0 | P22: =O22*0.05 -> 0 | Q22: =O22*0.01 -> 0 | R22: =O22*0.02 -> 0 | S22: =O22*0.025 -> 0 | T22: =SUM(O22:S22) -> 0 | V22: =IF(U22=0,0,SUM(U22)-SUM(V$5:V21)) -> 0 | W22: =T22-U22 -> 0
F23: =SUM(C23:E23) -> 0 | G23: =IF(F23=0,0,SUM(F23)-SUM(G$5:G22)) -> 0 | I23: =IF(H23=0,0,SUM(H23)-SUM(I$5:I22)) -> 0 | J23: =F23-H23 -> 0 | N23: =SUM(J23:M23) -> 0 | O23: =IF(N23=0,0,N23-N22) -> 0 | P23: =O23*0.05 -> 0 | Q23: =O23*0.01 -> 0 | R23: =O23*0.02 -> 0 | T23: =SUM(O23:S23) -> 0 | V23: =IF(U23=0,0,SUM(U23)-SUM(V$5:V22)) -> 0 | W23: =T23-U23 -> 0
F24: =SUM(C24:E24) -> 0 | G24: =IF(F24=0,0,SUM(F24)-SUM(G$5:G23)) -> 0 | I24: =IF(H24=0,0,SUM(H24)-SUM(I$5:I23)) -> 0 | J24: =F24-H24 -> 0 | N24: =SUM(J24:M24) -> 0 | O24: =IF(N24=0,0,N24-N23) -> 0 | P24: =O24*0.05 -> 0 | Q24: =O24*0.01 -> 0 | R24: =O24*0.02 -> 0 | T24: =SUM(O24:S24) -> 0 | V24: =IF(U24=0,0,SUM(U24)-SUM(V$5:V23)) -> 0 | W24: =T24-U24 -> 0
F25: =SUM(C25:E25) -> 0 | G25: =IF(F25=0,0,SUM(F25)-SUM(G$5:G24)) -> 0 | I25: =IF(H25=0,0,SUM(H25)-SUM(I$5:I24)) -> 0 | J25: =F25-H25 -> 0 | N25: =SUM(J25:M25) -> 0 | O25: =IF(N25=0,0,N25-N24) -> 0 | P25: =O25*0.05 -> 0 | Q25: =O25*0.01 -> 0 | R25: =O25*0.02 -> 0 | T25: =SUM(O25:S25) -> 0 | V25: =IF(U25=0,0,SUM(U25)-SUM(V$5:V24)) -> 0 | W25: =T25-U25 -> 0
F26: =SUM(C26:E26) -> 0 | G26: =IF(F26=0,0,SUM(F26)-SUM(G$5:G25)) -> 0 | I26: =IF(H26=0,0,SUM(H26)-SUM(I$5:I25)) -> 0 | J26: =F26-H26 -> 0 | N26: =SUM(J26:M26) -> 0 | O26: =IF(N26=0,0,N26-N25) -> 0 | P26: =O26*0.05 -> 0 | Q26: =O26*0.01 -> 0 | R26: =O26*0.02 -> 0 | T26: =SUM(O26:S26) -> 0 | V26: =IF(U26=0,0,SUM(U26)-SUM(V$5:V25)) -> 0 | W26: =T26-U26 -> 0
F27: =SUM(C27:E27) -> 0 | G27: =IF(F27=0,0,SUM(F27)-SUM(G$5:G26)) -> 0 | I27: =IF(H27=0,0,SUM(H27)-SUM(I$5:I26)) -> 0 | J27: =F27-H27 -> 0 | N27: =SUM(J27:M27) -> 0 | O27: =IF(N27=0,0,N27-N26) -> 0 | P27: =O27*0.05 -> 0 | Q27: =O27*0.01 -> 0 | R27: =O27*0.02 -> 0 | T27: =SUM(O27:S27) -> 0 | V27: =IF(U27=0,0,SUM(U27)-SUM(V$5:V26)) -> 0 | W27: =T27-U27 -> 0
F28: =SUM(C28:E28) -> 0 | G28: =IF(F28=0,0,SUM(F28)-SUM(G$5:G27)) -> 0 | I28: =IF(H28=0,0,SUM(H28)-SUM(I$5:I27)) -> 0 | J28: =F28-H28 -> 0 | N28: =SUM(J28:M28) -> 0 | O28: =IF(N28=0,0,N28-N27) -> 0 | P28: =O28*0.05 -> 0 | Q28: =O28*0.01 -> 0 | R28: =O28*0.02 -> 0 | T28: =SUM(O28:S28) -> 0 | V28: =IF(U28=0,0,SUM(U28)-SUM(V$5:V27)) -> 0 | W28: =T28-U28 -> 0
F29: =SUM(C29:E29) -> 0 | G29: =IF(F29=0,0,SUM(F29)-SUM(G$5:G28)) -> 0 | I29: =IF(H29=0,0,SUM(H29)-SUM(I$5:I28)) -> 0 | J29: =F29-H29 -> 0 | N29: =SUM(J29:M29) -> 0 | O29: =IF(N29=0,0,N29-N28) -> 0 | P29: =O29*0.05 -> 0 | Q29: =O29*0.01 -> 0 | R29: =O29*0.02 -> 0 | T29: =SUM(O29:S29) -> 0 | V29: =IF(U29=0,0,SUM(U29)-SUM(V$5:V28)) -> 0 | W29: =T29-U29 -> 0
F30: =SUM(C30:E30) -> 0 | G30: =IF(F30=0,0,SUM(F30)-SUM(G$5:G29)) -> 0 | I30: =IF(H30=0,0,SUM(H30)-SUM(I$5:I29)) -> 0 | J30: =F30-H30 -> 0 | N30: =SUM(J30:M30) -> 0 | O30: =IF(N30=0,0,N30-N29) -> 0 | P30: =O30*0.05 -> 0 | Q30: =O30*0.01 -> 0 | R30: =O30*0.02 -> 0 | T30: =SUM(O30:S30) -> 0 | V30: =IF(U30=0,0,SUM(U30)-SUM(V$5:V29)) -> 0 | W30: =T30-U30 -> 0
F31: =SUM(C31:E31) -> 0 | G31: =IF(F31=0,0,SUM(F31)-SUM(G$5:G30)) -> 0 | I31: =IF(H31=0,0,SUM(H31)-SUM(I$5:I30)) -> 0 | J31: =F31-H31 -> 0 | N31: =SUM(J31:M31) -> 0 | O31: =IF(N31=0,0,N31-N30) -> 0 | P31: =O31*0.05 -> 0 | Q31: =O31*0.01 -> 0 | R31: =O31*0.02 -> 0 | T31: =SUM(O31:S31) -> 0 | V31: =IF(U31=0,0,SUM(U31)-SUM(V$5:V30)) -> 0 | W31: =T31-U31 -> 0
A32: Totals | H32: =SUM(G5:G31) -> 0 | I32: =SUM(I5:I31) -> 0 | K32: =SUM(K5:K31) -> 0 | L32: =SUM(L5:L31) -> 0 | M32: =SUM(M5:M31) -> 0 | N32: =SUM(N5:N31) -> 0 | P32: =SUM(P5:P31) -> 0 | Q32: =SUM(Q5:Q31) -> 0 | R32: =SUM(R5:R31) -> 0 | S32: =SUM(S5:S31) -> 0 | T32: =SUM(T5:T31) -> 0 | V32: =SUM(V5:V31) -> 0 | W32: =SUM(W5:W31) -> 0
H33: ="Add VAT - "&Lists!$M$4*100&"%" -> Add VAT - 7.5% | I33: =I32*Lists!$M$4 -> 0 | K33: =K32*Lists!$M$4 -> 0 | U33: ="Add VAT - "&Lists!$M$4*100&"%" -> Add VAT - 7.5% | V33: 0
H34: Total Retention Deducted - Inc. VAT: | I34: =SUM(I32:I33) -> 0 | J34: Ret. Rel. - Inc VAT: | K34: =SUM(K32:K33) -> 0 | U34: Total Advance Recovered - Including VAT: | V34: =SUM(V32:V33) -> 0
A37: SUMMARY CERT STATUS
A38: Vetted | C38: =SUMIF($X$5:$X$31,$A38,C$5:C$31) -> 0 | D38: =SUMIF($X$5:$X$31,$A38,D$5:D$31) -> 0 | N38: =SUMIF($X$5:$X$31,$A38,N$5:N$31) -> 0 | W38: =SUMIF($X$5:$X$31,$A38,W$5:W$31) -> 0
A39: Not Vetted | C39: =SUMIF($X$5:$X$31,$A39,C$5:C$31) -> 0 | D39: =SUMIF($X$5:$X$31,$A39,D$5:D$31) -> 0 | N39: =SUMIF($X$5:$X$31,$A39,N$5:N$31) -> 0 | W39: =SUMIF($X$5:$X$31,$A39,W$5:W$31) -> 0
C40: =SUM(C38:C39) -> 0 | D40: =SUM(D38:D39) -> 0 | N40: =SUM(N38:N39) -> 0 | W40: =SUM(W38:W39) -> 0

Sheet Payments Recieved
A1: PAYMENTS RECEIVED | F1: Date: | G1: ='Contract Summary'!E1 -> 45717 | I1: Week No: | J1: =IF(G1=0,0,VLOOKUP(G1,Lists!A2:B5000,2,FALSE)) -> 9 | K1: Instructions
A2: ='Contract Summary'!C4 -> PROPOSED CONSTRUCTION OF 15 SPAN, DUAL CARRIAGEWAY, 6TH BRIDGE OVER RIVER KADUNA AND APPROACH ROADS
A3: PAYMENT DETAILS | E3: DEDUCTIONS | L3: Deductions %
A4: Date | B4: Voucher Number | C4: Payment Type | D4: Gross Amount (Including VAT) | E4: WHT | F4: VAT | G4: Vetting Fee | H4: Stamp Duty | I4: Other | J4: Net Amount Payable | L4: VAT % | M4: WHT % | N4: State Levy % | O4: Stamp Duty % | P4: Other %
B5: Advance No. 1 | C5: Advance | D5: 0 | E5: =2.5%*D5 -> 0 | F5: =7.5%*D5 -> 0 | G5: =0.5%*D5 -> 0 | H5: =1%*D5 -> 0 | I5: 0 | J5: =D5-SUM(E5:I5) -> 0 | L5: =IF(D5=0,0,E5/$D5) -> 0 | M5: =IF(E5=0,0,F5/$D5) -> 0 | N5: =IF(F5=0,0,G5/$D5) -> 0 | O5: =IF(G5=0,0,H5/$D5) -> 0 | P5: =IF(H5=0,0,I5/$D5) -> 0
B6: Cert No 2 | C6: Cert | D6: 0 | E6: =2.5%*D6 -> 0 | F6: =7.5%*D6 -> 0 | G6: =0.5%*D6 -> 0 | H6: =1%*D6 -> 0 | I6: 0 | J6: =D6-SUM(E6:I6) -> 0 | L6: =IF(D6=0,0,E6/$D6) -> 0 | M6: =IF(E6=0,0,F6/$D6) -> 0 | N6: =IF(F6=0,0,G6/$D6) -> 0 | O6: =IF(G6=0,0,H6/$D6) -> 0 | P6: =IF(H6=0,0,I6/$D6) -> 0
G7: 0 | H7: 0 | I7: 0 | J7: =D7-SUM(E7:I7) -> 0 | L7: =IF(D7=0,0,E7/$D7) -> 0 | M7: =IF(E7=0,0,F7/$D7) -> 0 | N7: =IF(F7=0,0,G7/$D7) -> 0 | O7: =IF(G7=0,0,H7/$D7) -> 0 | P7: =IF(H7=0,0,I7/$D7) -> 0
G8: 0 | H8: 0 | I8: 0 | J8: =D8-SUM(E8:I8) -> 0 | L8: =IF(D8=0,0,E8/$D8) -> 0 | M8: =IF(E8=0,0,F8/$D8) -> 0 | N8: =IF(F8=0,0,G8/$D8) -> 0 | O8: =IF(G8=0,0,H8/$D8) -> 0 | P8: =IF(H8=0,0,I8/$D8) -> 0
G9: 0 | H9: 0 | I9: 0 | J9: =D9-SUM(E9:I9) -> 0 | L9: =IF(D9=0,0,E9/$D9) -> 0 | M9: =IF(E9=0,0,F9/$D9) -> 0 | N9: =IF(F9=0,0,G9/$D9) -> 0 | O9: =IF(G9=0,0,H9/$D9) -> 0 | P9: =IF(H9=0,0,I9/$D9) -> 0
G10: 0 | H10: 0 | I10: 0 | J10: =D10-SUM(E10:I10) -> 0 | L10: =IF(D10=0,0,E10/$D10) -> 0 | M10: =IF(E10=0,0,F10/$D10) -> 0 | N10: =IF(F10=0,0,G10/$D10) -> 0 | O10: =IF(G10=0,0,H10/$D10) -> 0 | P10: =IF(H10=0,0,I10/$D10) -> 0
E11: =D11/1.05*0.05 -> 0 | G11: 0 | H11: 0 | I11: 0 | J11: =D11-SUM(E11:I11) -> 0 | L11: =IF(D11=0,0,E11/$D11) -> 0 | M11: =IF(E11=0,0,F11/$D11) -> 0 | N11: =IF(F11=0,0,G11/$D11) -> 0 | O11: =IF(G11=0,0,H11/$D11) -> 0 | P11: =IF(H11=0,0,I11/$D11) -> 0
E12: =D12/1.05*0.05 -> 0 | F12: =D12/1.05*0.05 -> 0 | J12: =D12-SUM(E12:I12) -> 0 | L12: =IF(D12=0,0,E12/$D12) -> 0 | M12: =IF(E12=0,0,F12/$D12) -> 0 | N12: =IF(F12=0,0,G12/$D12) -> 0 | O12: =IF(G12=0,0,H12/$D12) -> 0 | P12: =IF(H12=0,0,I12/$D12) -> 0
E13: =D13/1.05*0.05 -> 0 | F13: =D13/1.05*0.05 -> 0 | J13: =D13-SUM(E13:I13) -> 0 | L13: =IF(D13=0,0,E13/$D13) -> 0 | M13: =IF(E13=0,0,F13/$D13) -> 0 | N13: =IF(F13=0,0,G13/$D13) -> 0 | O13: =IF(G13=0,0,H13/$D13) -> 0 | P13: =IF(H13=0,0,I13/$D13) -> 0
J14: =D14-SUM(E14:I14) -> 0 | L14: =IF(D14=0,0,E14/$D14) -> 0 | M14: =IF(E14=0,0,F14/$D14) -> 0 | N14: =IF(F14=0,0,G14/$D14) -> 0 | O14: =IF(G14=0,0,H14/$D14) -> 0 | P14: =IF(H14=0,0,I14/$D14) -> 0
J15: =D15-SUM(E15:I15) -> 0 | L15: =IF(D15=0,0,E15/$D15) -> 0 | M15: =IF(E15=0,0,F15/$D15) -> 0 | N15: =IF(F15=0,0,G15/$D15) -> 0 | O15: =IF(G15=0,0,H15/$D15) -> 0 | P15: =IF(H15=0,0,I15/$D15) -> 0
J16: =D16-SUM(E16:I16) -> 0 | L16: =IF(D16=0,0,E16/$D16) -> 0 | M16: =IF(E16=0,0,F16/$D16) -> 0 | N16: =IF(F16=0,0,G16/$D16) -> 0 | O16: =IF(G16=0,0,H16/$D16) -> 0 | P16: =IF(H16=0,0,I16/$D16) -> 0
J17: =D17-SUM(E17:I17) -> 0 | L17: =IF(D17=0,0,E17/$D17) -> 0 | M17: =IF(E17=0,0,F17/$D17) -> 0 | N17: =IF(F17=0,0,G17/$D17) -> 0 | O17: =IF(G17=0,0,H17/$D17) -> 0 | P17: =IF(H17=0,0,I17/$D17) -> 0
J18: =D18-SUM(E18:I18) -> 0 | L18: =IF(D18=0,0,E18/$D18) -> 0 | M18: =IF(E18=0,0,F18/$D18) -> 0 | N18: =IF(F18=0,0,G18/$D18) -> 0 | O18: =IF(G18=0,0,H18/$D18) -> 0 | P18: =IF(H18=0,0,I18/$D18) -> 0
J19: =D19-SUM(E19:I19) -> 0 | L19: =IF(D19=0,0,E19/$D19) -> 0 | M19: =IF(E19=0,0,F19/$D19) -> 0 | N19: =IF(F19=0,0,G19/$D19) -> 0 | O19: =IF(G19=0,0,H19/$D19) -> 0 | P19: =IF(H19=0,0,I19/$D19) -> 0
J20: =D20-SUM(E20:I20) -> 0 | L20: =IF(D20=0,0,E20/$D20) -> 0 | M20: =IF(E20=0,0,F20/$D20) -> 0 | N20: =IF(F20=0,0,G20/$D20) -> 0 | O20: =IF(G20=0,0,H20/$D20) -> 0 | P20: =IF(H20=0,0,I20/$D20) -> 0
J21: =D21-SUM(E21:I21) -> 0 | L21: =IF(D21=0,0,E21/$D21) -> 0 | M21: =IF(E21=0,0,F21/$D21) -> 0 | N21: =IF(F21=0,0,G21/$D21) -> 0 | O21: =IF(G21=0,0,H21/$D21) -> 0 | P21: =IF(H21=0,0,I21/$D21) -> 0
J22: =D22-SUM(E22:I22) -> 0 | L22: =IF(D22=0,0,E22/$D22) -> 0 | M22: =IF(E22=0,0,F22/$D22) -> 0 | N22: =IF(F22=0,0,G22/$D22) -> 0 | O22: =IF(G22=0,0,H22/$D22) -> 0 | P22: =IF(H22=0,0,I22/$D22) -> 0
J23: =D23-SUM(E23:I23) -> 0 | L23: =IF(D23=0,0,E23/$D23) -> 0 | M23: =IF(E23=0,0,F23/$D23) -> 0 | N23: =IF(F23=0,0,G23/$D23) -> 0 | O23: =IF(G23=0,0,H23/$D23) -> 0 | P23: =IF(H23=0,0,I23/$D23) -> 0
J24: =D24-SUM(E24:I24) -> 0 | L24: =IF(D24=0,0,E24/$D24) -> 0 | M24: =IF(E24=0,0,F24/$D24) -> 0 | N24: =IF(F24=0,0,G24/$D24) -> 0 | O24: =IF(G24=0,0,H24/$D24) -> 0 | P24: =IF(H24=0,0,I24/$D24) -> 0
J25: =D25-SUM(E25:I25) -> 0 | L25: =IF(D25=0,0,E25/$D25) -> 0 | M25: =IF(E25=0,0,F25/$D25) -> 0 | N25: =IF(F25=0,0,G25/$D25) -> 0 | O25: =IF(G25=0,0,H25/$D25) -> 0 | P25: =IF(H25=0,0,I25/$D25) -> 0
... J37: =D37-SUM(E37:I37) -> 0 | L37: =IF(D37=0,0,E37/$D37) -> 0 | M37: =IF(E37=0,0,F37/$D37) -> 0 | N37: =IF(F37=0,0,G37/$D37) -> 0 | O37: =IF(G37=0,0,H37/$D37) -> 0 | P37: =IF(H37=0,0,I37/$D37) -> 0
A38: Total All: | D38: =SUM(D5:D37) -> 0 | E38: =SUM(E5:E37) -> 0 | F38: =SUM(F5:F37) -> 0 | G38: =SUM(G5:G37) -> 0 | H38: =SUM(H5:H37) -> 0 | I38: =SUM(I5:I37) -> 0 | J38: =SUM(J5:J37) -> 0 | L38: =IF(D38=0,0,E38/$D38) -> 0 | M38: =IF(E38=0,0,F38/$D38) -> 0 | N38: =IF(F38=0,0,G38/$D38) -> 0 | O38: =IF(G38=0,0,H38/$D38) -> 0 | P38: =IF(H38=0,0,I38/$D38) -> 0
D40: =D38-D5 -> 0

Sheet Cost Report
C1: COST REPORT | H1: Date: | I1: ='Contract Summary'!E1 -> 45717 | J1: Week No: | K1: =IF(I1=0,0,VLOOKUP(I1,Lists!A2:B5000,2,FALSE)) -> 9 | L1: Instructions
C2: ='[1]Contract Summary'!C4 -> CONSTRUCTION OF BUA LAFIAGI BYPASS ROAD | D2: ='Payments Recieved'!A2 -> PROPOSED CONSTRUCTION OF 15 SPAN, DUAL CARRIAGEWAY, 6TH BRIDGE OVER RIVER KADUNA AND APPROACH ROADS
C3: S/No | D3: Description | E3: Cost Category | F3: Unit | G3: Quantity This Week | H3: Rate N | I3: Amount Previous Week | J3: Amount This Week | K3: Amount Up to Date | M3: Source Legend | N3: Source Detail
C4: PLANT DEPARTMENT | M4: PLANT DEPARTMENT | N4: All information should be obtained from the plant department reports.
C5: 1 | D5: Diesel | E5: AGO | F5: Litres | G5: ='Diesel Consumption'!K91 -> 2193 | H5: 1100 | I5: 177509365 | J5: =G5*H5 -> 2412300 | K5: =I5+J5 -> 179921665 | M5: MATERIALS | N5: All information is auto populated from the materials reconcilaition sheet, other than the Amount Previous Week
C6: 2 | D6: Diesel (P.W. External Issues) | E6: AGO | F6: Litres | H6: =H5 -> 1100 | I6: 0 | J6: ='[1]Diesel Consumption'!O117 -> 0 | K6: =I6+J6 -> 0 | M6: OTHER MATERIALS | N6: Other material not captured on the materails & civils report that may be used on site.
C7: 3 | D7: Plant Internal | E7: Plant | F7: N/a | I7: 1.2189104e+08 | J7: ='Plant Return'!H83 -> 2516666.5 | K7: =I7+J7 -> 1.244077e+08 | M7: OTHER SITE COSTS | N7: All information is auto populated from the headcount and subcontractors report, other than the Amount Previous Week
C8: 4 | D8: Hired Plant/Equipment/Vehicle | E8: Plant | F8: N/a | I8: 813000 | J8: ='Hired Vehicles'!H25 -> 15000 | K8: =I8+J8 -> 828000 | M8: SITE LEVEL ACCOUNTS | N8: All information is obtained from the site accountant weekly financial report.
C9: 5 | D9: Petrol | E9: Plant | F9: Litres | G9: 162.3 | H9: 1000 | I9: 9520945.1 | J9: =G9*H9 -> 162300 | K9: =I9+J9 -> 9683245.1 | M9: OVERHEADS | N9: Information is provided by the PM other than Bill 1 information which is provided by the Accountant in completing the Bill 1 schedule.
C10: 6 | D10: Stores Cost | E10: Plant | F10: Various | J10: 0
C11: 7 | D11: Engine Oil | E11: Plant | F11: Litres | G11: 53 | H11: 4097.56 | I11: 14865204 | J11: =G11*H11 -> 217170.68 | K11: =I11+J11 -> 15082375
C12: 8 | D12: Gear oil | E12: Plant | F12: Litres | G12: 14 | H12: 6786 | I12: 1767586.3 | J12: =G12*H12 -> 95004 | K12: =I12+J12 -> 1862590.3
C13: 9 | D13: ATF 220 Oil | E13: Plant | F13: Litres | G13: 0 | H13: 6171 | I13: 601902.44 | J13: =G13*H13 -> 0 | K13: =I13+J13 -> 601902.44
C14: 10 | D14: Hydroualic Oil Azzolla | E14: Plant | F14: Litres | G14: 33 | H14: 3292.69 | I14: 2334807.1 | J14: =G14*H14 -> 108658.77 | K14: =I14+J14 -> 2443465.8
C15: 11 | D15: Rarius 427 Comp. Oil | E15: Plant | F15: Litres | H15: 0 | I15: 0 | J15: =G15*H15 -> 0 | K15: =I15+J15 -> 0
C16: 12 | D16: Almo 529 | E16: Plant | F16: Litres | H16: 0 | I16: 0 | J16: =G16*H16 -> 0 | K16: =I16+J16 -> 0
C17: 13 | D17: Grease | E17: Plant | F17: Kg | G17: 10 | H17: 12100 | I17: 984180 | J17: =G17*H17 -> 121000 | K17: =I17+J17 -> 1105180
C18: 14 | D18: 6440; Tyres | E18: Plant | F18: Each | I18: 0 | K18: =I18+J18 -> 0
C19: MATERIALS | I19: 0 | J19: =G19*H19 -> 0 | K19: =I19+J19 -> 0
C20: ='[1]Materials & Civils'!A5 -> 1 | D20: Cement (Bags) | E20: Materials | F20: =IF(ISBLANK('[1]Materials & Civils'!C5),"",'[1]Materials & Civils'!C5) -> Bags | G20: ='Materials & Civils'!N5 -> 468 | H20: 4650 | I20: 149870500 | J20: =G20*H20 -> 2176200 | K20: =I20+J20 -> 152046700
C21: ='[1]Materials & Civils'!A6 -> 2 | D21: Cement (Bulk) | E21: Materials | F21: =IF(ISBLANK('[1]Materials & Civils'!C6),"",'[1]Materials & Civils'!C6) -> Tonnes | G21: ='Materials & Civils'!N6 -> 0 | H21: =IF(D21="",0,VLOOKUP(D21,'Materials & Civils'!$B$5:$N$38,3,FALSE)) -> 95000 | I21: 0 | J21: =G21*H21 -> 0 | K21: =I21+J21 -> 0
C22: ='[1]Materials & Civils'!A7 -> 3 | D22: Rebar (10mm) Local | E22: Materials | F22: =IF(ISBLANK('[1]Materials & Civils'!C7),"",'[1]Materials & Civils'!C7) -> Tonnes | G22: ='Materials & Civils'!N7 -> 1.312185 | H22: 550000 | I22: 15191382 | J22: =G22*H22 -> 721701.75 | K22: =I22+J22 -> 15913084
C23: ='[1]Materials & Civils'!A8 -> 4 | D23: Rebar (12mm) Local | E23: Materials | F23: =IF(ISBLANK('[1]Materials & Civils'!C8),"",'[1]Materials & Civils'!C8) -> Tonnes | G23: ='Materials & Civils'!N8 -> 1.5431486 | H23: 550000 | I23: 36252567 | J23: =G23*H23 -> 848731.75 | K23: =I23+J23 -> 37101299
C24: ='[1]Materials & Civils'!A9 -> 5 | D24: Rebar (16mm) Local | E24: Materials | F24: =IF(ISBLANK('[1]Materials & Civils'!C9),"",'[1]Materials & Civils'!C9) -> Tonnes | G24: ='Materials & Civils'!N9 -> 1.5892272 | H24: 550000 | I24: 33672342 | J24: =G24*H24 -> 874074.96 | K24: =I24+J24 -> 34546417
C25: ='[1]Materials & Civils'!A10 -> 6 | D25: Rebar (12mm) Imported | E25: Materials | F25: =IF(ISBLANK('[1]Materials & Civils'!C10),"",'[1]Materials & Civils'!C10) -> Tonnes | G25: ='Materials & Civils'!N10 -> 0 | H25: 550000 | I25: 0 | J25: =G25*H25 -> 0 | K25: =I25+J25 -> 0
C26: ='[1]Materials & Civils'!A11 -> 7 | D26: Rebar (16mm) Imported | E26: Materials | F26: =IF(ISBLANK('[1]Materials & Civils'!C11),"",'[1]Materials & Civils'!C11) -> Tonnes | G26: ='Materials & Civils'!N11 -> 0 | H26: 550000 | I26: 0 | J26: =G26*H26 -> 0 | K26: =I26+J26 -> 0
C27: ='[1]Materials & Civils'!A12 -> 8 | D27: Rebar (20mm) Imported | E27: Materials | F27: =IF(ISBLANK('[1]Materials & Civils'!C12),"",'[1]Materials & Civils'!C12) -> Tonnes | G27: ='Materials & Civils'!N12 -> 0 | H27: 550000 | I27: 0 | J27: =G27*H27 -> 0 | K27: =I27+J27 -> 0
C28: ='[1]Materials & Civils'!A13 -> 9 | D28: Rebar (25mm) Imported | E28: Materials | F28: =IF(ISBLANK('[1]Materials & Civils'!C13),"",'[1]Materials & Civils'!C13) -> Tonnes | G28: ='Materials & Civils'!N13 -> 9.536976 | H28: 550000 | I28: 1.672038e+08 | J28: =G28*H28 -> 5245336.8 | K28: =I28+J28 -> 1.7244914e+08
C29: ='[1]Materials & Civils'!A13 -> 9 | D29: Rebar (32mm) Imported | E29: Materials | F29: Tonne | G29: ='Materials & Civils'!N14 -> 0 | H29: 550000 | I29: 0 | J29: =G29*H29 -> 0 | K29: =I29+J29 -> 0
C30: ='[1]Materials & Civils'!A14 -> 10 | D30: Binding Wire | E30: Materials | F30: Roll | G30: ='Materials & Civils'!N15 -> 0 | H30: 14000 | I30: 252000 | J30: =G30*H30 -> 0 | K30: =I30+J30 -> 252000
C31: ='[1]Materials & Civils'!A15 -> 11 | D31: =IF(ISBLANK('[1]Materials & Civils'!B15),"",'[1]Materials & Civils'!B15) -> Sharp Sand | E31: Materials | F31: =IF(ISBLANK('[1]Materials & Civils'!C15),"",'[1]Materials & Civils'!C15) -> Tonnes | G31: ='Materials & Civils'!J16 -> 47.199421 | H31: 3000 | I31: 11495641 | J31: =G31*H31 -> 141598.26 | K31: =I31+J31 -> 11637239
C32: ='[1]Materials & Civils'!A16 -> 12 | D32: =IF(ISBLANK('[1]Materials & Civils'!B16),"",'[1]Materials & Civils'!B16) -> Blocks 9" | E32: Materials | F32: =IF(ISBLANK('[1]Materials & Civils'!C16),"",'[1]Materials & Civils'!C16) -> Each | G32: ='Materials & Civils'!J17 -> 0 | H32: 600 | I32: 1144810 | J32: =G32*H32 -> 0 | K32: =I32+J32 -> 1144810
C33: ='[1]Materials & Civils'!A17 -> 13 | D33: =IF(ISBLANK('[1]Materials & Civils'!B17),"",'[1]Materials & Civils'!B17) -> Geotextile | E33: Materials | F33: =IF(ISBLANK('[1]Materials & Civils'!C17),"",'[1]Materials & Civils'!C17) -> M2 | G33: ='Materials & Civils'!J18 -> 0 | H33: =IF(D33="",0,VLOOKUP(D33,'[1]Materials & Civils'!$B$5:$N$42,3,FALSE)) -> 1200000 | I33: 0 | J33: =G33*H33 -> 0 | K33: =I33+J33 -> 0
C34: ='[1]Materials & Civils'!A18 -> 14 | D34: =IF(ISBLANK('[1]Materials & Civils'!B18),"",'[1]Materials & Civils'!B18) -> UPVC Pipe(300mm) | E34: Materials | F34: =IF(ISBLANK('[1]Materials & Civils'!C18),"",'[1]Materials & Civils'!C18) -> Each | G34: ='Materials & Civils'!J18 -> 0 | H34: =IF(D34="",0,VLOOKUP(D34,'[1]Materials & Civils'!$B$5:$N$42,3,FALSE)) -> 2800 | I34: 0 | J34: =G34*H34 -> 0 | K34: =I34+J34 -> 0
C35: ='[1]Materials & Civils'!A19 -> 15 | D35: =IF(ISBLANK('[1]Materials & Civils'!B19),"",'[1]Materials & Civils'!B19) -> UPVC Pipe(100mm) | E35: Materials | F35: =IF(ISBLANK('[1]Materials & Civils'!C19),"",'[1]Materials & Civils'!C19) -> Each | G35: ='Materials & Civils'!J19 -> 0 | H35: =IF(D35="",0,VLOOKUP(D35,'[1]Materials & Civils'!$B$5:$N$42,3,FALSE)) -> 3800 | I35: 0 | J35: =G35*H35 -> 0 | K35: =I35+J35 -> 0
C36: ='[1]Materials & Civils'!A20 -> 16 | D36: =IF(ISBLANK('[1]Materials & Civils'!B20),"",'[1]Materials & Civils'!B20) -> Interlocking Paving Stone | E36: Materials | F36: =IF(ISBLANK('[1]Materials & Civils'!C20),"",'[1]Materials & Civils'!C20) -> m2 | G36: =IF(D36="",0,VLOOKUP(D36,'[1]Materials & Civils'!$B$5:$N$42,13,FALSE)) -> 0 | H36: =IF(D36="",0,VLOOKUP(D36,'[1]Materials & Civils'!$B$5:$N$42,3,FALSE)) -> 3600 | I36: 0 | J36: =G36*H36 -> 0 | K36: =I36+J36 -> 0
C37: ='[1]Materials & Civils'!A21 -> 17 | D37: =IF(ISBLANK('[1]Materials & Civils'!B21),"",'[1]Materials & Civils'!B21) -> Precast Units | E37: Materials | F37: =IF(ISBLANK('[1]Materials & Civils'!C21),"",'[1]Materials & Civils'!C21) -> LM | G37: =Precast!G4 -> 0 | H37: =IF(D37="",0,VLOOKUP(D37,'[1]Materials & Civils'!$B$5:$N$42,3,FALSE)) -> 25000 | I37: 0 | J37: =G37*H37 -> 0 | K37: =I37+J37 -> 0
C38: ='[1]Materials & Civils'!A25 -> QUARRY MATERIALS | F38: =IF(ISBLANK('[1]Materials & Civils'!C25),"",'[1]Materials & Civils'!C25) -> 0
C39: 18 | D39: =IF(ISBLANK('[1]Materials & Civils'!B27),"",'[1]Materials & Civils'!B27) -> 3/4" Aggregates | E39: Materials | F39: =IF(ISBLANK('[1]Materials & Civils'!C27),"",'[1]Materials & Civils'!C27) -> Tonnes | G39: ='Materials & Civils'!J23 -> 13.734023 | H39: 8350 | I39: 15196029 | J39: =G39*H39 -> 114679.09 | K39: =I39+J39 -> 15310708
C40: 19 | D40: =IF(ISBLANK('[1]Materials & Civils'!B28),"",'[1]Materials & Civils'!B28) -> 1/2" Aggregates | E40: Materials | F40: =IF(ISBLANK('[1]Materials & Civils'!C28),"",'[1]Materials & Civils'!C28) -> Tonnes | G40: ='Materials & Civils'!J22 -> 39.589687 | H40: 8350 | I40: 22873503 | J40: =G40*H40 -> 330573.89 | K40: =I40+J40 -> 23204077
C41: 20 | D41: =IF(ISBLANK('[1]Materials & Civils'!B29),"",'[1]Materials & Civils'!B29) -> 3/8" Aggregates | E41: Materials | F41: =IF(ISBLANK('[1]Materials & Civils'!C29),"",'[1]Materials & Civils'!C29) -> Tonnes | G41: ='Materials & Civils'!J24 -> 0 | H41: 8350 | I41: 0 | J41: =G41*H41 -> 0 | K41: =I41+J41 -> 0
C42: 21 | D42: Sand | E42: Materials | F42: =IF(ISBLANK('[1]Materials & Civils'!C30),"",'[1]Materials & Civils'!C30) -> Tonnes | G42: ='Materials & Civils'!J25 -> 0 | H42: 3000 | I42: 0 | J42: =G42*H42 -> 0 | K42: =I42+J42 -> 0
C43: 22 | D43: =IF(ISBLANK('[1]Materials & Civils'!B30),"",'[1]Materials & Civils'!B30) -> Stone Base | E43: Materials | F43: =IF(ISBLANK('[1]Materials & Civils'!C30),"",'[1]Materials & Civils'!C30) -> Tonnes | G43: ='Materials & Civils'!J26 -> 0 | H43: =IF(D43="",0,VLOOKUP(D43,'Materials & Civils'!$B$5:$N$38,3,FALSE)) -> 6500 | I43: 0 | J43: =G43*H43 -> 0 | K43: =I43+J43 -> 0
C44: 23 | D44: Hardcore | E44: Materials | F44: =IF(ISBLANK('[1]Materials & Civils'!C30),"",'[1]Materials & Civils'!C30) -> Tonnes | G44: ='Materials & Civils'!J27 -> 0 | H44: 6500 | I44: 0 | J44: =G44*H44 -> 0 | K44: =I44+J44 -> 0
C45: 24 | D45: =IF(ISBLANK('[1]Materials & Civils'!B31),"",'[1]Materials & Civils'!B31) -> MC1 | E45: Materials | F45: =IF(ISBLANK('[1]Materials & Civils'!C31),"",'[1]Materials & Civils'!C31) -> Tonne | G45: ='Materials & Civils'!J28 -> 0 | H45: 0 | I45: 0 | J45: =G45*H45 -> 0 | K45: =I45+J45 -> 0
C46: 25 | D46: =IF(ISBLANK('[1]Materials & Civils'!B32),"",'[1]Materials & Civils'!B32) -> Tack Coat (MC1) | E46: Materials | F46: =IF(ISBLANK('[1]Materials & Civils'!C32),"",'[1]Materials & Civils'!C32) -> Litres | G46: =IF(D46="",0,VLOOKUP(D46,'[1]Materials & Civils'!$B$5:$N$42,13,FALSE)) -> 0 | H46: 0 | I46: 0 | J46: =G46*H46 -> 0 | K46: =I46+J46 -> 0
C47: 26 | D47: =IF(ISBLANK('[1]Materials & Civils'!B33),"",'[1]Materials & Civils'!B33) -> S125 | E47: Materials | F47: =IF(ISBLANK('[1]Materials & Civils'!C33),"",'[1]Materials & Civils'!C33) -> Litres | G47: =IF(D47="",0,VLOOKUP(D47,'[1]Materials & Civils'!$B$5:$N$42,13,FALSE)) -> 0 | H47: 0 | I47: 0 | J47: =G47*H47 -> 0 | K47: =I47+J47 -> 0
C48: 27 | D48: =IF(ISBLANK('[1]Materials & Civils'!B34),"",'[1]Materials & Civils'!B34) -> Wearing Course Asphalt | E48: Materials | F48: =IF(ISBLANK('[1]Materials & Civils'!C34),"",'[1]Materials & Civils'!C34) -> Tonnes | G48: =IF(D48="",0,VLOOKUP(D48,'[1]Materials & Civils'!$B$5:$N$42,13,FALSE)) -> 0 | H48: 0 | I48: 0 | J48: =G48*H48 -> 0 | K48: =I48+J48 -> 0
C49: 28 | D49: =IF(ISBLANK('[1]Materials & Civils'!B35),"",'[1]Materials & Civils'!B35) -> Binder Course Asphalt | E49: Materials | F49: =IF(ISBLANK('[1]Materials & Civils'!C35),"",'[1]Materials & Civils'!C35) -> Tonnes | G49: =IF(D49="",0,VLOOKUP(D49,'[1]Materials & Civils'!$B$5:$N$42,13,FALSE)) -> 0 | H49: 0 | I49: 0 | J49: =G49*H49 -> 0 | K49: =I49+J49 -> 0
C50: 29 | D50: =IF(ISBLANK('[1]Materials & Civils'!B37),"",'[1]Materials & Civils'!B37) -> Borrow Pit | E50: Materials | F50: =IF(ISBLANK('[1]Materials & Civils'!C37),"",'[1]Materials & Civils'!C37) -> m2 | G50: =IF(D50="",0,VLOOKUP(D50,'[1]Materials & Civils'!$B$5:$N$42,13,FALSE)) -> 0 | H50: 0 | I50: 0 | J50: =G50*H50 -> 0 | K50: =I50+J50 -> 0
C51: OTHER MATERIALS
C52: 1 | D52: 6400; Timber | E52: Materials | I52: 0 | K52: =I52+J52 -> 0
C53: 2 | D53: Diesel (P.W. External Issues) | E53: AGO | F53: Litre | H53: 1100 | I53: 0 | J53: =G53*H53 -> 0 | K53: =I53+J53 -> 0
C54: 3 | I54: 0 | K54: =I54+J54 -> 0
C55: OTHER SITE COSTS | I55: 0 | K55: =I55+J55 -> 0
C56: 1 | D56: Sub-Contractor's Expenses | E56: Sub Contractors | I56: 34045601 | J56: =Subcontractors!N100 -> 0 | K56: =I56+J56 -> 34045601
C57: 2 | D57: Labour | E57: Local Labour | F57: No. | G57: ='Labour Strength'!C19 -> 51 | H57: =[1]Lists!M5 -> 25000 | I57: 74500000 | J57: =G57*H57 -> 1275000 | K57: =I57+J57 -> 75775000
I58: 0 | K58: =I58+J58 -> 0
C59: SITE LEVEL ACCOUNTS | I59: 0 | K59: =I59+J59 -> 0
C60: 1 | D60: 6320; Spare Parts | E60: Plant | I60: 4675080 | J60: 34000 | K60: =I60+J60 -> 4709080
C61: 2 | D61: 1041; Building & Site Development | E61: Site Level Expenses | I61: 261500 | K61: =I61+J61 -> 261500
C62: 3 | D62: 6021; P.W. Tippers (Haulage-fees) | E62: Materials | I62: 0 | K62: =I62+J62 -> 0
C63: 4 | D63: 6100; Compensation | E63: Site Level Expenses | I63: 245000 | K63: =I63+J63 -> 245000
C64: 5 | D64: 6230; Security Expenses | E64: Site Level Expenses | I64: 18769500 | J64: 265000 | K64: =I64+J64 -> 19034500
C65: 6 | D65: 6300; Steel Plate/Reinforcement | E65: Plant | I65: 276000 | K65: =I65+J65 -> 276000
C66: 7 | D66: 6350; Materials | E66: Materials | I66: 6630000 | K66: =I66+J66 -> 6630000
C67: 8 | D67: 6420; Tools and Consumables | E67: Site Level Expenses | I67: 70395465 | J67: 140007 | K67: =I67+J67 -> 70535472
C68: 9 | D68: 6220; External Labour | E68: Local Labour | I68: 4387600 | J68: 89500 | K68: =I68+J68 -> 4477100
C69: 10 | D69: 6540; Sundry Expenses | E69: Site Level Expenses | I69: 10700950 | K69: =I69+J69 -> 10700950
C70: 11 | D70: 7020; Miscellaneous Running Costs/Expenses | E70: Site Level Expenses | I70: 5973093 | K70: =I70+J70 -> 5973093
C71: 12 | D71: 7220; Expatriate Living Costs | E71: Site Level Expenses | I71: 7046443 | J71: 75200 | K71: =I71+J71 -> 7121643
C72: 13 | D72: 7340; Office Equipment Maintenance | E72: Site Level Expenses | I72: 575000 | K72: =I72+J72 -> 575000
C73: 14 | D73: 7350; I.T. Costs - Internet | E73: Site Level Expenses | I73: 316000 | K73: =I73+J73 -> 316000
C74: 15 | D74: 7351; I.T. Costs - Software / Maint. Costs | E74: Site Level Expenses | I74: 120000 | K74: =I74+J74 -> 120000
C75: 16 | D75: 7320; Medical Expenses | E75: Site Level Expenses | I75: 3921660 | J75: 24550 | K75: =I75+J75 -> 3946210
C76: 17 | D76: 7460; Rent | E76: Site Level Expenses | I76: 0 | K76: =I76+J76 -> 0
C77: 18 | D77: 7500; Stationary | E77: Site Level Expenses | I77: 435750 | J77: 3200 | K77: =I77+J77 -> 438950
C78: 19 | D78: 7560; Telephone | E78: Site Level Expenses | I78: 1425000 | J78: 31000 | K78: =I78+J78 -> 1456000
C79: 20 | D79: 7620; Travelling | E79: Site Level Expenses | I79: 3782250 | J79: 59500 | K79: =I79+J79 -> 3841750
C80: 21 | D80: 7622: Outstation | E80: Site Level Expenses | I80: 101250 | K80: =I80+J80 -> 101250
C81: 22 | D81: 8020; Bank Charges | E81: Site Level Expenses | I81: 264341.79 | J81: 14088.95 | K81: =I81+J81 -> 278430.74
C82: 23
C83: 24 | I83: 0 | K83: =I83+J83 -> 0
C84: OVERHEADS | I84: 0 | K84: =I84+J84 -> 0
C85: 1 | D85: Administration | E85: Overheads | F85: No. | G85: 0 | H85: 1000000 | I85: 31000000 | K85: =I85+J85 -> 31000000
D87: Total | I87: =SUM(I4:I85) -> 1.0632881e+09 | J87: =SUM(J4:J85) -> 18112042 | K87: =SUM(K4:K85) -> 1.0814001e+09
J89: =IF(J88=0,"","ERROR") | K89: =IF(K88=0,"","ERROR")

Sheet Plant Return
A1: WEEKLY PLANT RETURNS | H1: Date: | I1: ='Contract Summary'!E1 -> 45717 | J1: Week No: | K1: =IF(I1=0,0,VLOOKUP(I1,Lists!A2:B5000,2,FALSE)) -> 9 | L1: Instructions
A2: ='Cost Report'!D2 -> PROPOSED CONSTRUCTION OF 15 SPAN, DUAL CARRIAGEWAY, 6TH BRIDGE OVER RIVER KADUNA AND APPROACH ROADS
A3: Fleet No. | B3: Description | C3: Plant Category | D3: Hours Worked | E3: S/B Hours | F3: B/D Hours | G3: Rate (N) | H3: Plant Cost | I3: Transfered From | J3: Current Location | K3: Remarks
A4: AC69 | B4: STATIC AIR COMPRESSOR | D4: 40 | E4: 30 | F4: 0 | G4: 300 | H4: =SUM(D4*G4) -> 12000 | J4: Kaduna | K4: working
A5: AC173 | B5: Mobile Air compressor | D5: 8 | E5: 62 | F5: 0 | G5: 500 | H5: =SUM(D5*G5) -> 4000 | J5: Kaduna | K5: working
A6: BB18 | B6: BAR BENDER | D6: 40 | E6: 30 | F6: 0 | G6: 500 | H6: =SUM(D6*G6) -> 20000 | J6: Kaduna | K6: working
A7: BP10 | B7: BATCHING PLANT (DRY) | D7: 40 | E7: 30 | F7: 0 | G7: 6100 | H7: =SUM(D7*G7) -> 244000 | J7: Kaduna | K7: working
A8: D67 | B8: DOZER | D8: 23 | E8: 47 | F8: 0 | G8: 8200 | H8: =SUM(D8*G8) -> 188600 | J8: Kaduna | K8: working
A9: E88 | B9: Excavator | D9: 17 | E9: 53 | F9: 0 | G9: 8200 | H9: =SUM(D9*G9) -> 139400 | J9: Kaduna
A10: E94 | B10: JS200 EXCAVATOR | D10: 44 | E10: 26 | F10: 0 | G10: 8200 | H10: =SUM(D10*G10) -> 360800 | J10: Kaduna | K10: working
A11: EG86 | B11: Generator set | D11: 34 | E11: 36 | F11: 0 | G11: 1300 | H11: =SUM(D11*G11) -> 44200 | J11: Kaduna
A12: EG214 | B12: GENERATOR SET | D12: 42 | E12: 28 | F12: 0 | G12: 1300 | H12: =SUM(D12*G12) -> 54600 | J12: Kaduna | K12: working
A13: EG251 | B13: GENERATOR SET | D13: 0 | E13: 0 | F13: 70 | G13: 1300 | H13: =SUM(D13*G13) -> 0 | J13: Kaduna | K13: Engine problem, to send to Abuja for overhaul
A14: EG252 | B14: GENERATOR SET | D14: 0 | E14: 0 | F14: 70 | G14: 1300 | H14: =SUM(D14*G14) -> 0 | J14: Kaduna | K14: Engine over consuming oil, to send to Abuja for repairs
A15: EG263 | B15: GENERATOR SET | D15: 53 | E15: 17 | F15: 0 | G15: 1300 | H15: =SUM(D15*G15) -> 68900 | J15: Kaduna | K15: working
A16: EG284 | B16: GENERATOR SET Honda | D16: 0 | E16: 70 | F16: 0 | G16: 500 | H16: =SUM(D16*G16) -> 0 | J16: Kaduna | K16: standby
A17: EG287 | B17: GENERATOR SET Firman | D17: 0 | E17: 0 | F17: 70 | G17: 500 | H17: =SUM(D17*G17) -> 0 | J17: Kaduna | K17: Nozzle problem, Not starting
A18: FMP20 | B18: FUEL METER PUMP | D18: 40 | E18: 30 | F18: 0 | G18: 500 | H18: =SUM(D18*G18) -> 20000 | J18: Kaduna | K18: working
A19: G38 | B19: Grader | D19: 0 | E19: 70 | F19: 0 | G19: 501 | H19: =SUM(D19*G19) -> 0 | J19: Kaduna
A20: IC26 | B20: IRON CUTTER | D20: 40 | E20: 30 | F20: 0 | G20: 500 | H20: =SUM(D20*G20) -> 20000 | J20: Kaduna | K20: working
A21: L66 | B21: L70F PAYLOADER | D21: 22 | E21: 48 | F21: 0 | G21: 8200 | H21: =SUM(D21*G21) -> 180400 | J21: Kaduna | K21: working
A22: L67 | B22: L150H PAYLOADER | D22: 0 | E22: 70 | F22: 0 | G22: 8200 | H22: =SUM(D22*G22) -> 0 | J22: Kaduna | K22: standby
A23: LL11 | B23: Low loader | D23: 0 | E23: 70 | F23: 0 | G23: 5800 | H23: =SUM(D23*G23) -> 0 | J23: Kaduna | K23: standby
A24: LT8 | B24: LUXURIOUS BUS | D24: 50 | E24: 20 | F24: 0 | G24: 1600 | H24: =SUM(D24*G24) -> 80000 | J24: Kaduna | K24: working
A25: MCM15 | B25: MOBILE CAR MIXER | D25: 8 | E25: 62 | F25: 0 | G25: 2000 | H25: =SUM(D25*G25) -> 16000 | J25: Kaduna | K25: working
A26: P370 | B26: PICK UP | D26: 0 | E26: 0 | F26: 70 | G26: 1000 | H26: =SUM(D26*G26) -> 0 | J26: Kaduna | K26: Injector pump and Nozzles problem
A27: P413 | B27: PICK UP | D27: 50 | E27: 20 | F27: 0 | G27: 1000 | H27: =SUM(D27*G27) -> 50000 | J27: Kaduna | K27: working
A28: P416 | B28: PICK UP | D28: 60 | E28: 10 | F28: 0 | G28: 1000 | H28: =SUM(D28*G28) -> 60000 | J28: Kaduna | K28: working
A29: P418 | B29: PICK UP | D29: 50 | E29: 20 | F29: 0 | G29: 1000 | H29: =SUM(D29*G29) -> 50000 | J29: Kaduna | K29: Propella plange yoke and cross bearing changed back to work
A30: P439 | B30: PICK UP | D30: 50 | E30: 20 | F30: 0 | G30: 1000 | H30: =SUM(D30*G30) -> 50000 | J30: Kaduna | K30: working
A31: PF5 | B31: POWER FLOAT | D31: 0 | E31: 70 | F31: 0 | H31: =SUM(D31*G31) -> 0 | J31: Kaduna | K31: standby
A32: PF6 | B32: POWER FLOAT | D32: 0 | E32: 70 | F32: 0 | H32: =SUM(D32*G32) -> 0 | J32: Kaduna | K32: standby
A33: RT12 | B33: GROVE CRANE | D33: 15 | E33: 55 | F33: 0 | G33: 13200 | H33: =SUM(D33*G33) -> 198000 | J33: Kaduna | K33: working
A34: T210 | B34: WATER TANKER | D34: 40 | E34: 30 | F34: 0 | G34: 4100 | H34: =SUM(D34*G34) -> 164000 | J34: Kaduna | K34: working
A35: T229 | B35: WATER TANKER | D35: 40 | E35: 30 | F35: 0 | G35: 4100 | H35: =SUM(D35*G35) -> 164000 | J35: Kaduna | K35: working
A36: T343 | B36: Low loader | D36: 0 | E36: 70 | F36: 0 | G36: 4900 | H36: =SUM(D36*G36) -> 0 | J36: Kaduna | K36: standby
A37: T365 | B37: TRACTOR UNIT | D37: 50 | E37: 20 | F37: 0 | G37: 4900 | H37: =SUM(D37*G37) -> 245000 | J37: Kaduna | K37: working
A38: T385 | B38: TRUCK MIXER | D38: 50 | E38: 20 | F38: 0 | G38: 4900 | H38: =SUM(D38*G38) -> 245000 | J38: Kaduna | K38: working
A39: T403 | B39: Concrete Pump | D39: 0 | E39: 70 | F39: 0 | H39: =SUM(D39*G39) -> 0 | J39: Kaduna | K39: standby
A40: T488 | B40: FUEL BOWSER | D40: 8 | E40: 62 | F40: 0 | G40: 5800 | H40: =SUM(D40*G40) -> 46400 | J40: Kaduna | K40: working
A41: T510 | B41: HIAB TRUCK | D41: 40 | E41: 30 | F41: 0 | G41: 4900 | H41: =SUM(D41*G41) -> 196000 | J41: Kaduna | K41: working
A42: T576 | B42: TRUCK MIXER | D42: 0 | E42: 70 | F42: 0 | G42: 5800 | H42: =SUM(D42*G42) -> 0 | J42: Kaduna | K42: working
A43: T607 | B43: VOLVO TIPPER | D43: 0 | E43: 70 | F43: 0 | G43: 5800 | H43: =SUM(D43*G43) -> 0 | J43: Kaduna | K43: standby
A44: T608 | B44: VOLVO TIPPER | D44: 0 | E44: 70 | F44: 0 | G44: 5800 | H44: =SUM(D44*G44) -> 0 | J44: Kaduna | K44: standby
A45: VPE134 | B45: VIBRATING POKER ENGINE | D45: 0 | E45: 70 | F45: 0 | G45: 100 | H45: =SUM(D45*G45) -> 0 | J45: Kaduna | K45: standby
A46: VPE140 | B46: VIBRATING POKER ENGINE | D46: 40 | E46: 30 | F46: 0 | G46: 100 | H46: =SUM(D46*G46) -> 4000 | J46: Kaduna | K46: working
A47: VPE217 | B47: VIBRATING POKER ENGINE | D47: 0 | E47: 70 | F47: 0 | G47: 100 | H47: =SUM(D47*G47) -> 0 | J47: Kaduna | K47: standby
A48: VPE244 | B48: VIBRATING POKER ENGINE | D48: 0 | E48: 70 | F48: 0 | G48: 100 | H48: =SUM(D48*G48) -> 0 | J48: Kaduna | K48: standby
A49: VPE258 | B49: VIBRATING POKER ENGINE | D49: 40 | E49: 30 | F49: 0 | G49: 100 | H49: =SUM(D49*G49) -> 4000 | J49: Kaduna | K49: working
A50: VPE280 | B50: VIBRATING POKER ENGINE | D50: 40 | E50: 30 | F50: 0 | G50: 100 | H50: =SUM(D50*G50) -> 4000 | J50: Kaduna | K50: working
A51: VPE282 | B51: VIBRATING POKER ENGINE | D51: 0 | E51: 70 | F51: 0 | G51: 100 | H51: =SUM(D51*G51) -> 0 | J51: Kaduna | K51: standby
... A61: WP349 | B61: WATER PUMP | D61: 25 | E61: 45 | F61: 0 | G61: 500 | H61: =SUM(D61*G61) -> 12500 | J61: Kaduna | K61: working
A62: WP420 | B62: WATER PUMP | D62: 26 | E62: 44 | F62: 0 | H62: =SUM(D62*G62) -> 0 | J62: Kaduna | K62: working
H63: =SUM(D63*G63) -> 0
B65: TOTAL All : | D65: =SUM(D4:D62) -> 1188 | E65: =SUM(E4:E62) -> 2662 | F65: =SUM(F4:F62) -> 280 | H65: =SUM(H4:H62) -> 3092500
E67: % Allocated to the project | H67: 1
E69: Total Internal Plant cost Allocated | H69: =H65*H67 -> 3092500
E71: Internal Plant Cost Adjusted for
E72: =IF(ISBLANK('[1]Cost Report'!D11),"",'[1]Cost Report'!D11) -> Engine Oil | H72: ='Cost Report'!J11 -> 217170.68
E73: =IF(ISBLANK('[1]Cost Report'!D12),"",'[1]Cost Report'!D12) -> Gear oil | H73: ='Cost Report'!J12 -> 95004
E74: =IF(ISBLANK('[1]Cost Report'!D13),"",'[1]Cost Report'!D13) -> ATF 220 Oil | H74: ='Cost Report'!J13 -> 0
E75: =IF(ISBLANK('[1]Cost Report'!D14),"",'[1]Cost Report'!D14) -> DTE 26 Oil | H75: ='Cost Report'!J14 -> 108658.77
E76: =IF(ISBLANK('[1]Cost Report'!D15),"",'[1]Cost Report'!D15) -> Rarius 427 Comp. Oil | H76: ='Cost Report'!J15 -> 0
E77: =IF(ISBLANK('[1]Cost Report'!D16),"",'[1]Cost Report'!D16) -> Almo 529 | H77: ='Cost Report'!J16 -> 0
E78: =IF(ISBLANK('[1]Cost Report'!D17),"",'[1]Cost Report'!D17) -> Grease | H78: ='Cost Report'!J17 -> 121000
E79: =IF(ISBLANK('[1]Cost Report'!D18),"",'[1]Cost Report'!D18) -> 6440; Tyres | H79: ='Cost Report'!J18 -> 0
E80: ='[1]Cost Report'!D66 -> 6320; Spare Parts | H80: ='Cost Report'!J60 -> 34000
E81: Tota All Adjusted | H81: =SUM(H72:H80) -> 575833.45
E83: Net Plant Cost Cost Report | H83: =H69-H81 -> 2516666.5

Sheet Diesel Consumption
A1: WEEKLY DIESEL CONSUMPTION | G1: Date: | H1: ='Contract Summary'!E1 -> 45717 | N1: Week No: | O1: =IF(H1=0,0,VLOOKUP(H1,Lists!A2:B5000,2,FALSE)) -> 9 | R1: Instructions
A2: ='Plant Return'!A2 -> PROPOSED CONSTRUCTION OF 15 SPAN, DUAL CARRIAGEWAY, 6TH BRIDGE OVER RIVER KADUNA AND APPROACH ROADS
C3: Opening Stock: | D3: 0 | H3: Received this Week: | I3: 0 | L3: Used This Week: | M3: =K87 -> 2193 | P3: Closing Stock: | Q3: =D3+I3-M3 -> -2193
A4: Fleet No. | B4: Description | C4: Plant Category | D4: Saturday | E4: Sunday | F4: Monday | G4: Tuesday | H4: Wednesday | I4: Thursday | J4: Friday | K4: Total Fuel Taken | L4: Standard Ltrs/Hour | M4: Standard Usage | N4: Variance | O4: Variance Value | P4: Usage Value | Q4: Remarks
A5: AC69 | B5: STATIC AIR COMPRESSOR | D5: 0 | E5: 0 | F5: 0 | G5: 0 | H5: 0 | I5: 0 | J5: 0 | K5: =D5+E5+F5+G5+H5+I5+J5 -> 0 | L5: 0 | M5: =IF(A5="",0,VLOOKUP(A5,'Plant Return'!$A$4:$D$62,4,FALSE)*L5) -> 0 | N5: =K5-M5 -> 0 | O5: =N5*'Cost Report'!$H$5 -> 0 | P5: =K5*'Cost Report'!$H$5 -> 0
A6: AC173 | B6: Mobile Air compressor | D6: 0 | E6: 0 | F6: 0 | G6: 0 | H6: 0 | I6: 0 | J6: 0 | K6: =D6+E6+F6+G6+H6+I6+J6 -> 0 | L6: 0 | M6: =IF(A6="",0,VLOOKUP(A6,'Plant Return'!$A$4:$D$62,4,FALSE)*L6) -> 0 | N6: =K6-M6 -> 0 | O6: =N6*'Cost Report'!$H$5 -> 0 | P6: =K6*'Cost Report'!$H$5 -> 0
A7: BB18 | B7: BAR BENDER | D7: 0 | E7: 0 | F7: 0 | G7: 0 | H7: 0 | I7: 0 | J7: 0 | K7: =D7+E7+F7+G7+H7+I7+J7 -> 0 | M7: =IF(A7="",0,VLOOKUP(A7,'Plant Return'!$A$4:$D$62,4,FALSE)*L7) -> 0 | N7: =K7-M7 -> 0 | O7: =N7*'Cost Report'!$H$5 -> 0 | P7: =K7*'Cost Report'!$H$5 -> 0
A8: BP10 | B8: BATCHING PLANT (DRY) | D8: 0 | E8: 0 | F8: 0 | G8: 0 | H8: 0 | I8: 0 | J8: 0 | K8: =D8+E8+F8+G8+H8+I8+J8 -> 0 | M8: =IF(A8="",0,VLOOKUP(A8,'Plant Return'!$A$4:$D$62,4,FALSE)*L8) -> 0 | N8: =K8-M8 -> 0 | O8: =N8*'Cost Report'!$H$5 -> 0 | P8: =K8*'Cost Report'!$H$5 -> 0
A9: D67 | B9: DOZER | D9: 0 | E9: 0 | F9: 100 | G9: 0 | H9: 50 | I9: 100 | J9: 50 | K9: =D9+E9+F9+G9+H9+I9+J9 -> 300 | M9: =IF(A9="",0,VLOOKUP(A9,'Plant Return'!$A$4:$D$62,4,FALSE)*L9) -> 0 | N9: =K9-M9 -> 300 | O9: =N9*'Cost Report'!$H$5 -> 330000 | P9: =K9*'Cost Report'!$H$5 -> 330000
A10: E88 | B10: Excavator | D10: 0 | E10: 0 | F10: 50 | G10: 0 | H10: 50 | I10: 80 | J10: 60 | K10: =D10+E10+F10+G10+H10+I10+J10 -> 240 | M10: =IF(A10="",0,VLOOKUP(A10,'Plant Return'!$A$4:$D$62,4,FALSE)*L10) -> 0 | N10: =K10-M10 -> 240 | O10: =N10*'Cost Report'!$H$5 -> 264000 | P10: =K10*'Cost Report'!$H$5 -> 264000
A11: E94 | B11: JS200 EXCAVATOR | D11: 0 | E11: 0 | F11: 120 | G11: 50 | H11: 115 | I11: 80 | J11: 30 | K11: =D11+E11+F11+G11+H11+I11+J11 -> 395 | M11: =IF(A11="",0,VLOOKUP(A11,'Plant Return'!$A$4:$D$62,4,FALSE)*L11) -> 0 | N11: =K11-M11 -> 395 | O11: =N11*'Cost Report'!$H$5 -> 434500 | P11: =K11*'Cost Report'!$H$5 -> 434500
A12: EG86 | B12: Generator set | D12: 0 | E12: 0 | F12: 30 | G12: 10 | H12: 20 | I12: 30 | J12: 20 | K12: =D12+E12+F12+G12+H12+I12+J12 -> 110 | M12: =IF(A12="",0,VLOOKUP(A12,'Plant Return'!$A$4:$D$62,4,FALSE)*L12) -> 0 | N12: =K12-M12 -> 110 | O12: =N12*'Cost Report'!$H$5 -> 121000 | P12: =K12*'Cost Report'!$H$5 -> 121000
A13: EG214 | B13: GENERATOR SET | D13: 0 | E13: 0 | F13: 30 | G13: 10 | H13: 20 | I13: 30 | J13: 20 | K13: =D13+E13+F13+G13+H13+I13+J13 -> 110 | M13: =IF(A13="",0,VLOOKUP(A13,'Plant Return'!$A$4:$D$62,4,FALSE)*L13) -> 0 | N13: =K13-M13 -> 110 | O13: =N13*'Cost Report'!$H$5 -> 121000 | P13: =K13*'Cost Report'!$H$5 -> 121000
A14: EG251 | B14: GENERATOR SET | D14: 0 | E14: 0 | F14: 0 | G14: 0 | H14: 0 | I14: 0 | J14: 0 | K14: =D14+E14+F14+G14+H14+I14+J14 -> 0 | M14: =IF(A14="",0,VLOOKUP(A14,'Plant Return'!$A$4:$D$62,4,FALSE)*L14) -> 0 | N14: =K14-M14 -> 0 | O14: =N14*'Cost Report'!$H$5 -> 0 | P14: =K14*'Cost Report'!$H$5 -> 0
A15: EG252 | B15: GENERATOR SET | D15: 0 | E15: 0 | F15: 0 | G15: 0 | H15: 0 | I15: 0 | J15: 0 | K15: =D15+E15+F15+G15+H15+I15+J15 -> 0 | M15: =IF(A15="",0,VLOOKUP(A15,'Plant Return'!$A$4:$D$62,4,FALSE)*L15) -> 0 | N15: =K15-M15 -> 0 | O15: =N15*'Cost Report'!$H$5 -> 0 | P15: =K15*'Cost Report'!$H$5 -> 0
A16: EG263 | B16: GENERATOR SET | D16: 0 | E16: 0 | F16: 0 | G16: 0 | H16: 200 | I16: 0 | J16: 0 | K16: =D16+E16+F16+G16+H16+I16+J16 -> 200 | M16: =IF(A16="",0,VLOOKUP(A16,'Plant Return'!$A$4:$D$62,4,FALSE)*L16) -> 0 | N16: =K16-M16 -> 200 | O16: =N16*'Cost Report'!$H$5 -> 220000 | P16: =K16*'Cost Report'!$H$5 -> 220000
A17: EG284 | B17: GENERATOR SET Honda | D17: 0 | E17: 0 | F17: 0 | G17: 0 | H17: 0 | I17: 0 | J17: 0 | K17: =D17+E17+F17+G17+H17+I17+J17 -> 0 | M17: =IF(A17="",0,VLOOKUP(A17,'Plant Return'!$A$4:$D$62,4,FALSE)*L17) -> 0 | N17: =K17-M17 -> 0 | O17: =N17*'Cost Report'!$H$5 -> 0 | P17: =K17*'Cost Report'!$H$5 -> 0
A18: EG287 | B18: GENERATOR SET Firman | D18: 0 | E18: 0 | F18: 0 | G18: 0 | H18: 0 | I18: 0 | J18: 0 | K18: =D18+E18+F18+G18+H18+I18+J18 -> 0 | M18: =IF(A18="",0,VLOOKUP(A18,'Plant Return'!$A$4:$D$62,4,FALSE)*L18) -> 0 | N18: =K18-M18 -> 0 | O18: =N18*'Cost Report'!$H$5 -> 0 | P18: =K18*'Cost Report'!$H$5 -> 0
... A63: WP420 | B63: WATER PUMP | D63: 0 | E63: 0 | F63: 0 | G63: 0 | H63: 0 | I63: 0 | J63: 0 | K63: =D63+E63+F63+G63+H63+I63+J63 -> 0 | M63: =IF(A63="",0,VLOOKUP(A63,'Plant Return'!$A$4:$D$62,4,FALSE)*L63) -> 0 | N63: =K63-M63 -> 0 | O63: =N63*'Cost Report'!$H$5 -> 0 | P63: =K63*'Cost Report'!$H$5 -> 0
D64: =SUM(D5:D63) -> 0 | E64: =SUM(E5:E63) -> 0 | F64: =SUM(F5:F63) -> 530 | G64: =SUM(G5:G63) -> 140 | H64: =SUM(H5:H63) -> 639 | I64: =SUM(I5:I63) -> 515 | J64: =SUM(J5:J63) -> 310 | K64: =SUM(K5:K63) -> 2134 | ... P64: =SUM(P5:P63) -> 2347400
F65: 0
A66: Other Uses | P66: =K66*'Cost Report'!$H$5 -> 0
A67: Precast | D67: 0 | E67: 0 | F67: 15 | G67: 0 | H67: 15 | I67: 15 | J67: 10 | K67: =D67+E67+F67+G67+H67+I67+J67 -> 55 | P67: =K67*'Cost Report'!$H$5 -> 60500
A68: workshop | D68: 0 | E68: 0 | F68: 0 | G68: 0 | H68: 4 | I68: 0 | J68: 0 | K68: =D68+E68+F68+G68+H68+I68+J68 -> 4 | P68: =K68*'Cost Report'!$H$5 -> 4400
A69: Ministry | D69: 0 | E69: 0 | F69: 0 | G69: 0 | H69: 0 | I69: 0 | J69: 0 | K69: =D69+E69+F69+G69+H69+I69+J69 -> 0 | P69: =K69*'Cost Report'!$H$5 -> 0
A70: Drillers | D70: 0 | E70: 0 | F70: 0 | G70: 0 | H70: 0 | I70: 0 | J70: 0 | K70: =D70+E70+F70+G70+H70+I70+J70 -> 0 | P70: =K70*'Cost Report'!$H$5 -> 0
A71: P408 | D71: 0 | E71: 0 | F71: 0 | G71: 0 | H71: 0 | I71: 0 | J71: 0 | K71: =D71+E71+F71+G71+H71+I71+J71 -> 0 | P71: =K71*'Cost Report'!$H$5 -> 0
E72: 0 | F72: 0 | G72: 0 | H72: 0 | I72: 0 | J72: 0 | K72: =D72+E72+F72+G72+H72+I72+J72 -> 0 | P72: =K72*'Cost Report'!$H$5 -> 0
K73: =D73+E73+F73+G73+H73+I73+J73 -> 0 | P73: =K73*'Cost Report'!$H$5 -> 0
K74: =D74+E74+F74+G74+H74+I74+J74 -> 0 | P74: =K74*'Cost Report'!$H$5 -> 0
K75: =D75+E75+F75+G75+H75+I75+J75 -> 0 | P75: =K75*'Cost Report'!$H$5 -> 0
K76: =D76+E76+F76+G76+H76+I76+J76 -> 0 | P76: =K76*'Cost Report'!$H$5 -> 0
K77: =D77+E77+F77+G77+H77+I77+J77 -> 0 | P77: =K77*'Cost Report'!$H$5 -> 0
F78: 0 | K78: =D78+E78+F78+G78+H78+I78+J78 -> 0 | P78: =K78*'Cost Report'!$H$5 -> 0
F79: 0 | K79: =D79+E79+F79+G79+H79+I79+J79 -> 0 | P79: =K79*'Cost Report'!$H$5 -> 0
F80: 0 | K80: =D80+E80+F80+G80+H80+I80+J80 -> 0 | P80: =K80*'Cost Report'!$H$5 -> 0
F81: 0 | K81: =D81+E81+F81+G81+H81+I81+J81 -> 0 | P81: =K81*'Cost Report'!$H$5 -> 0
K82: =D82+E82+F82+G82+H82+I82+J82 -> 0 | P82: =K82*'Cost Report'!$H$5 -> 0
K83: =D83+E83+F83+G83+H83+I83+J83 -> 0 | P83: =K83*'Cost Report'!$H$5 -> 0
K84: =D84+E84+F84+G84+H84+I84+J84 -> 0 | P84: =K84*'Cost Report'!$H$5 -> 0
A85: Sub Total Other Used | D85: =SUM(D67:D84) -> 0 | E85: =SUM(E67:E84) -> 0 | F85: =SUM(F67:F84) -> 15 | G85: =SUM(G67:G84) -> 0 | H85: =SUM(H67:H84) -> 19 | I85: =SUM(I67:I84) -> 15 | J85: =SUM(J67:J84) -> 10 | K85: =SUM(K67:K84) -> 59 | M85: =SUM(M67:M84) -> 0 | N85: =SUM(N67:N84) -> 0 | P85: =SUM(P67:P84) -> 64900
K86: =D86+E86+F86+G86+H86+I86+J86 -> 0
A87: Total All Diesel Used | D87: =SUM(D64,D85) -> 0 | E87: =SUM(E64,E85) -> 0 | F87: =SUM(F64,F85) -> 545 | G87: =SUM(G64,G85) -> 140 | H87: =SUM(H64,H85) -> 658 | I87: =SUM(I64,I85) -> 530 | J87: =SUM(J64,J85) -> 320 | K87: =SUM(K64,K85) -> 2193 | M87: =SUM(M64,M85) -> 0 | N87: =SUM(N64,N85) -> 2134 | O87: =SUM(O64,O85) -> 2347400 | P87: =SUM(P64,P85) -> 2412300
F89: % Allocated to the project | K89: 1
F91: Total Internal Plant cost Allocated | K91: =K87*K89 -> 2193

Sheet Materials & Civils
A1: MATERIAL STOCKS | L1: Date: | M1: ='Weekly Summary'!E1 -> 45717 | O1: ='Weekly Summary'!F1 -> Week No: | P1: ='Weekly Summary'!G1 -> 9 | Q1: ='Weekly Summary'!G1 -> 9
B2: =Subcontractors!B2 -> PROPOSED CONSTRUCTION OF 15 SPAN, DUAL CARRIAGEWAY, 6TH BRIDGE OVER RIVER KADUNA AND APPROACH ROADS
J3: USED IN THE WEEK
A4: # | B4: Description | C4: Unit | D4: Current Price | E4: Opening Stock | F4: Received / Purchased | G4: Closing Stock | H4: Available for Use | J4: On Site Works | K4: Precast | L4: Mobilsation | M4: Other Uses | N4: Total Used | O4: Variance Qty | P4: Variance Value | Q4: Comments
A5: 1 | B5: Cement (Bags) | C5: Bags | D5: 6700 | E5: 934 | F5: 900 | G5: 1366 | H5: =E5+F5-G5 -> 468 | J5: 468 | N5: =SUM(J5:M5) -> 468 | O5: =H5-N5 -> 0 | P5: =D5*O5 -> 0
A6: =+A5+1 -> 2 | B6: Cement (Bulk) | C6: Tonne | D6: 95000 | E6: 0 | G6: 0 | H6: =E6+F6-G6 -> 0 | J6: 0 | N6: =SUM(J6:M6) -> 0 | O6: =H6-N6 -> 0 | P6: =D6*O6 -> 0
A7: =+A6+1 -> 3 | B7: Rebar (10mm) Local | C7: Tonne | D7: 587000 | E7: 15.581193 | G7: 14.269008 | H7: =E7+F7-G7 -> 1.312185 | J7: 1.312185 | N7: =SUM(J7:M7) -> 1.312185 | O7: =H7-N7 -> 0 | P7: =D7*O7 -> 0
A8: =+A7+1 -> 4 | B8: Rebar (12mm) Local | C8: Tonne | D8: 587000 | E8: 43.576367 | F8: 20.05584 | G8: 62.089058 | H8: =E8+F8-G8 -> 1.5431486 | J8: 1.5431486 | N8: =SUM(J8:M8) -> 1.5431486 | O8: =H8-N8 -> 0 | P8: =D8*O8 -> 0
A9: =+A8+1 -> 5 | B9: Rebar (16mm) Local | C9: Tonne | D9: 587000 | E9: 45.567752 | G9: 43.978525 | H9: =E9+F9-G9 -> 1.5892272 | J9: 1.5892272 | N9: =SUM(J9:M9) -> 1.5892272 | O9: =H9-N9 -> 0 | P9: =D9*O9 -> 0
A10: =+A9+1 -> 6 | B10: Rebar (12mm) Imported | C10: Tonne | D10: 657500 | E10: 0 | G10: 0 | H10: =E10+F10-G10 -> 0 | J10: 0 | N10: =SUM(J10:M10) -> 0 | O10: =H10-N10 -> 0 | P10: =D10*O10 -> 0
A11: =+A10+1 -> 7 | B11: Rebar (16mm) Imported | C11: Tonne | D11: 657500 | E11: 0 | G11: 0 | H11: =E11+F11-G11 -> 0 | J11: 0 | N11: =SUM(J11:M11) -> 0 | O11: =H11-N11 -> 0 | P11: =D11*O11 -> 0
A12: =+A11+1 -> 8 | B12: Rebar (20mm) Imported | C12: Tonne | D12: 657500 | E12: 0 | G12: 0 | H12: =E12+F12-G12 -> 0 | J12: 0 | N12: =SUM(J12:M12) -> 0 | O12: =H12-N12 -> 0 | P12: =D12*O12 -> 0
A13: =+A12+1 -> 9 | B13: Rebar (25mm) Imported | C13: Tonne | D13: 657500 | E13: 0.509256 | F13: 10.18512 | G13: 1.1574 | H13: =E13+F13-G13 -> 9.536976 | J13: 9.536976 | N13: =SUM(J13:M13) -> 9.536976 | O13: =H13-N13 -> 0 | P13: =D13*O13 -> 0
A14: =+A13+1 -> 10 | B14: Rebar (32mm) Imported | C14: Tonne | D14: 657500 | E14: 27.615064 | G14: 27.615064 | H14: =E14+F14-G14 -> 0 | J14: 0 | N14: =SUM(J14:M14) -> 0 | O14: =H14-N14 -> 0 | P14: =D14*O14 -> 0
A15: =+A14+1 -> 11 | B15: Binding Wire | C15: Roll | D15: 4500 | E15: 0 | G15: 0 | H15: =E15+F15-G15 -> 0 | J15: 0 | N15: =SUM(J15:M15) -> 0 | O15: =H15-N15 -> 0 | P15: =D15*O15 -> 0
A16: =+A15+1 -> 12 | B16: Sharp Sand | C16: Tonne | D16: 4000 | E16: 132.08233 | F16: 49.23 | G16: 134.11291 | H16: =E16+F16-G16 -> 47.199421 | J16: 47.199421 | N16: =SUM(J16:M16) -> 47.199421 | O16: =H16-N16 -> 0 | P16: =D16*O16 -> 0
A17: =+A16+1 -> 13 | B17: Blocks 9" | C17: Each | D17: 480 | E17: 0 | G17: 0 | H17: =E17+F17-G17 -> 0 | J17: 0 | N17: =SUM(J17:M17) -> 0 | O17: =H17-N17 -> 0 | P17: =D17*O17 -> 0
A18: =+A17+1 -> 14 | B18: Geotextile | E18: 0 | G18: 0 | H18: =E18+F18-G18 -> 0 | J18: 0 | N18: =SUM(J18:M18) -> 0 | O18: =H18-N18 -> 0 | P18: =D18*O18 -> 0
E19: 0 | G19: 0 | H19: =E19+F19-G19 -> 0 | J19: 0 | N19: =SUM(J19:M19) -> 0 | O19: =H19-N19 -> 0 | P19: =D19*O19 -> 0
E20: 0 | G20: 0 | H20: =E20+F20-G20 -> 0 | J20: 0 | N20: =SUM(J20:M20) -> 0 | O20: =H20-N20 -> 0 | P20: =D20*O20 -> 0
A21: QUARRY MATERIALS | E21: 0 | G21: 0 | H21: =E21+F21-G21 -> 0 | J21: 0 | N21: =SUM(J21:M21) -> 0 | O21: =H21-N21 -> 0 | P21: =D21*O21 -> 0
A22: =+A23+1 -> 26 | B22: 1/2" Aggregates | C22: Tonne | D22: 10000 | E22: 150.22711 | F22: 65.85 | G22: 176.48743 | H22: =E22+F22-G22 -> 39.589687 | J22: 39.589687 | N22: =SUM(J22:M22) -> 39.589687 | O22: =H22-N22 -> 0 | P22: =D22*O22 -> 0
A23: 25 | B23: 3/4" Aggregates | C23: Tonne | D23: 10000 | E23: 150.86474 | G23: 137.13072 | H23: =E23+F23-G23 -> 13.734023 | J23: 13.734023 | N23: =SUM(J23:M23) -> 13.734023 | O23: =H23-N23 -> 0 | P23: =D23*O23 -> 0
A24: =+A22+1 -> 27 | B24: 3/8" Aggregates | C24: Tonne | D24: 6000 | H24: =E24+F24-G24 -> 0 | N24: =SUM(J24:M24) -> 0 | O24: =H24-N24 -> 0 | P24: =D24*O24 -> 0
A25: =+A24+1 -> 28 | B25: Sand | C25: Tonne | D25: 8200 | H25: =E25+F25-G25 -> 0 | N25: =SUM(J25:M25) -> 0 | O25: =H25-N25 -> 0 | P25: =D25*O25 -> 0
A26: =+A25+1 -> 29 | B26: Stone base | C26: Tonne | D26: 6500 | H26: =E26+F26-G26 -> 0 | N26: =SUM(J26:M26) -> 0 | O26: =H26-N26 -> 0 | P26: =D26*O26 -> 0
A27: =+A26+1 -> 30 | B27: Hardcore | C27: Tonne | D27: 6500 | H27: =E27+F27-G27 -> 0 | N27: =SUM(J27:M27) -> 0 | O27: =H27-N27 -> 0 | P27: =D27*O27 -> 0
A28: =+A27+1 -> 31 | B28: MC1 Priming | C28: Tonne | D28: 918000 | H28: =E28+F28-G28 -> 0 | N28: =SUM(J28:M28) -> 0 | O28: =H28-N28 -> 0 | P28: =D28*O28 -> 0
A29: =+A28+1 -> 32 | B29: S125 Surface Dressing | C29: Tonne | D29: 957000 | H29: =E29+F29-G29 -> 0 | N29: =SUM(J29:M29) -> 0 | O29: =H29-N29 -> 0 | P29: =D29*O29 -> 0
A30: =+A29+1 -> 33 | B30: RSII Colas Tack Coat | C30: Tonne | D30: 930000 | H30: =E30+F30-G30 -> 0 | N30: =SUM(J30:M30) -> 0 | O30: =H30-N30 -> 0 | P30: =D30*O30 -> 0
A31: =+A30+1 -> 34 | B31: Crack Relief Layer CRL | C31: Tonne | D31: 0 | H31: =E31+F31-G31 -> 0 | N31: =SUM(J31:M31) -> 0 | O31: =H31-N31 -> 0 | P31: =D31*O31 -> 0
A32: =+A31+1 -> 35 | B32: Asphalt Binder Course | C32: Tonne | D32: 0 | H32: =E32+F32-G32 -> 0 | N32: =SUM(J32:M32) -> 0 | O32: =H32-N32 -> 0 | P32: =D32*O32 -> 0
A33: =+A32+1 -> 36 | B33: Asphalt Wearing Course | C33: Tonne | D33: 0 | H33: =E33+F33-G33 -> 0 | N33: =SUM(J33:M33) -> 0 | O33: =H33-N33 -> 0 | P33: =D33*O33 -> 0
A34: =+A33+1 -> 37 | B34: 60/70 Bitumen | C34: Tonne | H34: =E34+F34-G34 -> 0 | N34: =SUM(J34:M34) -> 0 | O34: =H34-N34 -> 0 | P34: =D34*O34 -> 0
A35: =+A34+1 -> 38 | B35: Kerosine | C35: Litres | H35: =E35+F35-G35 -> 0 | N35: =SUM(J35:M35) -> 0 | O35: =H35-N35 -> 0 | P35: =D35*O35 -> 0
A36: =+A35+1 -> 39 | H36: =E36+F36-G36 -> 0 | N36: =SUM(J36:M36) -> 0 | O36: =H36-N36 -> 0 | P36: =D36*O36 -> 0
A37: =+A36+1 -> 40 | H37: =E37+F37-G37 -> 0 | N37: =SUM(J37:M37) -> 0 | O37: =H37-N37 -> 0 | P37: =D37*O37 -> 0
B38: Total All: | H38: =E38+F38-G38 -> 0 | N38: =SUM(N5:N37) -> 582.50467 | O38: =SUM(O5:O37) -> 0 | P38: =SUM(P5:P37) -> 0

Sheet Hired Vehicles
A1: HIRED VEHICLES | F1: Date: | G1: ='Weekly Summary'!E1 -> 45717 | H1: Week No: | I1: =IF(G1=0,0,VLOOKUP(G1,Lists!A2:B5000,2,FALSE)) -> 9 | J1: Instructions
A2: =#REF! -> #REF! | B2: ='Diesel Consumption'!A2 -> PROPOSED CONSTRUCTION OF 15 SPAN, DUAL CARRIAGEWAY, 6TH BRIDGE OVER RIVER KADUNA AND APPROACH ROADS
A3: S/No. | B3: Reg. No | C3: Description | D3: Section | E3: Owners | F3: Days Worked | G3: Rate (N) | H3: Amount (N) | I3: Remarks
A4: 1 | D4: Engineer | E4: engr. | F4: 6 | G4: 2500 | H4: =SUM(F4*G4) -> 15000
A5: =A4+1 -> 2 | D5: Acct | E5: accountant | F5: 0 | G5: 2500 | H5: =SUM(F5*G5) -> 0
A6: =A5+1 -> 3 | D6: Survey | E6: surveyor | H6: =SUM(F6*G6) -> 0
A7: =A6+1 -> 4 | D7: Lab | H7: =SUM(F7*G7) -> 0
A8: =A7+1 -> 5 | D8: Mechanic | E8: Mechanic | F8: 0 | G8: 2000 | H8: =SUM(F8*G8) -> 0
A9: =A8+1 -> 6 | D9: Mechanic | E9: Mechanic | F9: 0 | G9: 1800 | H9: =SUM(F9*G9) -> 0
A10: =A9+1 -> 7 | H10: =SUM(F10*G10) -> 0
A11: =A10+1 -> 8 | H11: =SUM(F11*G11) -> 0
A12: =A11+1 -> 9 | H12: =SUM(F12*G12) -> 0
A13: =A12+1 -> 10 | H13: =SUM(F13*G13) -> 0
A14: =A13+1 -> 11 | H14: =SUM(F14*G14) -> 0
A15: =A14+1 -> 12 | H15: =SUM(F15*G15) -> 0
A16: =A15+1 -> 13 | H16: =SUM(F16*G16) -> 0
A17: =A16+1 -> 14 | H17: =SUM(F17*G17) -> 0
A18: =A17+1 -> 15 | H18: =SUM(F18*G18) -> 0
A19: =A18+1 -> 16 | H19: =SUM(F19*G19) -> 0
A20: =A19+1 -> 17 | H20: =SUM(F20*G20) -> 0
A21: =A20+1 -> 18 | H21: =SUM(F21*G21) -> 0
... A23: =A22+1 -> 20 | H23: =SUM(F23*G23) -> 0
E25: Total | H25: =SUM(H4:H24) -> 15000

Sheet Labour Strength
A1: LABOUR STRENGTH | C1: Date: | D1: ='Weekly Summary'!E1 -> 45717 | E1: ='Weekly Summary'!F1 -> Week No: | F1: ='Weekly Summary'!G1 -> 9 | G1: Instructions
A2: ='Hired Vehicles'!B2 -> PROPOSED CONSTRUCTION OF 15 SPAN, DUAL CARRIAGEWAY, 6TH BRIDGE OVER RIVER KADUNA AND APPROACH ROADS
A3: S/No | B3: Department | C3: Manning This Week | D3: Manning Previous Week | E3: Movement | F3: Comment
A4: 1 | B4: Senior Staff | C4: 0 | D4: 0 | E4: =C4-D4 -> 0
A5: =A4+1 -> 2 | B5: Civil Engineers | C5: 3 | D5: 3 | E5: =C5-D5 -> 0
A6: =A5+1 -> 3 | B6: Civil - Surveyors | C6: 4 | D6: 4 | E6: =C6-D6 -> 0
A7: =A6+1 -> 4 | B7: Administration | C7: 2 | D7: 2 | E7: =C7-D7 -> 0
A8: =A7+1 -> 5 | B8: Lab | C8: 4 | D8: 4 | E8: =C8-D8 -> 0
A9: =A8+1 -> 6 | B9: Domestics | C9: 2 | D9: 2 | E9: =C9-D9 -> 0
A10: =A9+1 -> 7 | B10: Security | C10: 1 | D10: 1 | E10: =C10-D10 -> 0
A11: =A10+1 -> 8 | B11: Plant | C11: 17 | D11: 17 | E11: =C11-D11 -> 0
A12: =A11+1 -> 9 | B12: Transport | C12: 3 | D12: 3 | E12: =C12-D12 -> 0
A13: =A12+1 -> 10 | B13: Earthworks | C13: 4 | D13: 4 | E13: =C13-D13 -> 0
A14: =A13+1 -> 11 | B14: Quarry | C14: 0 | D14: 0 | E14: =C14-D14 -> 0
A15: =A14+1 -> 12 | B15: Asphalt | E15: =C15-D15 -> 0
A16: =A15+1 -> 13 | B16: Marini | C16: 0 | D16: 0 | E16: =C16-D16 -> 0
A17: =A16+1 -> 14 | B17: Civil Batching Plant | C17: 11 | D17: 11 | E17: =C17-D17 -> 0
A18: =A17+1 -> 15 | B18: Electrical | E18: =C18-D18 -> 0
B19: Total Head Count | C19: =SUM(C4:C18) -> 51 | D19: =SUM(D4:D18) -> 51 | E19: =SUM(E4:E18) -> 0
A21: CASUAL STAFF
A22: S/No | B22: Department | C22: Manning This Week | D22: Manning Previous Week | E22: Movement | F22: Comment
A23: 1 | B23: Transport & Earthworks | E23: =C23-D23 -> 0
A24: =A23+1 -> 2 | B24: Engr, Survey, civil store & Batching plant | E24: =C24-D24 -> 0
A25: =A24+1 -> 3 | B25: Security | E25: =C25-D25 -> 0
A26: =A25+1 -> 4 | B26: Lab | E26: =C26-D26 -> 0
A27: =A26+1 -> 5 | B27: Quarry | C27: 0 | D27: 0 | E27: =C27-D27 -> 0
A28: 6 | B28: Civil | C28: 0 | D28: 0 | E28: =C28-D28 -> 0
B29: Total Casual Head Count | C29: =SUM(C23:C28) -> 0 | E29: =SUM(E23:E28) -> 0

Sheet Subcontractors
A1: SUBCONTRACTORS | N1: Date: | O1: ='Weekly Summary'!E1 -> 45717 | P1: ='Weekly Summary'!F1 -> Week No: | Q1: ='Weekly Summary'!G1 -> 9 | R1: Instructions
A2: =#REF! -> #REF! | B2: ='Hired Vehicles'!B2 -> PROPOSED CONSTRUCTION OF 15 SPAN, DUAL CARRIAGEWAY, 6TH BRIDGE OVER RIVER KADUNA AND APPROACH ROADS
A3: Item | B3: Subcontractor | C3: Description | D3: Location | E3: Unit | F3: Agreed Rate | G3: Assigned Qty | H3: Previous Qty | I3: Qty Executed for Week | J3: Total Qty Executed To-Date | K3: Balance to Complete | L3: Subcontract Value This Week | M3: Previous Value Completed | N3: Value Completed this week | O3: Total Value Completed | P3: Value to Completion | Q3: Remarks
B4: DOMINIC ANI GLOBAL NIG | H4: 0 | J4: =I4+H4 -> 0 | K4: =G4-J4 -> 0 | L4: =G4*F4 -> 0 | M4: =H4*F4 -> 0 | N4: =I4*F4 -> 0 | O4: =SUM(M4:N4) -> 0 | P4: =L4-O4 -> 0
A5: 1 | C5: Excavation | E5: m3 | F5: 1100 | H5: 64.608 | J5: =SUM(H5:I5) -> 64.608 | K5: =G5-J5 -> -64.608 | L5: =G5*F5 -> 0 | M5: =H5*F5 -> 71068.8 | N5: =I5*F5 -> 0 | O5: =SUM(M5:N5) -> 71068.8 | P5: =L5-O5 -> -71068.8
A6: 2 | C6: Formwork In Generator House/Iron Bending Floor | E6: m2 | F6: 825 | H6: 101.8902 | J6: =SUM(H6:I6) -> 101.8902 | K6: =G6-J6 -> -101.8902 | L6: =G6*F6 -> 0 | M6: =H6*F6 -> 84059.415 | N6: =I6*F6 -> 0 | O6: =SUM(M6:N6) -> 84059.415 | P6: =L6-O6 -> -84059.415
A7: 3 | C7: Formwork In Batching Plant | E7: m2 | F7: 825 | H7: 24.202 | J7: =SUM(H7:I7) -> 24.202 | K7: =G7-J7 -> -24.202 | L7: =G7*F7 -> 0 | M7: =H7*F7 -> 19966.65 | N7: =I7*F7 -> 0 | O7: =SUM(M7:N7) -> 19966.65 | P7: =L7-O7 -> -19966.65
A8: 4 | C8: Formwork In Precast Units | E8: m2 | F8: 825 | H8: 5462.748 | J8: =SUM(H8:I8) -> 5462.748 | K8: =G8-J8 -> -5462.748 | L8: =G8*F8 -> 0 | M8: =H8*F8 -> 4506767.1 | N8: =I8*F8 -> 0 | O8: =SUM(M8:N8) -> 4506767.1 | P8: =L8-O8 -> -4506767.1
A9: 5 | C9: Strapping/Striking of Formwork | E9: m2 | F9: 357.5 | H9: 5588.8402 | J9: =SUM(H9:I9) -> 5588.8402 | K9: =G9-J9 -> -5588.8402 | L9: =G9*F9 -> 0 | M9: =H9*F9 -> 1998010.4 | N9: =I9*F9 -> 0 | O9: =SUM(M9:N9) -> 1998010.4 | P9: =L9-O9 -> -1998010.4
A10: 6 | C10: Woodworks in Containers and Security Houses | E10: m2 | F10: 825 | H10: 170.04 | J10: =SUM(H10:I10) -> 170.04 | K10: =G10-J10 -> -170.04 | L10: =G10*F10 -> 0 | M10: =H10*F10 -> 140283 | N10: =I10*F10 -> 0 | O10: =SUM(M10:N10) -> 140283 | P10: =L10-O10 -> -140283
A11: 7 | C11: G15 Concrete Blinding In Batching Plant | E11: m3 | F11: 275 | H11: 28.8 | J11: =SUM(H11:I11) -> 28.8 | K11: =G11-J11 -> -28.8 | L11: =G11*F11 -> 0 | M11: =H11*F11 -> 7920 | N11: =I11*F11 -> 0 | O11: =SUM(M11:N11) -> 7920 | P11: =L11-O11 -> -7920
A12: 8 | C12: Block Laying in Yard | E12: m2 | F12: 770 | H12: 129.09 | J12: =SUM(H12:I12) -> 129.09 | K12: =G12-J12 -> -129.09 | L12: =G12*F12 -> 0 | M12: =H12*F12 -> 99399.3 | N12: =I12*F12 -> 0 | O12: =SUM(M12:N12) -> 99399.3 | P12: =L12-O12 -> -99399.3
A13: 9 | C13: Block Laying & Infilling in Yard | E13: m2 | F13: 1100 | H13: 86.93 | J13: =SUM(H13:I13) -> 86.93 | K13: =G13-J13 -> -86.93 | L13: =G13*F13 -> 0 | M13: =H13*F13 -> 95623 | N13: =I13*F13 -> 0 | O13: =SUM(M13:N13) -> 95623 | P13: =L13-O13 -> -95623
A14: 10 | C14: Block Laying & Infilling in Bridge Foundation | E14: m2 | F14: 1100 | H14: 1148.55 | J14: =SUM(H14:I14) -> 1148.55 | K14: =G14-J14 -> -1148.55 | L14: =G14*F14 -> 0 | M14: =H14*F14 -> 1263405 | N14: =I14*F14 -> 0 | O14: =SUM(M14:N14) -> 1263405 | P14: =L14-O14 -> -1263405
A15: 11 | C15: G25 Conc. in Generator House/Iron Bending Floor | E15: m3 | F15: 1100 | H15: 33.29361 | J15: =SUM(H15:I15) -> 33.29361 | K15: =G15-J15 -> -33.29361 | L15: =G15*F15 -> 0 | M15: =H15*F15 -> 36622.972 | N15: =I15*F15 -> 0 | O15: =SUM(M15:N15) -> 36622.972 | P15: =L15-O15 -> -36622.972
A16: 12 | C16: G25 Concrete in Batching Plant | E16: m3 | F16: 1100 | H16: 102.6894 | J16: =SUM(H16:I16) -> 102.6894 | K16: =G16-J16 -> -102.6894 | L16: =G16*F16 -> 0 | M16: =H16*F16 -> 112958.34 | N16: =I16*F16 -> 0 | O16: =SUM(M16:N16) -> 112958.34 | P16: =L16-O16 -> -112958.34
... A24: 20 | C24: Daywork - Workmen | E24: Days | F24: 3300 | H24: 505 | J24: =SUM(H24:I24) -> 505 | K24: =G24-J24 -> -505 | L24: =G24*F24 -> 0 | M24: =H24*F24 -> 1666500 | N24: =I24*F24 -> 0 | O24: =SUM(M24:N24) -> 1666500 | P24: =L24-O24 -> -1666500
H25: 0 | J25: =SUM(H25:I25) -> 0 | K25: =G25-J25 -> 0 | L25: =G25*F25 -> 0 | M25: =H25*F25 -> 0 | N25: =I25*F25 -> 0 | O25: =SUM(M25:N25) -> 0 | P25: =L25-O25 -> 0
B26: IBRAHIM MUHAMMED | H26: 0 | J26: =SUM(H26:I26) -> 0 | K26: =G26-J26 -> 0 | L26: =G26*F26 -> 0 | M26: =H26*F26 -> 0 | N26: =I26*F26 -> 0 | O26: =SUM(M26:N26) -> 0 | P26: =L26-O26 -> 0
A27: 1 | C27: Cuting and Bending Reinforcement Bars in Plant/Yard | E27: Ton | F27: 12100 | H27: 9.0994009 | J27: =SUM(H27:I27) -> 9.0994009 | K27: =G27-J27 -> -9.0994009 | L27: =G27*F27 -> 0 | M27: =H27*F27 -> 110102.75 | N27: =I27*F27 -> 0 | O27: =SUM(M27:N27) -> 110102.75 | P27: =L27-O27 -> -110102.75
A28: 2 | C28: Cuting and Bending Reinforcement Bars in Bridge Parapets | E28: Ton | F28: 12100 | H28: 38.064815 | J28: =SUM(H28:I28) -> 38.064815 | K28: =G28-J28 -> -38.064815 | L28: =G28*F28 -> 0 | M28: =H28*F28 -> 460584.26 | N28: =I28*F28 -> 0 | O28: =SUM(M28:N28) -> 460584.26 | P28: =L28-O28 -> -460584.26
A29: 3 | C29: Cuting and Bending Reinforcement Bars in Bridge Beams | E29: Ton | F29: 12100 | H29: 315.00998 | J29: =SUM(H29:I29) -> 315.00998 | K29: =G29-J29 -> -315.00998 | L29: =G29*F29 -> 0 | M29: =H29*F29 -> 3811620.8 | N29: =I29*F29 -> 0 | O29: =SUM(M29:N29) -> 3811620.8 | P29: =L29-O29 -> -3811620.8
A30: 4 | C30: Cuting and Bending Reinforcement Bars in Bridge Foundation | E30: Ton | F30: 12100 | H30: 73.50693 | J30: =SUM(H30:I30) -> 73.50693 | K30: =G30-J30 -> -73.50693 | L30: =G30*F30 -> 0 | M30: =H30*F30 -> 889433.86 | N30: =I30*F30 -> 0 | O30: =SUM(M30:N30) -> 889433.86 | P30: =L30-O30 -> -889433.86
A31: 5 | C31: Cuting and Bending Reinforcement Bars in Bridge Pier Columns | E31: Ton | F31: 12100 | H31: 26.121716 | J31: =SUM(H31:I31) -> 26.121716 | K31: =G31-J31 -> -26.121716 | L31: =G31*F31 -> 0 | M31: =H31*F31 -> 316072.76 | N31: =I31*F31 -> 0 | O31: =SUM(M31:N31) -> 316072.76 | P31: =L31-O31 -> -316072.76
A32: 6 | C32: Fixing Reinforcement Bars in Batching Plant/Yard | E32: Ton | F32: 8800 | H32: 9.0994009 | J32: =SUM(H32:I32) -> 9.0994009 | K32: =G32-J32 -> -9.0994009 | L32: =G32*F32 -> 0 | M32: =H32*F32 -> 80074.728 | N32: =I32*F32 -> 0 | O32: =SUM(M32:N32) -> 80074.728 | P32: =L32-O32 -> -80074.728
A33: 7 | C33: Fixing Reinforcement Bars in Bridge Parapets | E33: Ton | F33: 8800 | H33: 38.064815 | J33: =SUM(H33:I33) -> 38.064815 | K33: =G33-J33 -> -38.064815 | L33: =G33*F33 -> 0 | M33: =H33*F33 -> 334970.37 | N33: =I33*F33 -> 0 | O33: =SUM(M33:N33) -> 334970.37 | P33: =L33-O33 -> -334970.37
A34: 8 | C34: Fixing Reinforcement Bars in Bridge Beams | E34: Ton | F34: 8800 | H34: 278.31321 | J34: =SUM(H34:I34) -> 278.31321 | K34: =G34-J34 -> -278.31321 | L34: =G34*F34 -> 0 | M34: =H34*F34 -> 2449156.2 | N34: =I34*F34 -> 0 | O34: =SUM(M34:N34) -> 2449156.2 | P34: =L34-O34 -> -2449156.2
A35: 9 | C35: Fixing Reinforcement Bars in Bridge Foundation | E35: Ton | F35: 8800 | H35: 70.165648 | J35: =SUM(H35:I35) -> 70.165648 | K35: =G35-J35 -> -70.165648 | L35: =G35*F35 -> 0 | M35: =H35*F35 -> 617457.7 | N35: =I35*F35 -> 0 | O35: =SUM(M35:N35) -> 617457.7 | P35: =L35-O35 -> -617457.7
A36: 10 | C36: Fixing Reinforcement Bars in Bridge Pier Columns | E36: Ton | F36: 8800 | H36: 26.121716 | J36: =SUM(H36:I36) -> 26.121716 | K36: =G36-J36 -> -26.121716 | L36: =G36*F36 -> 0 | M36: =H36*F36 -> 229871.1 | N36: =I36*F36 -> 0 | O36: =SUM(M36:N36) -> 229871.1 | P36: =L36-O36 -> -229871.1
A37: 11 | C37: Off Loading of Reinforcement Bars | E37: Ton | F37: 1100 | H37: 251 | J37: =SUM(H37:I37) -> 251 | K37: =G37-J37 -> -251 | L37: =G37*F37 -> 0 | M37: =H37*F37 -> 276100 | N37: =I37*F37 -> 0 | O37: =SUM(M37:N37) -> 276100 | P37: =L37-O37 -> -276100
A38: 12 | C38: Daywork - Workmen | E38: Days | F38: 3300 | H38: 63.5 | J38: =SUM(H38:I38) -> 63.5 | K38: =G38-J38 -> -63.5 | L38: =G38*F38 -> 0 | M38: =H38*F38 -> 209550 | N38: =I38*F38 -> 0 | O38: =SUM(M38:N38) -> 209550 | P38: =L38-O38 -> -209550
B40: UMAR AMINU | H40: 0 | J40: =SUM(H40:I40) -> 0 | K40: =G40-J40 -> 0 | L40: =G40*F40 -> 0 | M40: =H40*F40 -> 0 | N40: =I40*F40 -> 0 | O40: =SUM(M40:N40) -> 0 | P40: =L40-O40 -> 0
A41: 1 | C41: Excavation for Soakaway | E41: m3 | F41: 1 | H41: 90000 | J41: =SUM(H41:I41) -> 90000 | K41: =G41-J41 -> -90000 | L41: =G41*F41 -> 0 | M41: =H41*F41 -> 90000 | N41: =I41*F41 -> 0 | O41: =SUM(M41:N41) -> 90000 | P41: =L41-O41 -> -90000
A42: 2 | C42: Backfiling for Soakaway | E42: m3 | F42: 1 | H42: 15000 | J42: =SUM(H42:I42) -> 15000 | K42: =G42-J42 -> -15000 | L42: =G42*F42 -> 0 | M42: =H42*F42 -> 15000 | N42: =I42*F42 -> 0 | O42: =SUM(M42:N42) -> 15000 | P42: =L42-O42 -> -15000
A43: 3 | C43: Block Laying in Toilet Building | E43: m2 | F43: 1 | H43: 59965.5 | J43: =SUM(H43:I43) -> 59965.5 | K43: =G43-J43 -> -59965.5 | L43: =G43*F43 -> 0 | M43: =H43*F43 -> 59965.5 | N43: =I43*F43 -> 0 | O43: =SUM(M43:N43) -> 59965.5 | P43: =L43-O43 -> -59965.5
A44: 4 | C44: Block Laying & Infilling in Soakaway | E44: m2 | F44: 1 | H44: 23186.1 | J44: =SUM(H44:I44) -> 23186.1 | K44: =G44-J44 -> -23186.1 | L44: =G44*F44 -> 0 | M44: =H44*F44 -> 23186.1 | N44: =I44*F44 -> 0 | O44: =SUM(M44:N44) -> 23186.1 | P44: =L44-O44 -> -23186.1
A45: 5 | C45: Plastering in Soakaway | E45: m2 | F45: 1 | H45: 84829.78 | J45: =SUM(H45:I45) -> 84829.78 | K45: =G45-J45 -> -84829.78 | L45: =G45*F45 -> 0 | M45: =H45*F45 -> 84829.78 | N45: =I45*F45 -> 0 | O45: =SUM(M45:N45) -> 84829.78 | P45: =L45-O45 -> -84829.78
H46: 0 | J46: =SUM(H46:I46) -> 0 | K46: =G46-J46 -> 0 | L46: =G46*F46 -> 0 | M46: =H46*F46 -> 0 | N46: =I46*F46 -> 0 | O46: =SUM(M46:N46) -> 0 | P46: =L46-O46 -> 0
B47: PAM JAMA JAMA | H47: 0 | J47: =SUM(H47:I47) -> 0 | K47: =G47-J47 -> 0 | L47: =G47*F47 -> 0 | M47: =H47*F47 -> 0 | N47: =I47*F47 -> 0 | O47: =SUM(M47:N47) -> 0 | P47: =L47-O47 -> 0
A48: 1 | C48: Batching of Concrete | E48: m3 | F48: 440 | H48: 1439.5 | J48: =SUM(H48:I48) -> 1439.5 | K48: =G48-J48 -> -1439.5 | L48: =G48*F48 -> 0 | M48: =H48*F48 -> 633380 | N48: =I48*F48 -> 0 | O48: =SUM(M48:N48) -> 633380 | P48: =L48-O48 -> -633380
A49: 2 | C49: Daywork - Workmen | E49: Days | F49: 3300 | H49: 123 | J49: =SUM(H49:I49) -> 123 | K49: =G49-J49 -> -123 | L49: =G49*F49 -> 0 | M49: =H49*F49 -> 405900 | N49: =I49*F49 -> 0 | O49: =SUM(M49:N49) -> 405900 | P49: =L49-O49 -> -405900
H50: 0 | J50: =SUM(H50:I50) -> 0 | K50: =G50-J50 -> 0 | L50: =G50*F50 -> 0 | M50: =H50*F50 -> 0 | N50: =I50*F50 -> 0 | O50: =SUM(M50:N50) -> 0 | P50: =L50-O50 -> 0
B51: SILAS IKEDICHI & SONS | H51: 0 | J51: =SUM(H51:I51) -> 0 | K51: =G51-J51 -> 0 | L51: =G51*F51 -> 0 | M51: =H51*F51 -> 0 | N51: =I51*F51 -> 0 | O51: =SUM(M51:N51) -> 0 | P51: =L51-O51 -> 0
A52: 1 | C52: Casting and Packing of 9" Sancrete Blocks | E52: No | F52: 143 | H52: 6678 | J52: =SUM(H52:I52) -> 6678 | M52: =H52*F52 -> 954954 | N52: =I52*F52 -> 0 | O52: =SUM(M52:N52) -> 954954 | P52: =L52-O52 -> -954954
A53: 2 | C53: Casting of Biscuit | E53: No | F53: 5.5 | H53: 28907 | J53: =SUM(H53:I53) -> 28907 | M53: =H53*F53 -> 158988.5 | N53: =I53*F53 -> 0 | O53: =SUM(M53:N53) -> 158988.5 | P53: =L53-O53 -> -158988.5
A54: 3 | C54: Batching of Concrete | E54: m3 | F54: 440 | H54: 1842.1 | J54: =SUM(H54:I54) -> 1842.1 | K54: =G54-J54 -> -1842.1 | L54: =+I54*F54 -> 0 | M54: =H54*F54 -> 810524 | N54: =I54*F54 -> 0 | O54: =SUM(M54:N54) -> 810524 | P54: =L54-O54 -> -810524
A55: 4 | C55: Daywork - Workmen | E55: Days | F55: 3300 | H55: 124 | J55: =SUM(H55:I55) -> 124 | M55: =H55*F55 -> 409200 | N55: =I55*F55 -> 0 | O55: =SUM(M55:N55) -> 409200 | P55: =L55-O55 -> -409200
H56: 0 | J56: =SUM(H56:I56) -> 0 | K56: =G56-J56 -> 0 | L56: =+I56*F56 -> 0 | M56: =H56*F56 -> 0 | N56: =I56*F56 -> 0 | O56: =SUM(M56:N56) -> 0 | P56: =L56-O56 -> 0
B57: DAVID DELL | H57: 0 | J57: =SUM(H57:I57) -> 0 | K57: =G57-J57 -> 0 | L57: =+I57*F57 -> 0 | M57: =H57*F57 -> 0 | N57: =I57*F57 -> 0 | O57: =SUM(M57:N57) -> 0 | P57: =L57-O57 -> 0
A58: 1 | C58: Formwork In Batching Plant | E58: m2 | F58: 825 | H58: 23.4723 | J58: =SUM(H58:I58) -> 23.4723 | K58: =G58-J58 -> -23.4723 | L58: =G58*F58 -> 0 | M58: =H58*F58 -> 19364.647 | N58: =I58*F58 -> 0 | O58: =SUM(M58:N58) -> 19364.647 | P58: =L58-O58 -> -19364.647
A59: 2 | C59: Batching of Concrete | E59: m3 | F59: 440 | H59: 7 | J59: =SUM(H59:I59) -> 7 | K59: =G59-J59 -> -7 | L59: =G59*F59 -> 0 | M59: =H59*F59 -> 3080 | N59: =I59*F59 -> 0 | O59: =SUM(M59:N59) -> 3080 | P59: =L59-O59 -> -3080
A60: 3 | C60: Formwork In Bridge Pier Bases | E60: m2 | F60: 825 | H60: 734.4 | J60: =SUM(H60:I60) -> 734.4 | K60: =G60-J60 -> -734.4 | L60: =G60*F60 -> 0 | M60: =H60*F60 -> 605880 | N60: =I60*F60 -> 0 | O60: =SUM(M60:N60) -> 605880 | P60: =L60-O60 -> -605880
A61: 4 | C61: Formwork In Bridge Piers Columns | E61: m2 | F61: 825 | H61: 1358.4 | J61: =SUM(H61:I61) -> 1358.4 | K61: =G61-J61 -> -1358.4 | L61: =G61*F61 -> 0 | M61: =H61*F61 -> 1120680 | N61: =I61*F61 -> 0 | O61: =SUM(M61:N61) -> 1120680 | P61: =L61-O61 -> -1120680
A62: 5 | C62: Strapping/Striking of Formwork | E62: m2 | F62: 357.5 | H62: 2116.2723 | J62: =SUM(H62:I62) -> 2116.2723 | K62: =G62-J62 -> -2116.2723 | L62: =G62*F62 -> 0 | M62: =H62*F62 -> 756567.35 | N62: =I62*F62 -> 0 | O62: =SUM(M62:N62) -> 756567.35 | P62: =L62-O62 -> -756567.35
A63: 6 | C63: G25 Concrete in Batching Plant | E63: m3 | F63: 1100 | H63: 2.58186 | J63: =SUM(H63:I63) -> 2.58186 | K63: =G63-J63 -> -2.58186 | L63: =G63*F63 -> 0 | M63: =H63*F63 -> 2840.046 | N63: =I63*F63 -> 0 | O63: =SUM(M63:N63) -> 2840.046 | P63: =L63-O63 -> -2840.046
A64: 7 | C64: G30 Concrete in Bridge Pier Bases | E64: m3 | F64: 1100 | H64: 691.104 | J64: =SUM(H64:I64) -> 691.104 | K64: =G64-J64 -> -691.104 | L64: =G64*F64 -> 0 | M64: =H64*F64 -> 760214.4 | N64: =I64*F64 -> 0 | O64: =SUM(M64:N64) -> 760214.4 | P64: =L64-O64 -> -760214.4
A65: 8 | C65: G30 Concrete in Bridge Pier Columns | E65: m3 | F65: 1100 | H65: 398.832 | J65: =SUM(H65:I65) -> 398.832 | K65: =G65-J65 -> -398.832 | L65: =G65*F65 -> 0 | M65: =H65*F65 -> 438715.2 | N65: =I65*F65 -> 0 | O65: =SUM(M65:N65) -> 438715.2 | P65: =L65-O65 -> -438715.2
A66: 9 | C66: Precasting of Parapets | E66: No | F66: 5000 | H66: 282 | J66: =SUM(H66:I66) -> 282 | K66: =G66-J66 -> -282 | L66: =G66*F66 -> 0 | M66: =H66*F66 -> 1410000 | N66: =I66*F66 -> 0 | O66: =SUM(M66:N66) -> 1410000 | P66: =L66-O66 -> -1410000
A67: 10 | C67: Fixing of Windows | E67: No | F67: 2500 | H67: 6 | J67: =SUM(H67:I67) -> 6 | K67: =G67-J67 -> -6 | L67: =G67*F67 -> 0 | M67: =H67*F67 -> 15000 | N67: =I67*F67 -> 0 | O67: =SUM(M67:N67) -> 15000 | P67: =L67-O67 -> -15000
A68: 11 | C68: Fixing of Doors | E68: No | F68: 4500 | H68: 2 | J68: =SUM(H68:I68) -> 2 | K68: =G68-J68 -> -2 | L68: =G68*F68 -> 0 | M68: =H68*F68 -> 9000 | N68: =I68*F68 -> 0 | O68: =SUM(M68:N68) -> 9000 | P68: =L68-O68 -> -9000
A69: 12 | C69: Daywork - Workmen | E69: Days | F69: 3300 | H69: 229 | J69: =SUM(H69:I69) -> 229 | K69: =G69-J69 -> -229 | L69: =G69*F69 -> 0 | M69: =H69*F69 -> 755700 | N69: =I69*F69 -> 0 | O69: =SUM(M69:N69) -> 755700 | P69: =L69-O69 -> -755700
H70: 0 | J70: =SUM(H70:I70) -> 0 | K70: =G70-J70 -> 0 | L70: =G70*F70 -> 0 | M70: =H70*F70 -> 0 | N70: =I70*F70 -> 0 | O70: =SUM(M70:N70) -> 0 | P70: =L70-O70 -> 0
B71: S.C. JANG ENTERPRISE | H71: 0 | J71: =SUM(H71:I71) -> 0 | K71: =G71-J71 -> 0 | L71: =G71*F71 -> 0 | M71: =H71*F71 -> 0 | N71: =I71*F71 -> 0 | O71: =SUM(M71:N71) -> 0 | P71: =L71-O71 -> 0
A72: 1 | C72: Casting and Packing of 9" Sancrete Blocks | E72: No | F72: 143 | H72: 2075 | J72: =SUM(H72:I72) -> 2075 | M72: =H72*F72 -> 296725 | N72: =I72*F72 -> 0 | O72: =SUM(M72:N72) -> 296725 | P72: =L72-O72 -> -296725
A73: 2 | C73: Casting of Biscuit | E73: No | F73: 5.5 | H73: 0 | J73: =SUM(H73:I73) -> 0 | M73: =H73*F73 -> 0 | N73: =I73*F73 -> 0 | O73: =SUM(M73:N73) -> 0 | P73: =L73-O73 -> 0
A74: 3 | C74: Batching of Concrete | E74: m3 | F74: 440 | H74: 518 | J74: =SUM(H74:I74) -> 518 | K74: =G74-J74 -> -518 | L74: =+I74*F74 -> 0 | M74: =H74*F74 -> 227920 | N74: =I74*F74 -> 0 | O74: =SUM(M74:N74) -> 227920 | P74: =L74-O74 -> -227920
A75: 4 | C75: Cuting and Bending Reinforcement Bars in Bridge Pier Columns | E75: Ton | F75: 12100 | H75: 15.012699 | J75: =SUM(H75:I75) -> 15.012699 | M75: =H75*F75 -> 181653.65 | N75: =I75*F75 -> 0 | O75: =SUM(M75:N75) -> 181653.65 | P75: =L75-O75 -> -181653.65
C76: Fixing Reinforcement Bars in Bridge Pier Columns | E76: Ton | F76: 8800 | H76: 11.351457 | J76: =SUM(H76:I76) -> 11.351457 | K76: =G76-J76 -> -11.351457 | L76: =G76*F76 -> 0 | M76: =H76*F76 -> 99892.818 | N76: =I76*F76 -> 0 | O76: =SUM(M76:N76) -> 99892.818 | P76: =L76-O76 -> -99892.818
C77: Daywork - Workmen | E77: Days | F77: 3300 | H77: 85 | J77: =SUM(H77:I77) -> 85 | K77: =G77-J77 -> -85 | L77: =G77*F77 -> 0 | M77: =H77*F77 -> 280500 | N77: =I77*F77 -> 0 | O77: =SUM(M77:N77) -> 280500 | P77: =L77-O77 -> -280500
J78: =SUM(H78:I78) -> 0 | K78: =G78-J78 -> 0 | L78: =G78*F78 -> 0 | M78: =H78*F78 -> 0 | N78: =I78*F78 -> 0 | O78: =SUM(M78:N78) -> 0 | P78: =L78-O78 -> 0
J79: =SUM(H79:I79) -> 0 | K79: =G79-J79 -> 0 | L79: =G79*F79 -> 0 | M79: =H79*F79 -> 0 | N79: =I79*F79 -> 0 | O79: =SUM(M79:N79) -> 0 | P79: =L79-O79 -> 0
J80: =SUM(H80:I80) -> 0 | K80: =G80-J80 -> 0 | L80: =G80*F80 -> 0 | M80: =H80*F80 -> 0 | N80: =I80*F80 -> 0 | O80: =SUM(M80:N80) -> 0 | P80: =L80-O80 -> 0
J81: =SUM(H81:I81) -> 0 | K81: =G81-J81 -> 0 | L81: =G81*F81 -> 0 | M81: =H81*F81 -> 0 | N81: =I81*F81 -> 0 | O81: =SUM(M81:N81) -> 0 | P81: =L81-O81 -> 0
J82: =SUM(H82:I82) -> 0 | K82: =G82-J82 -> 0 | L82: =G82*F82 -> 0 | M82: =H82*F82 -> 0 | N82: =I82*F82 -> 0 | O82: =SUM(M82:N82) -> 0 | P82: =L82-O82 -> 0
J83: =SUM(H83:I83) -> 0 | K83: =G83-J83 -> 0 | L83: =G83*F83 -> 0 | M83: =H83*F83 -> 0 | N83: =I83*F83 -> 0 | O83: =SUM(M83:N83) -> 0 | P83: =L83-O83 -> 0
J84: =SUM(H84:I84) -> 0 | K84: =G84-J84 -> 0 | L84: =G84*F84 -> 0 | M84: =H84*F84 -> 0 | N84: =I84*F84 -> 0 | O84: =SUM(M84:N84) -> 0 | P84: =L84-O84 -> 0
J85: =SUM(H85:I85) -> 0 | K85: =G85-J85 -> 0 | L85: =G85*F85 -> 0 | M85: =H85*F85 -> 0 | N85: =I85*F85 -> 0 | O85: =SUM(M85:N85) -> 0 | P85: =L85-O85 -> 0
J86: =SUM(H86:I86) -> 0 | K86: =G86-J86 -> 0 | L86: =G86*F86 -> 0 | M86: =H86*F86 -> 0 | N86: =I86*F86 -> 0 | O86: =SUM(M86:N86) -> 0 | P86: =L86-O86 -> 0
J87: =SUM(H87:I87) -> 0 | K87: =G87-J87 -> 0 | L87: =G87*F87 -> 0 | M87: =H87*F87 -> 0 | N87: =I87*F87 -> 0 | O87: =SUM(M87:N87) -> 0 | P87: =L87-O87 -> 0
J88: =SUM(H88:I88) -> 0 | K88: =G88-J88 -> 0 | L88: =G88*F88 -> 0 | M88: =H88*F88 -> 0 | N88: =I88*F88 -> 0 | O88: =SUM(M88:N88) -> 0 | P88: =L88-O88 -> 0
J89: =SUM(H89:I89) -> 0 | K89: =G89-J89 -> 0 | L89: =G89*F89 -> 0 | M89: =H89*F89 -> 0 | N89: =I89*F89 -> 0 | O89: =SUM(M89:N89) -> 0 | P89: =L89-O89 -> 0
... J92: =SUM(H92:I92) -> 0 | K92: =G92-J92 -> 0 | L92: =G92*F92 -> 0 | M92: =H92*F92 -> 0 | N92: =I92*F92 -> 0 | O92: =SUM(M92:N92) -> 0 | P92: =L92-O92 -> 0
H93: 0 | J93: =SUM(H93:I93) -> 0 | K93: =G93-J93 -> 0 | L93: =G93*F93 -> 0 | M93: =H93*F93 -> 0 | N93: =I93*F93 -> 0 | O93: =SUM(M93:N93) -> 0 | P93: =L93-O93 -> 0
J94: =SUM(H94:I94) -> 0 | K94: =G94-J94 -> 0 | L94: =G94*F94 -> 0 | M94: =H94*F94 -> 0 | N94: =I94*F94 -> 0 | O94: =SUM(M94:N94) -> 0 | P94: =L94-O94 -> 0
J95: =SUM(H95:I95) -> 0 | K95: =G95-J95 -> 0 | L95: =G95*F95 -> 0 | M95: =H95*F95 -> 0 | N95: =I95*F95 -> 0 | O95: =SUM(M95:N95) -> 0 | P95: =L95-O95 -> 0
J96: =SUM(H96:I96) -> 0 | K96: =G96-J96 -> 0 | L96: =G96*F96 -> 0 | M96: =H96*F96 -> 0 | N96: =I96*F96 -> 0 | O96: =SUM(M96:N96) -> 0 | P96: =L96-O96 -> 0
J97: =SUM(H97:I97) -> 0 | K97: =G97-J97 -> 0 | L97: =G97*F97 -> 0 | M97: =H97*F97 -> 0 | N97: =I97*F97 -> 0 | O97: =SUM(M97:N97) -> 0 | P97: =L97-O97 -> 0
J98: =SUM(H98:I98) -> 0 | K98: =G98-J98 -> 0 | L98: =G98*F98 -> 0 | M98: =H98*F98 -> 0 | N98: =I98*F98 -> 0 | O98: =SUM(M98:N98) -> 0 | P98: =L98-O98 -> 0
J99: =SUM(H99:I99) -> 0 | K99: =G99-J99 -> 0 | L99: =G99*F99 -> 0 | M99: =H99*F99 -> 0 | N99: =I99*F99 -> 0 | O99: =SUM(M99:N99) -> 0 | P99: =L99-O99 -> 0
K100: =SUM(K4:K99) -> -301565.23 | L100: =SUM(L4:L99) -> 0 | M100: =SUM(M4:M99) -> 34045590 | N100: =SUM(N4:N99) -> 0 | O100: =SUM(O4:O99) -> 34045590 | P100: =SUM(P4:P99) -> -34045590

Sheet Precast
A1: MATERIAL STOCKS | K1: Date: | L1: ='Weekly Summary'!E1 -> 45717 | N1: ='Weekly Summary'!F1 -> Week No: | O1: ='Weekly Summary'!G1 -> 9
A2: =#REF! -> #REF!
A3: S/No | B3: DESCRIPTION | C3: SIZE | D3: UOM | E3: BEME Amount | F3: Previous Cast Amount | G3: Cast This week | H3: Total Cast to Date | I3: Balance Required | J3: Used Previous | K3: Used This week | L3: Total Used | M3: Balance Available | N3: Closing Stock | O3: Variance | P3: REMARKS
A4: 1 | B4: Bridge Beam | F4: 0 | H4: =SUM(F4:G4) -> 0 | I4: =E4-H4 -> 0 | J4: 0 | K4: 0 | L4: =SUM(J4:K4) -> 0 | M4: =H4-L4 -> 0 | N4: 0 | O4: =M4-N4 -> 0
A5: 2 | B5: Bridge Parapet | G5: 0 | H5: =SUM(F5:G5) -> 0 | I5: =E5-H5 -> 0 | J5: =H5+I5 -> 0 | L5: =SUM(J5:K5) -> 0 | M5: =H5-L5 -> 0 | O5: =M5-N5 -> 0
A6: 3 | H6: =SUM(F6:G6) -> 0 | I6: =E6-H6 -> 0 | J6: =H6+I6 -> 0 | L6: =SUM(J6:K6) -> 0 | M6: =H6-L6 -> 0 | O6: =M6-N6 -> 0
A7: 4 | H7: =SUM(F7:G7) -> 0 | I7: =E7-H7 -> 0 | J7: =H7+I7 -> 0 | L7: =SUM(J7:K7) -> 0 | M7: =H7-L7 -> 0 | O7: =M7-N7 -> 0
A8: 5 | H8: =SUM(F8:G8) -> 0 | I8: =E8-H8 -> 0 | J8: =H8+I8 -> 0 | L8: =SUM(J8:K8) -> 0 | M8: =H8-L8 -> 0 | O8: =M8-N8 -> 0
A9: 6 | H9: =SUM(F9:G9) -> 0 | I9: =E9-H9 -> 0 | J9: =H9+I9 -> 0 | L9: =SUM(J9:K9) -> 0 | M9: =H9-L9 -> 0 | O9: =M9-N9 -> 0
A10: 7 | H10: =SUM(F10:G10) -> 0 | I10: =E10-H10 -> 0 | J10: =H10+I10 -> 0 | L10: =SUM(J10:K10) -> 0 | M10: =H10-L10 -> 0 | O10: =M10-N10 -> 0
A11: 8 | H11: =SUM(F11:G11) -> 0 | I11: =E11-H11 -> 0 | J11: =H11+I11 -> 0 | L11: =SUM(J11:K11) -> 0 | M11: =H11-L11 -> 0 | O11: =M11-N11 -> 0
A12: 9 | H12: =SUM(F12:G12) -> 0 | I12: =E12-H12 -> 0 | J12: =H12+I12 -> 0 | L12: =SUM(J12:K12) -> 0 | M12: =H12-L12 -> 0 | O12: =M12-N12 -> 0
A13: 10 | H13: =SUM(F13:G13) -> 0 | I13: =E13-H13 -> 0 | J13: =H13+I13 -> 0 | L13: =SUM(J13:K13) -> 0 | M13: =H13-L13 -> 0 | O13: =M13-N13 -> 0
A14: 11 | H14: =SUM(F14:G14) -> 0 | I14: =E14-H14 -> 0 | J14: =H14+I14 -> 0 | L14: =SUM(J14:K14) -> 0 | M14: =H14-L14 -> 0 | O14: =M14-N14 -> 0
A15: 12 | H15: =SUM(F15:G15) -> 0 | I15: =E15-H15 -> 0 | J15: =H15+I15 -> 0 | L15: =SUM(J15:K15) -> 0 | M15: =H15-L15 -> 0 | O15: =M15-N15 -> 0
A16: 13 | H16: =SUM(F16:G16) -> 0 | I16: =E16-H16 -> 0 | J16: =H16+I16 -> 0 | L16: =SUM(J16:K16) -> 0 | M16: =H16-L16 -> 0 | O16: =M16-N16 -> 0
A17: 14 | H17: =SUM(F17:G17) -> 0 | I17: =E17-H17 -> 0 | J17: =H17+I17 -> 0 | L17: =SUM(J17:K17) -> 0 | M17: =H17-L17 -> 0 | O17: =M17-N17 -> 0
... A21: 18 | H21: =SUM(F21:G21) -> 0 | I21: =E21-H21 -> 0 | J21: =H21+I21 -> 0 | L21: =SUM(J21:K21) -> 0 | M21: =H21-L21 -> 0 | O21: =M21-N21 -> 0
A22: =A21+1 -> 19 | H22: =SUM(F22:G22) -> 0 | I22: =E22-H22 -> 0 | J22: =H22+I22 -> 0 | L22: =SUM(J22:K22) -> 0 | M22: =H22-L22 -> 0 | O22: =M22-N22 -> 0
A23: =A22+1 -> 20 | H23: =SUM(F23:G23) -> 0 | I23: =E23-H23 -> 0 | J23: =H23+I23 -> 0 | L23: =SUM(J23:K23) -> 0 | M23: =H23-L23 -> 0 | O23: =M23-N23 -> 0
A24: =A23+1 -> 21 | H24: =SUM(F24:G24) -> 0 | I24: =E24-H24 -> 0 | J24: =H24+I24 -> 0 | L24: =SUM(J24:K24) -> 0 | M24: =H24-L24 -> 0 | O24: =M24-N24 -> 0
A25: =A24+1 -> 22 | H25: =SUM(F25:G25) -> 0 | I25: =E25-H25 -> 0 | J25: =H25+I25 -> 0 | L25: =SUM(J25:K25) -> 0 | M25: =H25-L25 -> 0 | O25: =M25-N25 -> 0
A26: =A25+1 -> 23 | H26: =SUM(F26:G26) -> 0 | I26: =E26-H26 -> 0 | J26: =H26+I26 -> 0 | L26: =SUM(J26:K26) -> 0 | M26: =H26-L26 -> 0 | O26: =M26-N26 -> 0
A27: =A26+1 -> 24 | H27: =SUM(F27:G27) -> 0 | I27: =E27-H27 -> 0 | J27: =H27+I27 -> 0 | L27: =SUM(J27:K27) -> 0 | M27: =H27-L27 -> 0 | O27: =M27-N27 -> 0
H28: =SUM(F28:G28) -> 0 | I28: =E28-H28 -> 0 | J28: =H28+I28 -> 0 | L28: =SUM(J28:K28) -> 0 | M28: =H28-L28 -> 0 | O28: =M28-N28 -> 0
H29: =SUM(F29:G29) -> 0 | I29: =E29-H29 -> 0 | J29: =H29+I29 -> 0 | L29: =SUM(J29:K29) -> 0 | M29: =H29-L29 -> 0 | O29: =M29-N29 -> 0
H30: =SUM(F30:G30) -> 0 | I30: =E30-H30 -> 0 | J30: =H30+I30 -> 0 | L30: =SUM(J30:K30) -> 0 | M30: =H30-L30 -> 0 | O30: =M30-N30 -> 0
O31: =SUM(O4:O30) -> 0

Sheet Bill 1 Summary
A1: BILL 1 SCHEDULE | J1: Date: | L1: ='Weekly Summary'!E1 -> 45717 | N1: ='Weekly Summary'!F1 -> Week No: | O1: ='Weekly Summary'!G1 -> 9 | P1: Instructions
A2: =#REF! -> #REF! | N2: Service Charge: | O2: 0.025 | Q2: CLAIMED IN CERTS (Inclusive of Service Charge)
A3: Item NO. | B3: DESCRIPTION | C3: REQUESTED BY MINISTRY | D3: PAID to date by P.W. | F3: OUTSTANDING By P.W. | H3: ="CLAIMED IN CERTS (Net of "&TEXT($O2,"0.00%")&")" -> CLAIMED IN CERTS (Net of 2.50%) | J3: ="PAID BY CLIENT (Net of "&TEXT($O2,"0.00%")&")" -> PAID BY CLIENT (Net of 2.50%) | L3: PAYMENT RECIVED, OUTSTANDING BY PW | N3: Ministry Letter Reference | O3: Request Date | Q3: Cert 1 | R3: Cert 2 | S3: Cert 3 | T3: Cert 4 | U3: Cert 5 | V3: Cert 6 | W3: Cert 7 | X3: Cert 8 | Y3: Cert 9 | Z3: Cert 10 | AA3: Cert 11 | AB3: Cert 12 | AC3: Cert 13 | AD3: Cert 14 | AE3: Cert 15 | AF3: Cert 16 | AG3: Cert 17 | AH3: Cert 18 | AI3: Cert 19 | AJ3: Cert 20 | AK3: Cert 21 | AL3: Cert 22 | AM3: Cert 23 | AN3: Total
P4: Cert Status: | R4: Not Paid | AN4: =SUM(Q4:AM4) -> 0
D5: =SUMIF('Bill 1 Payments'!$E$4:$E$76,'Bill 1 Summary'!B5,'Bill 1 Payments'!$F$4:$F$76) -> 0 | F5: =C5-D5 -> 0 | H5: =AN5/(1+$O$2) -> 0 | J5: =SUMIF($Q$4:$AM$4,"Paid",$Q5:$AM5)/(1+$O$2) -> 0 | L5: =J5-D5 -> 0 | AN5: =SUM(Q5:AM5) -> 0
D6: =SUMIF('Bill 1 Payments'!$E$4:$E$76,'Bill 1 Summary'!B6,'Bill 1 Payments'!$F$4:$F$76) -> 0 | F6: =C6-D6 -> 0 | J6: =SUMIF($Q$4:$AM$4,"Paid",$Q6:$AM6)/(1+$O$2) -> 0 | L6: =J6-D6 -> 0 | R6: 0 | AN6: =SUM(Q6:AM6) -> 0
D7: =SUMIF('Bill 1 Payments'!$E$4:$E$76,'Bill 1 Summary'!B7,'Bill 1 Payments'!$F$4:$F$76) -> 0 | F7: =C7-D7 -> 0 | J7: =SUMIF($Q$4:$AM$4,"Paid",$Q7:$AM7)/(1+$O$2) -> 0 | L7: =J7-D7 -> 0 | R7: 0 | AN7: =SUM(Q7:AM7) -> 0
D8: =SUMIF('Bill 1 Payments'!$E$4:$E$76,'Bill 1 Summary'!B8,'Bill 1 Payments'!$F$4:$F$76) -> 0 | F8: =C8-D8 -> 0 | J8: =SUMIF($Q$4:$AM$4,"Paid",$Q8:$AM8)/(1+$O$2) -> 0 | L8: =J8-D8 -> 0 | R8: 0 | AN8: =SUM(Q8:AM8) -> 0
D9: =SUMIF('Bill 1 Payments'!$E$4:$E$76,'Bill 1 Summary'!B9,'Bill 1 Payments'!$F$4:$F$76) -> 0 | F9: =C9-D9 -> 0 | J9: =SUMIF($Q$4:$AM$4,"Paid",$Q9:$AM9)/(1+$O$2) -> 0 | L9: =J9-D9 -> 0 | R9: 0 | AN9: =SUM(Q9:AM9) -> 0
D10: =SUMIF('Bill 1 Payments'!$E$4:$E$76,'Bill 1 Summary'!B10,'Bill 1 Payments'!$F$4:$F$76) -> 0 | F10: =C10-D10 -> 0 | J10: =SUMIF($Q$4:$AM$4,"Paid",$Q10:$AM10)/(1+$O$2) -> 0 | L10: =J10-D10 -> 0 | R10: 0 | AN10: =SUM(Q10:AM10) -> 0
D11: =SUMIF('Bill 1 Payments'!$E$4:$E$76,'Bill 1 Summary'!B11,'Bill 1 Payments'!$F$4:$F$76) -> 0 | F11: =C11-D11 -> 0 | H11: =AN11/(1+$O$2) -> 0 | J11: =SUMIF($Q$4:$AM$4,"Paid",$Q11:$AM11)/(1+$O$2) -> 0 | L11: =J11-D11 -> 0 | AN11: =SUM(Q11:AM11) -> 0
D12: =SUMIF('Bill 1 Payments'!$E$4:$E$76,'Bill 1 Summary'!B12,'Bill 1 Payments'!$F$4:$F$76) -> 0 | F12: =C12-D12 -> 0 | H12: =AN12/(1+$O$2) -> 0 | J12: =SUMIF($Q$4:$AM$4,"Paid",$Q12:$AM12)/(1+$O$2) -> 0 | L12: =J12-D12 -> 0 | AN12: =SUM(Q12:AM12) -> 0
D13: =SUMIF('Bill 1 Payments'!$E$4:$E$76,'Bill 1 Summary'!B13,'Bill 1 Payments'!$F$4:$F$76) -> 0 | F13: =C13-D13 -> 0 | H13: =AN13/(1+$O$2) -> 0 | J13: =SUMIF($Q$4:$AM$4,"Paid",$Q13:$AM13)/(1+$O$2) -> 0 | L13: =J13-D13 -> 0 | AN13: =SUM(Q13:AM13) -> 0
D14: =SUMIF('Bill 1 Payments'!$E$4:$E$76,'Bill 1 Summary'!B14,'Bill 1 Payments'!$F$4:$F$76) -> 0 | F14: =C14-D14 -> 0 | H14: =AN14/(1+$O$2) -> 0 | J14: =SUMIF($Q$4:$AM$4,"Paid",$Q14:$AM14)/(1+$O$2) -> 0 | L14: =J14-D14 -> 0 | AN14: =SUM(Q14:AM14) -> 0
D15: =SUMIF('Bill 1 Payments'!$E$4:$E$76,'Bill 1 Summary'!B15,'Bill 1 Payments'!$F$4:$F$76) -> 0 | F15: =C15-D15 -> 0 | H15: =AN15/(1+$O$2) -> 0 | J15: =SUMIF($Q$4:$AM$4,"Paid",$Q15:$AM15)/(1+$O$2) -> 0 | L15: =J15-D15 -> 0 | AN15: =SUM(Q15:AM15) -> 0
D16: =SUMIF('Bill 1 Payments'!$E$4:$E$76,'Bill 1 Summary'!B16,'Bill 1 Payments'!$F$4:$F$76) -> 0 | F16: =C16-D16 -> 0 | H16: =AN16/(1+$O$2) -> 0 | J16: =SUMIF($Q$4:$AM$4,"Paid",$Q16:$AM16)/(1+$O$2) -> 0 | L16: =J16-D16 -> 0 | AN16: =SUM(Q16:AM16) -> 0
D17: =SUMIF('Bill 1 Payments'!$E$4:$E$76,'Bill 1 Summary'!B17,'Bill 1 Payments'!$F$4:$F$76) -> 0 | F17: =C17-D17 -> 0 | H17: =AN17/(1+$O$2) -> 0 | J17: =SUMIF($Q$4:$AM$4,"Paid",$Q17:$AM17)/(1+$O$2) -> 0 | L17: =J17-D17 -> 0 | AN17: =SUM(Q17:AM17) -> 0
D18: =SUMIF('Bill 1 Payments'!$E$4:$E$76,'Bill 1 Summary'!B18,'Bill 1 Payments'!$F$4:$F$76) -> 0 | F18: =C18-D18 -> 0 | H18: =AN18/(1+$O$2) -> 0 | J18: =SUMIF($Q$4:$AM$4,"Paid",$Q18:$AM18)/(1+$O$2) -> 0 | L18: =J18-D18 -> 0 | AN18: =SUM(Q18:AM18) -> 0
D19: =SUMIF('Bill 1 Payments'!$E$4:$E$76,'Bill 1 Summary'!B19,'Bill 1 Payments'!$F$4:$F$76) -> 0 | F19: =C19-D19 -> 0 | H19: =AN19/(1+$O$2) -> 0 | J19: =SUMIF($Q$4:$AM$4,"Paid",$Q19:$AM19)/(1+$O$2) -> 0 | L19: =J19-D19 -> 0 | AN19: =SUM(Q19:AM19) -> 0
D20: =SUMIF('Bill 1 Payments'!$E$4:$E$76,'Bill 1 Summary'!B20,'Bill 1 Payments'!$F$4:$F$76) -> 0 | F20: =C20-D20 -> 0 | H20: =AN20/(1+$O$2) -> 0 | J20: =SUMIF($Q$4:$AM$4,"Paid",$Q20:$AM20)/(1+$O$2) -> 0 | L20: =J20-D20 -> 0 | AN20: =SUM(Q20:AM20) -> 0
D21: =SUMIF('Bill 1 Payments'!$E$4:$E$76,'Bill 1 Summary'!B21,'Bill 1 Payments'!$F$4:$F$76) -> 0 | F21: =C21-D21 -> 0 | H21: =AN21/(1+$O$2) -> 0 | J21: =SUMIF($Q$4:$AM$4,"Paid",$Q21:$AM21)/(1+$O$2) -> 0 | L21: =J21-D21 -> 0 | AN21: =SUM(Q21:AM21) -> 0
D22: =SUMIF('Bill 1 Payments'!$E$4:$E$76,'Bill 1 Summary'!B22,'Bill 1 Payments'!$F$4:$F$76) -> 0 | F22: =C22-D22 -> 0 | H22: =AN22/(1+$O$2) -> 0 | J22: =SUMIF($Q$4:$AM$4,"Paid",$Q22:$AM22)/(1+$O$2) -> 0 | L22: =J22-D22 -> 0 | AN22: =SUM(Q22:AM22) -> 0
... D48: =SUMIF('Bill 1 Payments'!$E$4:$E$76,'Bill 1 Summary'!B48,'Bill 1 Payments'!$F$4:$F$76) -> 0 | F48: =C48-D48 -> 0 | H48: =AN48/(1+$O$2) -> 0 | J48: =SUMIF($Q$4:$AM$4,"Paid",$Q48:$AM48)/(1+$O$2) -> 0 | L48: =J48-D48 -> 0 | AN48: =SUM(Q48:AM48) -> 0
C49: =SUM(C5:C48) -> 0 | D49: =SUM(D5:D48) -> 0 | F49: =SUM(F5:F48) -> 0 | H49: =SUM(H5:H48) -> 0 | J49: =SUM(J5:J48) -> 0 | L49: =SUM(L5:L23) -> 0 | Q49: =SUM(Q5:Q48) -> 0 | R49: =SUM(R5:R48) -> 0 | S49: =SUM(S5:S48) -> 0 | T49: =SUM(T5:T48) -> 0 | U49: =SUM(U5:U48) -> 0 | V49: =SUM(V5:V48) -> 0 | W49: =SUM(W5:W48) -> 0 | X49: =SUM(X5:X48) -> 0 | ... AN49: =SUM(AN5:AN48) -> 0

Sheet Bill 1 Payments
A1: DETAIL SCHEDULE BILL 1 PAYMENTS | D1: Date: | E1: ='Weekly Summary'!E1 -> 45717 | F1: ='Weekly Summary'!F1 -> Week No: | G1: Instructions
A2: =#REF! -> #REF!
A3: Date | B3: Payee | C3: Bank | D3: Chq No. / Ref | E3: Bill 1 Item | F3: Amount | I3: Wk- YR
I4: =IF(ISBLANK(A4),"",VLOOKUP(A4,Lists!$A$2:$C$5000,3,FALSE))
I5: =IF(ISBLANK(A5),"",VLOOKUP(A5,Lists!$A$2:$C$5000,3,FALSE))
I6: =IF(ISBLANK(A6),"",VLOOKUP(A6,Lists!$A$2:$C$5000,3,FALSE))
I7: =IF(ISBLANK(A7),"",VLOOKUP(A7,Lists!$A$2:$C$5000,3,FALSE))
I8: =IF(ISBLANK(A8),"",VLOOKUP(A8,Lists!$A$2:$C$5000,3,FALSE))
I9: =IF(ISBLANK(A9),"",VLOOKUP(A9,Lists!$A$2:$C$5000,3,FALSE))
I10: =IF(ISBLANK(A10),"",VLOOKUP(A10,Lists!$A$2:$C$5000,3,FALSE))
I11: =IF(ISBLANK(A11),"",VLOOKUP(A11,Lists!$A$2:$C$5000,3,FALSE))
I12: =IF(ISBLANK(A12),"",VLOOKUP(A12,Lists!$A$2:$C$5000,3,FALSE))
I13: =IF(ISBLANK(A13),"",VLOOKUP(A13,Lists!$A$2:$C$5000,3,FALSE))
I14: =IF(ISBLANK(A14),"",VLOOKUP(A14,Lists!$A$2:$C$5000,3,FALSE))
I15: =IF(ISBLANK(A15),"",VLOOKUP(A15,Lists!$A$2:$C$5000,3,FALSE))
... I76: =IF(ISBLANK(A76),"",VLOOKUP(A76,Lists!$A$2:$C$5000,3,FALSE))
E77: Total All Bill 1 Items to date: | F77: =SUM(F4:F76) -> 0
F78: =SUM('Bill 1 Summary'!D49)-F77 -> 0

Sheet Lists
A1: Date | B1: Week no. | C1: Wk & Year | E1: UOM | F1: Description | H1: Cost Categories | J1: Plant Categories | L1: Cost Assumption | M1: Rate | N1: Basis | P1: Contract Bank Details | S1: CONCRETE CLASS: | T1: 15N/mm² | W1: 20N/mm² | Z1: 25N/mm² | AC1: 30N/mm² | AF1: 40N/mm² | AJ1: P.W. NIGERIA LIMITED | AN1: NOVEMBER 2015
A2: 43831 | B2: =WEEKNUM(A2) -> 1 | C2: 1-20 | E2: m3 | F2: Cubic Metre | H2: Plant | J2: Lowloader | L2: Employer Pension Rate | M2: 0.1 | N2: % | P2: Bank Name: | Q2: First Bank of Nigeria Limited | S2: Bill of Quanties for Design Mix of concrete | T2: Batch by wt. | V2: Batch by volume | W2: Batch by wt. | Y2: Batch by volume | Z2: Batch by wt. | AB2: Batch by volume | AC2: Batch by wt. | AE2: Batch by volume | AF2: Batch by wt. | AH2: Batch by volume
A3: 43832 | B3: =WEEKNUM(A3) -> 1 | C3: 1-20 | E3: m2 | F3: Metre Squared | H3: AGO | J3: Tippers | L3: Administration Cost | M3: 1400000 | N3: Per Expat | P3: Account Name: | Q3: P.W. NIGERIA LIMITED | AJ3: STANDARD APPROVED RATES FOR SUBCONTRACTS
A4: 43833 | B4: =WEEKNUM(A4) -> 1 | C4: 1-20 | E4: Lm | F4: Linear Metre | H4: Materials | J4: Tipping Trailers | L4: VAT (Value Added Tax) | M4: 0.075 | N4: % | P4: Account Number: | Q4: 2001507098 | T4: kg/m³ | U4: % | V4: m³ | W4: kg/m³ | X4: % | Y4: m³ | Z4: kg/m³ | AA4: % | AB4: m³ | AC4: kg/m³ | AD4: % | AE4: m³ | AF4: kg/m³ | AG4: % | AH4: m³
A5: 43834 | B5: =WEEKNUM(A5) -> 1 | C5: 1-20 | E5: Litre | F5: Litres | H5: Sub Contractors | J5: Trucks | L5: Local Staff Cost | M5: 25000 | N5: Per Week | P5: Sort Code: | Q5: 001084060 | S5: 20mm (3/4 Inch) | T5: 785 | U5: =IF(T$14=0,0,T5/T$14) -> 0.33052632 | V5: 0.586 | W5: 733 | X5: =IF(W$14=0,0,W5/W$14) -> 0.30541667 | Y5: 0.547 | Z5: 726 | AA5: =IF(Z$14=0,0,Z5/Z$14) -> 0.30262609 | AB5: 0.542 | AD5: =IF(AC$14=0,0,AC5/AC$14) -> 0 | AG5: =IF(AF$14=0,0,AF5/AF$14) -> 0 | AJ5: S/NO | AK5: DESCRIPTION | AM5: UNIT | AN5: APROVED | AO5: COMMENTS
A6: 43835 | B6: =WEEKNUM(A6) -> 2 | C6: 2-20 | E6: Tonne | F6: Metric Tonnes | H6: Local Labour | J6: Flat Bed Trailers | L6: Bill 1 Service Charge | M6: 0.025 | S6: 10mm (1/2 Inch) | T6: 391 | U6: =IF(T$14=0,0,T6/T$14) -> 0.16463158 | V6: 0.294 | W6: 383 | X6: =IF(W$14=0,0,W6/W$14) -> 0.15958333 | Y6: 0.288 | Z6: 365 | AA6: =IF(Z$14=0,0,Z6/Z$14) -> 0.15214673 | AB6: 0.275 | AD6: =IF(AC$14=0,0,AC6/AC$14) -> 0 | AG6: =IF(AF$14=0,0,AF6/AF$14) -> 0 | AN6: RATE (N)
A7: 43836 | B7: =WEEKNUM(A7) -> 2 | C7: 2-20 | E7: Roll | F7: Roll | H7: Overheads | J7: Lorries | L7: Withholding Tax | M7: 0.075 | S7: 12.5mm (3/8 Inch) | U7: =IF(T$14=0,0,T7/T$14) -> 0 | X7: =IF(W$14=0,0,W7/W$14) -> 0 | AA7: =IF(Z$14=0,0,Z7/Z$14) -> 0 | AD7: =IF(AC$14=0,0,AC7/AC$14) -> 0 | AG7: =IF(AF$14=0,0,AF7/AF$14) -> 0 | AK7: EXCAVATION
A8: 43837 | B8: =WEEKNUM(A8) -> 2 | C8: 2-20 | E8: Each | F8: Per Unit | H8: Site Level Expenses | J8: Tractor Units | S8: River Sand | T8: 717 | U8: =IF(T$14=0,0,T8/T$14) -> 0.30189474 | V8: 0.496 | W8: 748 | X8: =IF(W$14=0,0,W8/W$14) -> 0.31166667 | Y8: 0.517 | Z8: 753 | AA8: =IF(Z$14=0,0,Z8/Z$14) -> 0.31388078 | AB8: 0.52 | AD8: =IF(AC$14=0,0,AC8/AC$14) -> 0 | AG8: =IF(AF$14=0,0,AF8/AF$14) -> 0 | AL8: General excavation including any necessary trimming, levelling & compaction of excavated ground surface | AM8: m3 | AN8: 500 | AO8: This is for excavation works carried out solely by the subcontractor. It is not applicable to their attendance on PW excavator.
A9: 43838 | B9: =WEEKNUM(A9) -> 2 | C9: 2-20 | E9: Bags | F9: Per Bag | H9: Bill 1 | J9: Water Tanker Trucks | S9: Quarry Dust | U9: =IF(T$14=0,0,T9/T$14) -> 0 | X9: =IF(W$14=0,0,W9/W$14) -> 0 | AA9: =IF(Z$14=0,0,Z9/Z$14) -> 0 | AD9: =IF(AC$14=0,0,AC9/AC$14) -> 0 | AG9: =IF(AF$14=0,0,AF9/AF$14) -> 0 | AL9: Backfilling & compaction | AM9: m3 | AN9: 200
A10: 43839 | B10: =WEEKNUM(A10) -> 2 | C10: 2-20 | E10: Kgs | F10: Per Kg | J10: Water Tanker - Trailers | S10: Free water Ltrs | T10: 175 | U10: =IF(T$14=0,0,T10/T$14) -> 0.073684211 | V10: 0.175 | W10: 174 | X10: =IF(W$14=0,0,W10/W$14) -> 0.0725 | Y10: 0.174 | Z10: 180 | AA10: =IF(Z$14=0,0,Z10/Z$14) -> 0.075031263 | AB10: 0.18 | AD10: =IF(AC$14=0,0,AC10/AC$14) -> 0 | AG10: =IF(AF$14=0,0,AF10/AF$14) -> 0 | AL10: Ground Preparation | AM10: m2 | AO10: Trimming, levelling & compaction of previously excavated ground
A11: 43840 | B11: =WEEKNUM(A11) -> 2 | C11: 2-20 | E11: Loads | F11: Per Load | J11: Fuel Bowsers | S11: Complast Admixture | U11: =IF(T$14=0,0,T11/T$14) -> 0 | X11: =IF(W$14=0,0,W11/W$14) -> 0 | AA11: =IF(Z$14=0,0,Z11/Z$14) -> 0 | AD11: =IF(AC$14=0,0,AC11/AC$14) -> 0 | AG11: =IF(AF$14=0,0,AF11/AF$14) -> 0
A12: 43841 | B12: =WEEKNUM(A12) -> 2 | C12: 2-20 | E12: Litres | F12: Litres | J12: Lube Tankers | S12: Cement | T12: 307 | U12: =IF(T$14=0,0,T12/T$14) -> 0.12926316 | V12: 0.249 | W12: 362 | X12: =IF(W$14=0,0,W12/W$14) -> 0.15083333 | Y12: 0.294 | Z12: 375 | AA12: =IF(Z$14=0,0,Z12/Z$14) -> 0.15631513 | AB12: 0.304 | AD12: =IF(AC$14=0,0,AC12/AC$14) -> 0 | AG12: =IF(AF$14=0,0,AF12/AF$14) -> 0 | AK12: BLOCK DRAINS, 450MM INTERNAL WIDTH - NO REINFORCEMENT - ALL INCLUSIVE RATE
A13: 43842 | B13: =WEEKNUM(A13) -> 3 | C13: 3-20 | E13: N/a | J13: Service Trucks | U13: =IF(T$14=0,0,T13/T$14) -> 0 | X13: =IF(W$14=0,0,W13/W$14) -> 0 | AA13: =IF(Z$14=0,0,Z13/Z$14) -> 0 | AD13: =IF(AC$14=0,0,AC13/AC$14) -> 0 | AG13: =IF(AF$14=0,0,AF13/AF$14) -> 0 | AL13: 1 course full block drain | AM13: Lm | AO13: Rates include, excavation, backfilling & compaction, supply of all labour and materials
A14: 43843 | B14: =WEEKNUM(A14) -> 3 | C14: 3-20 | J14: Luxurious | T14: =SUM(T5:T12) -> 2375 | U14: =SUM(U5:U13) -> 1 | V14: =SUM(V5:V12) -> 1.8 | W14: =SUM(W5:W12) -> 2400 | X14: =SUM(X5:X13) -> 1 | Y14: =SUM(Y5:Y12) -> 1.82 | Z14: =SUM(Z5:Z12) -> 2399 | AA14: =SUM(AA5:AA13) -> 1 | AB14: =SUM(AB5:AB12) -> 1.821 | AC14: =SUM(AC5:AC12) -> 0 | AD14: =SUM(AD5:AD13) -> 0 | AE14: =SUM(AE5:AE12) -> 0 | AF14: =SUM(AF5:AF12) -> 0 | AG14: =SUM(AG5:AG13) -> 0 | AH14: =SUM(AH5:AH12) -> 0 | AL14: 2 courses full block drain | AM14: Lm | AO14: Rates include, excavation, backfilling & compaction, supply of all labour and materials
A15: 43844 | B15: =WEEKNUM(A15) -> 3 | C15: 3-20 | J15: Hiab
A16: 43845 | B16: =WEEKNUM(A16) -> 3 | C16: 3-20 | J16: Bulk Cement Trucks | AK16: BLOCK DRAINS, 450MM INTERNAL WIDTH - REINFORCED - ALL INCLUSIVE RATE
A17: 43846 | B17: =WEEKNUM(A17) -> 3 | C17: 3-20 | J17: Ambulance | AL17: 1 course full block drain | AM17: Lm | AN17: 10100 | AO17: Rates include, excavation, backfilling & compaction, supply of all labour and materials
A18: 43847 | B18: =WEEKNUM(A18) -> 3 | C18: 3-20 | J18: 4 X 4 Suvs | AL18: 2 courses full block drain | AM18: Lm | AN18: 12300 | AO18: Rates include, excavation, backfilling & compaction, supply of all labour and materials
A19: 43848 | B19: =WEEKNUM(A19) -> 3 | C19: 3-20 | J19: Pickups | AL19: 3 courses full block drain | AM19: Lm | AN19: 13500 | AO19: Rates include, excavation, backfilling & compaction, supply of all labour and materials
A20: 43849 | B20: =WEEKNUM(A20) -> 4 | C20: 4-20 | J20: Saloon Cars | AL20: 4 courses full block drain | AM20: Lm | AN20: 15700 | AO20: Rates include, excavation, backfilling & compaction, supply of all labour and materials
A21: 43850 | B21: =WEEKNUM(A21) -> 4 | C21: 4-20 | J21: Motor Bikes
A22: 43851 | B22: =WEEKNUM(A22) -> 4 | C22: 4-20 | J22: Dump Truck - Rigid (Cat) | AK22: PRE-CAST DRAINS - LABOUR ONLY
A23: 43852 | B23: =WEEKNUM(A23) -> 4 | C23: 4-20 | J23: Dump Truck - Articulated (Volvo) | AL23: Casting drain units | AM23: Lm | AN23: 500 | AO23: Rate includes, assembling / striking / cleaning moulds, fixing rebar, pouring concrete, curing concrete, removing units from moulds, stacking precast units and all other handling required in precast yard other than loading onto flatbed
A24: 43853 | B24: =WEEKNUM(A24) -> 4 | C24: 4-20 | J24: Scrapers | AL24: Loading & offloading drain units | AM24: Lm | AN24: 50 | AO24: This is specifically for loading the precast units onto the flatbed in the precast yard and offloading at site. This should be paid for once only. All other handling of precast units in the precast yard is covered under casting drain units
A25: 43854 | B25: =WEEKNUM(A25) -> 4 | C25: 4-20 | J25: Dozers | AL25: Laying & stitching both sides of L drain | AM25: Lm | AN25: 1550 | AO25: Rate includes laying both roadside and kerbside units. Fixing rebar and placing concrete in gap to be stitched.
A26: 43855 | B26: =WEEKNUM(A26) -> 4 | C26: 4-20 | J26: Excavators | AL26: Casting cover slabs | AM26: no. | AN26: 600 | AO26: Rate includes, assembling / striking / cleaning moulds, fixing rebar, pouring concrete, curing concrete, removing units from moulds, stacking precast units and all other handling required in precast yard
A27: 43856 | B27: =WEEKNUM(A27) -> 5 | C27: 5-20 | J27: Hammer Breakers | AL27: Lay cover slabs, including loading & unloading | AM27: no. | AN27: 500
A28: 43857 | B28: =WEEKNUM(A28) -> 5 | C28: 5-20 | J28: Payloaders
A29: 43858 | B29: =WEEKNUM(A29) -> 5 | C29: 5-20 | J29: Graders | AK29: CULVERTS - ALL INCLUSIVE RATE
A30: 43859 | B30: =WEEKNUM(A30) -> 5 | C30: 5-20 | J30: Dumpers | AL30: 450mm Diam. Culverts | AM30: Lm | AO30: Rates include, excavation, backfilling & compaction, supply of all labour and materials
A31: 43860 | B31: =WEEKNUM(A31) -> 5 | C31: 5-20 | J31: Piling Rigs | AL31: 600mm Diam. Culverts | AM31: Lm | AN31: 26500 | AO31: Rates include, excavation, backfilling & compaction, supply of all labour and materials
A32: 43861 | B32: =WEEKNUM(A32) -> 5 | C32: 5-20 | J32: Compactors | AL32: 750mm Diam. Culverts | AM32: Lm | AN32: 32000 | AO32: Rates include, excavation, backfilling & compaction, supply of all labour and materials
A33: 43862 | B33: =WEEKNUM(A33) -> 5 | C33: 5-20 | J33: Rollers | AL33: 900mm Diam. Culverts | AM33: Lm | AN33: 42000 | AO33: Rates include, excavation, backfilling & compaction, supply of all labour and materials
A34: 43863 | B34: =WEEKNUM(A34) -> 6 | C34: 6-20 | J34: Vibrating Plates | AL34: Supply & place concrete in culvert headwalls, wingwalls and aprons, including formwork | AM34: m3 | AN34: 31500 | AO34: Rates include, excavation, backfilling & compaction, supply of all labour and materials
A35: 43864 | B35: =WEEKNUM(A35) -> 6 | C35: 6-20 | J35: Cranes - Mobile
A36: 43865 | B36: =WEEKNUM(A36) -> 6 | C36: 6-20 | J36: Cranes - Tower | AK36: DEMOLITION OF EXISTING DRAINS / CULVERTS
A37: 43866 | B37: =WEEKNUM(A37) -> 6 | C37: 6-20 | J37: Slip Form Paver (Gomaco) | AL37: Drainage demolition - Labour only | AM37: Lm | AN37: 300
A38: 43867 | B38: =WEEKNUM(A38) -> 6 | C38: 6-20 | J38: Concrete Batching Plants (Static Type) - Wetmix | AL38: Culvert Demolition, including removal | AM38: m3 | AN38: 1800
A39: 43868 | B39: =WEEKNUM(A39) -> 6 | C39: 6-20 | J39: Concrete Batching Plants (Static Type) - Drymix | AL39: Concrete demolition - Labour only | AM39: m3 | AN39: 2750
A40: 43869 | B40: =WEEKNUM(A40) -> 6 | C40: 6-20 | J40: Concrete Mixer - Mobile (Carmixer Type) | AL40: Drainage Cleaning | AM40: Lm | AN40: 200
A41: 43870 | B41: =WEEKNUM(A41) -> 7 | C41: 7-20 | J41: Concrete Mixer - Small (Winget Type) | AL41: Culvert Cleaning | AM41: Lm | AN41: 200
A42: 43871 | B42: =WEEKNUM(A42) -> 7 | C42: 7-20 | J42: Concrete Pump - Truck Mounted
A43: 43872 | B43: =WEEKNUM(A43) -> 7 | C43: 7-20 | J43: Concrete Pump - Static | AK43: CONCRETE BATCHING
A44: 43873 | B44: =WEEKNUM(A44) -> 7 | C44: 7-20 | J44: Concrete Mixer Trucks | AL44: Batching of Grade 25 Concrete | AM44: m3 | AN44: 400 | AO44: Rate is for all labour required to operate static batching plant in precast yard provided by PW, includes handling of all raw materials and loading concrete onto mixer trucks. PW to provide all materials, payloader for loading aggregates, water tanker if necessary for water.
A45: 43874 | B45: =WEEKNUM(A45) -> 7 | C45: 7-20 | J45: Vibrating Poker Engines | AK45: CONCRETE SUPPLY & PLACEMENT
A46: 43875 | B46: =WEEKNUM(A46) -> 7 | C46: 7-20 | J46: Concrete Power Float Machines | AL46: Supply and place Gr. 25 concrete to headwalls, wingwalls and aprons etc into existing formwork | AM46: m3 | AO46: Rate is for supplying and mixing all concrete materials, placing, vibrating and finishing concrete within formwork containing reinforcement bars already fixed in place
A47: 43876 | B47: =WEEKNUM(A47) -> 7 | C47: 7-20 | J47: Asphalt Batching Plant | AL47: Supply and place Gr. 25 concrete to headwalls, wingwalls and aprons etc including supplying & installing formwork | AM47: m3 | AO47: Rate is for supplying and mixing all concrete materials, placing, vibrating and finishing concrete including supplying and fixing all formwork
A48: 43877 | B48: =WEEKNUM(A48) -> 8 | C48: 8-20 | J48: Heating Plant
A49: 43878 | B49: =WEEKNUM(A49) -> 8 | C49: 8-20 | J49: Tar Sprayer - Truck | AK49: CONCRETE PLACEMENT - LABOUR ONLY
A50: 43879 | B50: =WEEKNUM(A50) -> 8 | C50: 8-20 | J50: Tar Sprayer - Trailer Only | AL50: Blinding Concrete | AM50: m3 | AN50: 125
A51: 43880 | B51: =WEEKNUM(A51) -> 8 | C51: 8-20 | J51: Planing Machines | AL51: Mass concrete | AM51: m3 | AN51: 250
A52: 43881 | B52: =WEEKNUM(A52) -> 8 | C52: 8-20 | J52: Asphalt Finishers (Pavers) | AL52: Reinforced concrete placement - General | AM52: m3 | AN52: 300 | AO52: Rate is for placing, vibrating and finishing concrete within formwork containing reinforcement bars already fixed in place
A53: 43882 | B53: =WEEKNUM(A53) -> 8 | C53: 8-20 | J53: Asphalt Cutting Machines | AL53: Reinforced concrete placement - Bridge Substructure - In-situ (not including filling of piles) | AM53: m3 | AO53: Rate is for placing, vibrating and finishing concrete within formwork containing reinforcement bars already fixed in place
A54: 43883 | B54: =WEEKNUM(A54) -> 8 | C54: 8-20 | J54: Farm Tractors | AL54: Reinforced concrete placement - Bridge Superstructure - In-situ | AM54: m3 | AO54: Rate is for placing, vibrating and finishing concrete within formwork containing reinforcement bars already fixed in place
A55: 43884 | B55: =WEEKNUM(A55) -> 9 | C55: 9-20 | J55: Road Brushes | AL55: Pre-casting of main longitudinal bridge beams | AM55: m3 | AO55: Rate is for placing, vibrating and finishing concrete within formwork containing reinforcement bars already fixed in place
A56: 43885 | B56: =WEEKNUM(A56) -> 9 | C56: 9-20 | J56: Chiiping Spreaders | AL56: Pre-casting of bridge deck slabs (2.1m X 1.4 X 0.07) | AM56: no. | AN56: 750 | AO56: Rate includes, assembling / striking / cleaning moulds, fixing rebar, pouring concrete, curing concrete, removing units from moulds, stacking precast units and all other handling required in precast yard
A57: 43886 | B57: =WEEKNUM(A57) -> 9 | C57: 9-20 | J57: Generators | AL57: Pre-casting of bridge parapet walls (2.1m long) | AM57: no. | AN57: 2100 | AO57: Rate includes, assembling / striking / cleaning moulds, fixing rebar, pouring concrete, curing concrete, removing units from moulds, stacking precast units and all other handling required in precast yard
A58: 43887 | B58: =WEEKNUM(A58) -> 9 | C58: 9-20 | J58: Compressors | AL58: Placement and fixing of pre-cast bridge parapet walls (2.1m long) | AM58: no. | AO58: Rate includes loading the precast units onto the flatbed in the precast yard and offloading at site. This should be paid for once only. All other handling of precast units in the precast yard is covered under casting pre-cast units
A59: 43888 | B59: =WEEKNUM(A59) -> 9 | C59: 9-20 | J59: Cement Blowers
A60: 43889 | B60: =WEEKNUM(A60) -> 9 | C60: 9-20 | J60: Fuel Meter Pumps | AK60: REINFORCEMENT - LABOUR ONLY
A61: 43890 | B61: =WEEKNUM(A61) -> 9 | C61: 9-20 | J61: Weigh Bridges | AL61: Cutting & bending | AM61: ton | AN61: 9000
A62: 43891 | B62: =WEEKNUM(A62) -> 10 | C62: 10-20 | J62: Telehandlers / Fork Lifts | AL62: Fixing | AM62: ton | AN62: 6000
A63: 43892 | B63: =WEEKNUM(A63) -> 10 | C63: 10-20 | J63: Block Moulding Machines
A64: 43893 | B64: =WEEKNUM(A64) -> 10 | C64: 10-20 | J64: Welding Sets | AK64: REINFORCEMENT - ALL INCLUSIVE RATE
A65: 43894 | B65: =WEEKNUM(A65) -> 10 | C65: 10-20 | J65: Bending & Cutting Machines | AL65: Supply, cutting, bending & fixing | AM65: ton | AO65: Rate includes, material supply (including tie wire), delivery, cutting, bending and fixing.
A66: 43895 | B66: =WEEKNUM(A66) -> 10 | C66: 10-20 | J66: Turning Machines
A67: 43896 | B67: =WEEKNUM(A67) -> 10 | C67: 10-20 | J67: Sand Blaster
A68: 43897 | B68: =WEEKNUM(A68) -> 10 | C68: 10-20 | J68: Washing Machines | AK68: FORMWORK - LABOUR ONLY
A69: 43898 | B69: =WEEKNUM(A69) -> 11 | C69: 11-20 | J69: Grass Cutting Machines | AL69: Placing formwork - generally | AM69: m2 | AN69: 750
A70: 43899 | B70: =WEEKNUM(A70) -> 11 | C70: 11-20 | J70: Line Painting Machines
A71: 43900 | B71: =WEEKNUM(A71) -> 11 | C71: 11-20 | J71: Mobile Lighting Sets | AK71: STONE PITCHING
A72: 43901 | B72: =WEEKNUM(A72) -> 11 | C72: 11-20 | J72: Water Pumps | AL72: 150mm Stone pitching including trimming, levelling & preparation of ground surface. Materials supplied by PW | AM72: m2 | AN72: 750
A73: 43902 | B73: =WEEKNUM(A73) -> 11 | C73: 11-20 | J73: Crusher - Static | AL73: 150mm Stone pitching. Materials by subcontractor - All in rate | AM73: m2 | AN73: 4200
A74: 43903 | B74: =WEEKNUM(A74) -> 11 | C74: 11-20 | J74: Crusher - Mobile
A75: 43904 | B75: =WEEKNUM(A75) -> 11 | C75: 11-20 | J75: Mobile Screen | AK75: KERBING
A76: 43905 | B76: =WEEKNUM(A76) -> 12 | C76: 12-20 | J76: Vertical Shaft Impactor (Vsi) | AL76: Removal of existing kerbs | AM76: Lm | AO76: Rate includes removal of base & haunch and loading onto trucks for disposal.
A77: 43906 | B77: =WEEKNUM(A77) -> 12 | C77: 12-20 | J77: Crawler Drill | AL77: Casting kerbs & handling | AM77: Lm | AN77: 350
A78: 43907 | B78: =WEEKNUM(A78) -> 12 | C78: 12-20 | AL78: Excavate, blind, lay & haunch | AM78: Lm | AN78: 900
A79: 43908 | B79: =WEEKNUM(A79) -> 12 | C79: 12-20
A80: 43909 | B80: =WEEKNUM(A80) -> 12 | C80: 12-20 | AK80: BLOCKS - CASTING
A81: 43910 | B81: =WEEKNUM(A81) -> 12 | C81: 12-20 | AL81: 6" Blocks, cast, water & stack - Labour only | AM81: no. | AN81: 30
A82: 43911 | B82: =WEEKNUM(A82) -> 12 | C82: 12-20 | AL82: 9" Blocks, cast, water & stack - Labour only | AM82: no. | AN82: 50
A83: 43912 | B83: =WEEKNUM(A83) -> 13 | C83: 13-20
A84: 43913 | B84: =WEEKNUM(A84) -> 13 | C84: 13-20 | AK84: SANDCRETE BLOCKS - LAYING - LABOUR ONLY
A85: 43914 | B85: =WEEKNUM(A85) -> 13 | C85: 13-20 | AL85: Laying 6" blocks (labour only) | AM85: m2 | AN85: 500
A86: 43915 | B86: =WEEKNUM(A86) -> 13 | C86: 13-20 | AL86: Laying 9" blocks (labour only) | AM86: m2 | AN86: 700
A87: 43916 | B87: =WEEKNUM(A87) -> 13 | C87: 13-20 | AL87: Filling of block with concrete | AM87: m2 | AN87: 300
A88: 43917 | B88: =WEEKNUM(A88) -> 13 | C88: 13-20
A89: 43918 | B89: =WEEKNUM(A89) -> 13 | C89: 13-20 | AK89: SANDCRETE BLOCKS - ALL INCLUSIVE RATE
A90: 43919 | B90: =WEEKNUM(A90) -> 14 | C90: 14-20 | AL90: Supply & Laying 6" blocks | AM90: m2 | AO90: Rate includes supply & mixing of all mortar
A91: 43920 | B91: =WEEKNUM(A91) -> 14 | C91: 14-20 | AL91: Supply & Laying 9" blocks | AM91: m2 | AO91: Rate includes supply & mixing of all mortar
A92: 43921 | B92: =WEEKNUM(A92) -> 14 | C92: 14-20 | AL92: Filling of block with concrete | AM92: m2 | AO92: Rate includes supply & mixing of all concrete
A93: 43922 | B93: =WEEKNUM(A93) -> 14 | C93: 14-20
A94: 43923 | B94: =WEEKNUM(A94) -> 14 | C94: 14-20 | AK94: INTERLOCKING CONCRETE PAVING - 80MM THK
A95: 43924 | B95: =WEEKNUM(A95) -> 14 | C95: 14-20 | AL95: Place Interlocking Tiles and bedding sand, including filling joints with sand - Labour only | AM95: m2 | AN95: 500
A96: 43925 | B96: =WEEKNUM(A96) -> 14 | C96: 14-20 | AL96: Supply & place Interlocking Tiles - All inclusive rate including supply of bedding sand | AM96: m2 | AN96: 4500
A97: 43926 | B97: =WEEKNUM(A97) -> 15 | C97: 15-20
A98: 43927 | B98: =WEEKNUM(A98) -> 15 | C98: 15-20 | AK98: MISCELLANEOUS OTHERS
A99: 43928 | B99: =WEEKNUM(A99) -> 15 | C99: 15-20 | AL99: Grassing - including supply & placement of topsoil | AM99: m2 | AN99: 500
A100: 43929 | B100: =WEEKNUM(A100) -> 15 | C100: 15-20 | AL100: Plastering - Labour only | AM100: m2 | AN100: 500
...
